Workbook

Sheet Dashboard
B2: Planung Stand:
B4: Projekt:
B6: Fördergeber:
B7: Förderprogramm:
B8: Projektträger:
B10: beantragte Fördersumme:
B12: Laufzeitbeginn
B13: Laufzeitende

Sheet Nav
A1: Navigation
H2: Laufzeitbeginn | I2: 45047 | K2: 1. Jahr | O2: =IF(O3="","","2. Jahr") | S2: =IF(S3="","","3. Jahr") | W2: =IF(W3="","","4. Jahr")
C3: Durchführbarkeitsstudie "BioInk" | H3: Laufzeitende | I3: 45289 | K3: =YEAR(L4) -> 2023 | O3: =IF(MONTH(N4)<12,"",IF(YEAR(N4)=YEAR($I$3),"",YEAR(P4))) | S3: =IF(R4="","",IF(MONTH(R4)<12,"",YEAR(T4))) | W3: =IF(V4="","",IF(MONTH(V4)<12,"",YEAR(X4)))
B4: Projekt: | K4: von | L4: =I2 -> 45047 | M4: bis | N4: =DATE(YEAR(I2),12,31) -> 45291 | O4: von | P4: =IF(MONTH(N4)<12,"",IF(YEAR(N4)=YEAR($I$3),"",N4+1)) | Q4: bis | R4: =IF(P4="","",IF(MONTH(N4)<12,"",(IF(YEAR(P4)=YEAR($I$3),$I$3,DATE(YEAR(P4),12,31))))) | S4: von | T4: =IF(R4="","",IF(MONTH(R4)<12,"",R4+1)) | U4: bis | V4: =IF(T4="","",IF(MONTH(R4)<12,"",(IF(YEAR(T4)=YEAR($I$3),$I$3,DATE(YEAR(T4),12,31))))) | W4: von | X4: =IF(V4="","",IF(MONTH(V4)<12,"",V4+1)) | Y4: bis | Z4: =IF(V4="","",IF(MONTH(V4)<12,"",(IF(YEAR(X4)=YEAR($I$3),$I$3,DATE(YEAR(X4),12,31)))))
J5: Eigenanteil: | K5: 0.3 | O5: =K5 -> 0.3 | S5: =O5 -> 0.3 | W5: =IF(W3="-","-",S5) -> 0.3
B6: FKZ: | C6: DS200424 | J6: Bundesanteil: | K6: =1-K5 -> 0.7 | O6: =1-O5 -> 0.7 | S6: =1-S5 -> 0.7 | W6: =IF(W3="-","-",1-W5) -> 0.7
B7: Unternehmen | C7: Tippl GmbH
B8: Anschrift | C8: Im Gehrn 10, 71737 Kirchberg a.d.Murr | J8: Fördersumme PLAN: | K8: =E20 -> 53855 | O8: ='Planung Personal'!AA35 -> 0 | S8: ='Planung Personal'!AA49 -> 0 | W8: ='Planung Personal'!AA63 -> 0 | AA8: =SUM(K8:Z8) -> 53855
B9: Ansprechpartner | C9: Mario Tippl | J9: bisher abgerechet: | K9: ='Ermittl.-Stunden J1'!AF31 -> 54227.311 | O9: ='Auswertung J2'!R66 -> 0 | S9: ='Auswertung J3'!R66 -> 0 | W9: ='Auswertung J4'!R66 -> 0 | AA9: =SUM(K9:Z9) -> 54227.311
B10: Telefon | J10: Differenz: | K10: =K8-K9 -> -372.31087 | O10: =O8-O9 -> 0 | S10: =S8-S9 -> 0 | W10: =W8-W9 -> 0 | AA10: =SUM(K10:Z10) -> -372.31087
B11: Bankverb.
B12: IBAN | I12: Zuschlagsatz: | L12: technisch | M12: 0.2842
B13: BIC | L13: nicht-technisch | M13: 0.2988
I14: Fördermittelabruf
C15: Zuwendungen pro Haushaltsjahr | I15: Plan-Abrechnung | N15: Zuwendungen
B16: =L4 -> 45047 | C16: 20197 | H16: =$L$4 -> 45047 | I16: =E20 -> 53855 | N16: abgerufen | P16: =AA9 -> 54227.311
B17: =IF(C17>0,B16+365,$P$4) -> 45412 | C17: 33658 | H17: =$P$4 | I17: ='Planung Personal'!AA35 -> 0 | N17: verfügbar | P17: =E20-P18-AA9 -> -5757.8109
B18: =IF(C18>0,B17+365,$T$4) | H18: =$T$4 | I18: ='Planung Personal'!AA49 -> 0 | N18: gesperrt | P18: =E20*0.1 -> 5385.5
B19: =IF(C19>0,B18+365,$X$4) | H19: =$X$4 | I19: ='Planung Personal'!AA63 -> 0
C20: Fördersumme gesamt: | E20: =SUM(C16:F19) -> 53855 | I20: =SUM(I16:L19) -> 53855
X22: Projektträger: EURONORM
B23: Personalkosten | I23: Soll-Ist- Auswertung | X23: Anschrift | Z23: Straße | AA23: Stralauer Platz 34
I24: =B16 -> 45047 | Z24: PLZ Ort | AA24: 10243 | AB24: Berlin
B25: Ermittlung Jahresstundennsatz
X26: Ansprechpartner Technik
B27: =B16 -> 45047 | C27: =B17 -> 45412 | D27: =B18 | E27: =B19 | I27: =B17 -> 45412 | Y27: Name:
Y28: E-Mail:
Y29: Telefon:
B31: Stundennachweise | I31: =B18 | X31: Ansprechpartner BWL
B32: Tippl, Mario | C32: =B16 -> 45047 | D32: =B17 -> 45412 | E32: =B18 | F32: =B19 | Y32: Name: | Z32: Dr. Christian Liebold
B33: Socha, Pawel | C33: =B16 -> 45047 | D33: =B17 -> 45412 | E33: =B18 | F33: =B19 | Y33: E-Mail:
B34: Tippl, Karen | C34: =B16 -> 45047 | D34: =B17 -> 45412 | E34: =B18 | F34: =B19 | Y34: Telefon:
B35: MA 4 | C35: =B16 -> 45047 | D35: =B17 -> 45412 | E35: =B18 | F35: =B19 | I35: =B19
B36: MA 5 | C36: =B16 -> 45047 | D36: =B17 -> 45412 | E36: =B18 | F36: =B19

Sheet AP Übersicht
B1: =Nav!C3 -> Durchführbarkeitsstudie "BioInk"
B2: =Nav!C7 -> Tippl GmbH
A4: Arbeitspakete | D4: =Nav!$B$16 -> 45047 | AI4: =Nav!$B$17 -> 45412 | BE4: =Nav!$B$18 | CA4: Arbeitspakete
D5: Realisierungszeitraum | G5: Aufwand NWM | V5: =D4 -> 45047 | AI5: Realisierungszeitraum | AL5: Aufwand NWM | AR5: =AI4 -> 45412 | BE5: Realisierungszeitraum | BH5: Aufwand NWM | BN5: =BE4
A6: Nr. | B6: Arbeitspaket | C6: T | D6: von | E6: bis | F6: Monate | G6: =Nav!$B$32 -> Tippl, Mario | K6: =Nav!$B$33 -> Socha, Pawel | O6: =Nav!$B$34 -> Tippl, Karen | S6: =Nav!$B$35 -> MA 4 | T6: =Nav!$B$36 -> MA 5 | U6: PM | V6: =DATE(YEAR(Nav!$L$4),1,1) -> 44927 | W6: =V6+31 -> 44958 | X6: =IF((MOD(YEAR(W6),4)=0)-(MOD(YEAR(W6),100)=0)+(MOD(YEAR(W6),400)=0)=0,W6+28,W6+29) -> 44986 | Y6: =X6+31 -> 45017 | Z6: =Y6+30 -> 45047 | AA6: =Z6+31 -> 45078 | AB6: =AA6+30 -> 45108 | AC6: =AB6+31 -> 45139 | AD6: =AC6+31 -> 45170 | AE6: =AD6+30 -> 45200 | AF6: =AE6+31 -> 45231 | AG6: =AF6+30 -> 45261 | AI6: von | AJ6: bis | AK6: Monate | AL6: =Nav!$B$32 -> Tippl, Mario | AM6: =Nav!$B$33 -> Socha, Pawel | AN6: =Nav!$B$34 -> Tippl, Karen | AO6: =Nav!$B$35 -> MA 4 | AP6: =Nav!$B$36 -> MA 5 | AQ6: PM | AR6: =AR5 -> 45412 | AS6: =AR6+31 -> 45443 | AT6: =IF((MOD(YEAR(AS6),4)=0)-(MOD(YEAR(AS6),100)=0)+(MOD(YEAR(AS6),400)=0)=0,AS6+28,AS6+29) -> 45472 | AU6: =AT6+31 -> 45503 | AV6: =AU6+30 -> 45533 | AW6: =AV6+31 -> 45564 | AX6: =AW6+30 -> 45594 | AY6: =AX6+31 -> 45625 | AZ6: =AY6+31 -> 45656 | BA6: =AZ6+30 -> 45686 | BB6: =BA6+31 -> 45717 | BC6: =BB6+30 -> 45747 | BE6: von | BF6: bis | BG6: Monate | BH6: =Nav!$B$32 -> Tippl, Mario | BI6: =Nav!$B$33 -> Socha, Pawel | BJ6: =Nav!$B$34 -> Tippl, Karen | BK6: =Nav!$B$35 -> MA 4 | BL6: =Nav!$B$36 -> MA 5 | BM6: PM | BN6: =BN5 | BO6: =BN6+31 -> #VALUE! | BP6: =IF((MOD(YEAR(BO6),4)=0)-(MOD(YEAR(BO6),100)=0)+(MOD(YEAR(BO6),400)=0)=0,BO6+28,BO6+29) -> #VALUE! | BQ6: =BP6+31 -> #VALUE! | BR6: =BQ6+30 -> #VALUE! | BS6: =BR6+31 -> #VALUE! | BT6: =BS6+30 -> #VALUE! | BU6: =BT6+31 -> #VALUE! | BV6: =BU6+31 -> #VALUE! | BW6: =BV6+30 -> #VALUE! | BX6: =BW6+31 -> #VALUE! | BY6: =BX6+30 -> #VALUE! | CA6: Nr. | CB6: Arbeitspaket
G7: ='Planung Personal'!$T$9/12 -> 10000 | H7: h | I7: ZA | J7: offen | K7: ='Planung Personal'!$T$11/12 -> 3225 | L7: h | M7: ZA | N7: offen | O7: ='Planung Personal'!$T$13/12 -> 2975 | P7: h | Q7: ZA | R7: offen | S7: ='Planung Personal'!$T$15/12 -> 0 | T7: ='Planung Personal'!$T$17/12 -> 0 | AL7: ='Planung Personal'!$T$9/12 -> 10000 | AM7: ='Planung Personal'!$T$11/12 -> 3225 | AN7: ='Planung Personal'!$T$13/12 -> 2975 | AO7: ='Planung Personal'!$T$15/12 -> 0 | AP7: ='Planung Personal'!$T$17/12 -> 0 | BH7: ='Planung Personal'!$T$9/12 -> 10000 | BI7: ='Planung Personal'!$T$11/12 -> 3225 | BJ7: ='Planung Personal'!$T$13/12 -> 2975 | BK7: ='Planung Personal'!$T$15/12 -> 0 | BL7: ='Planung Personal'!$T$17/12 -> 0
A8: 1 | B8: Analyse Stand der Technik | D8: 45047 | E8: 45077 | F8: =IF(D8="","",ROUND((E8-D8)/30,0)) -> 1 | G8: 0.5 | H8: =$G8*'Ermittl.-Stunden J1'!$T$5 -> 86.666667 | I8: =SUMIF('Tippl M. J1'!$B$17:$AK$511,'AP Übersicht'!$A8,'Tippl M. J1'!$AK$17:$AK$511) -> 86.67 | J8: =H8-I8 -> -0.0033333333 | L8: =$K8*'Ermittl.-Stunden J1'!$T$15 -> 0 | M8: =SUMIF('Socha J1'!$B$17:$AK$511,'AP Übersicht'!$A8,'Socha J1'!$AK$17:$AK$511) -> 0 | N8: =L8-M8 -> 0 | P8: =$O8*'Ermittl.-Stunden J1'!$T$25 -> 0 | Q8: =SUMIF('Tippl K. J1'!$B$17:$AK$511,'AP Übersicht'!$A8,'Tippl K. J1'!$AK$17:$AK$511) -> 0 | R8: =P8-Q8 -> 0 | U8: =SUM(G8,K8,O8) -> 0.5 | V8: =IF(AND(V$6>=$D8,V$6<=$E8),"x","") | W8: =IF(AND(W$6>=$D8,W$6<=$E8),"x","") | X8: =IF(AND(X$6>=$D8,X$6<=$E8),"x","") | Y8: =IF(AND(Y$6>=$D8,Y$6<=$E8),"x","") | Z8: =IF(AND(Z$6>=$D8,Z$6<=$E8),"x","") -> x | AA8: =IF(AND(AA$6>=$D8,AA$6<=$E8),"x","") | AB8: =IF(AND(AB$6>=$D8,AB$6<=$E8),"x","") | AC8: =IF(AND(AC$6>=$D8,AC$6<=$E8),"x","") | ... AG8: =IF(AND(AG$6>=$D8,AG$6<=$E8),"x","") | AK8: =IF(AI8="","",ROUND((AJ8-AI8)/30,0)) | AQ8: =SUM(AL8:AP8) -> 0 | AR8: =IF(AND(AR$6>=$AI8,AR$6<=$AJ8),"x","") | AS8: =IF(AND(AS$6>=$AI8,AS$6<=$AJ8),"x","") | AT8: =IF(AND(AT$6>=$AI8,AT$6<=$AJ8),"x","") | AU8: =IF(AND(AU$6>=$AI8,AU$6<=$AJ8),"x","") | AV8: =IF(AND(AV$6>=$AI8,AV$6<=$AJ8),"x","") | AW8: =IF(AND(AW$6>=$AI8,AW$6<=$AJ8),"x","") | AX8: =IF(AND(AX$6>=$AI8,AX$6<=$AJ8),"x","") | AY8: =IF(AND(AY$6>=$AI8,AY$6<=$AJ8),"x","") | ... BC8: =IF(AND(BC$6>=$AI8,BC$6<=$AJ8),"x","") | BG8: =IF(BE8="","",ROUND((BF8-BE8)/30,0)) | BM8: =SUM(BH8:BL8) -> 0 | BN8: =IF(AND(BN$6>=$BE8,BN$6<=$BF8),"x","") -> x | BO8: =IF(AND(BO$6>=$BE8,BO$6<=$BF8),"x","") -> #VALUE! | BP8: =IF(AND(BP$6>=$BE8,BP$6<=$BF8),"x","") -> #VALUE! | BQ8: =IF(AND(BQ$6>=$BE8,BQ$6<=$BF8),"x","") -> #VALUE! | BR8: =IF(AND(BR$6>=$BE8,BR$6<=$BF8),"x","") -> #VALUE! | BS8: =IF(AND(BS$6>=$BE8,BS$6<=$BF8),"x","") -> #VALUE! | BT8: =IF(AND(BT$6>=$BE8,BT$6<=$BF8),"x","") -> #VALUE! | BU8: =IF(AND(BU$6>=$BE8,BU$6<=$BF8),"x","") -> #VALUE! | ... BY8: =IF(AND(BY$6>=$BE8,BY$6<=$BF8),"x","") -> #VALUE! | CA8: =A8 -> 1 | CB8: =B8 -> Analyse Stand der Technik
A9: 2.1 | D9: 45047 | E9: 45077 | F9: =IF(D9="","",ROUND((E9-D9)/30,0)) -> 1 | H9: =$G9*'Ermittl.-Stunden J1'!$T$5 -> 0 | I9: =SUMIF('Tippl M. J1'!$B$17:$AK$511,'AP Übersicht'!$A9,'Tippl M. J1'!$AK$17:$AK$511) -> 0 | J9: =H9-I9 -> 0 | L9: =$K9*'Ermittl.-Stunden J1'!$T$15 -> 0 | M9: =SUMIF('Socha J1'!$B$17:$AK$511,'AP Übersicht'!$A9,'Socha J1'!$AK$17:$AK$511) -> 0 | N9: =L9-M9 -> 0 | P9: =$O9*'Ermittl.-Stunden J1'!$T$25 -> 0 | Q9: =SUMIF('Tippl K. J1'!$B$17:$AK$511,'AP Übersicht'!$A9,'Tippl K. J1'!$AK$17:$AK$511) -> 0 | R9: =P9-Q9 -> 0 | U9: =SUM(G9,K9,O9) -> 0 | V9: =IF(AND(V$6>=$D9,V$6<=$E9),"x","") | W9: =IF(AND(W$6>=$D9,W$6<=$E9),"x","") | X9: =IF(AND(X$6>=$D9,X$6<=$E9),"x","") | Y9: =IF(AND(Y$6>=$D9,Y$6<=$E9),"x","") | Z9: =IF(AND(Z$6>=$D9,Z$6<=$E9),"x","") -> x | AA9: =IF(AND(AA$6>=$D9,AA$6<=$E9),"x","") | AB9: =IF(AND(AB$6>=$D9,AB$6<=$E9),"x","") | AC9: =IF(AND(AC$6>=$D9,AC$6<=$E9),"x","") | ... AG9: =IF(AND(AG$6>=$D9,AG$6<=$E9),"x","") | AK9: =IF(AI9="","",ROUND((AJ9-AI9)/30,0)) | AQ9: =SUM(AL9:AP9) -> 0 | AR9: =IF(AND(AR$6>=$AI9,AR$6<=$AJ9),"x","") | AS9: =IF(AND(AS$6>=$AI9,AS$6<=$AJ9),"x","") | AT9: =IF(AND(AT$6>=$AI9,AT$6<=$AJ9),"x","") | AU9: =IF(AND(AU$6>=$AI9,AU$6<=$AJ9),"x","") | AV9: =IF(AND(AV$6>=$AI9,AV$6<=$AJ9),"x","") | AW9: =IF(AND(AW$6>=$AI9,AW$6<=$AJ9),"x","") | AX9: =IF(AND(AX$6>=$AI9,AX$6<=$AJ9),"x","") | AY9: =IF(AND(AY$6>=$AI9,AY$6<=$AJ9),"x","") | ... BC9: =IF(AND(BC$6>=$AI9,BC$6<=$AJ9),"x","") | BG9: =IF(BE9="","",ROUND((BF9-BE9)/30,0)) | BM9: =SUM(BH9:BL9) -> 0 | BN9: =IF(AND(BN$6>=$BE9,BN$6<=$BF9),"x","") -> x | BO9: =IF(AND(BO$6>=$BE9,BO$6<=$BF9),"x","") -> #VALUE! | BP9: =IF(AND(BP$6>=$BE9,BP$6<=$BF9),"x","") -> #VALUE! | BQ9: =IF(AND(BQ$6>=$BE9,BQ$6<=$BF9),"x","") -> #VALUE! | BR9: =IF(AND(BR$6>=$BE9,BR$6<=$BF9),"x","") -> #VALUE! | BS9: =IF(AND(BS$6>=$BE9,BS$6<=$BF9),"x","") -> #VALUE! | BT9: =IF(AND(BT$6>=$BE9,BT$6<=$BF9),"x","") -> #VALUE! | BU9: =IF(AND(BU$6>=$BE9,BU$6<=$BF9),"x","") -> #VALUE! | ... BY9: =IF(AND(BY$6>=$BE9,BY$6<=$BF9),"x","") -> #VALUE! | CA9: =A9 -> 2.1 | CB9: =B9 -> 0
A10: 2.2 | B10: Analyse Marktpotential/Patentprüfung | D10: 45047 | E10: 45077 | F10: =IF(D10="","",ROUND((E10-D10)/30,0)) -> 1 | H10: =$G10*'Ermittl.-Stunden J1'!$T$5 -> 0 | I10: =SUMIF('Tippl M. J1'!$B$17:$AK$511,'AP Übersicht'!$A10,'Tippl M. J1'!$AK$17:$AK$511) -> 0 | J10: =H10-I10 -> 0 | K10: 0.5 | L10: =$K10*'Ermittl.-Stunden J1'!$T$15 -> 86.666667 | M10: =SUMIF('Socha J1'!$B$17:$AK$511,'AP Übersicht'!$A10,'Socha J1'!$AK$17:$AK$511) -> 86.67 | N10: =L10-M10 -> -0.0033333333 | P10: =$O10*'Ermittl.-Stunden J1'!$T$25 -> 0 | Q10: =SUMIF('Tippl K. J1'!$B$17:$AK$511,'AP Übersicht'!$A10,'Tippl K. J1'!$AK$17:$AK$511) -> 86.67 | R10: =P10-Q10 -> -86.67 | U10: =SUM(G10,K10,O10) -> 0.5 | V10: =IF(AND(V$6>=$D10,V$6<=$E10),"x","") | W10: =IF(AND(W$6>=$D10,W$6<=$E10),"x","") | X10: =IF(AND(X$6>=$D10,X$6<=$E10),"x","") | Y10: =IF(AND(Y$6>=$D10,Y$6<=$E10),"x","") | Z10: =IF(AND(Z$6>=$D10,Z$6<=$E10),"x","") -> x | AA10: =IF(AND(AA$6>=$D10,AA$6<=$E10),"x","") | AB10: =IF(AND(AB$6>=$D10,AB$6<=$E10),"x","") | AC10: =IF(AND(AC$6>=$D10,AC$6<=$E10),"x","") | ... AG10: =IF(AND(AG$6>=$D10,AG$6<=$E10),"x","") | AK10: =IF(AI10="","",ROUND((AJ10-AI10)/30,0)) | AQ10: =SUM(AL10:AP10) -> 0 | AR10: =IF(AND(AR$6>=$AI10,AR$6<=$AJ10),"x","") | AS10: =IF(AND(AS$6>=$AI10,AS$6<=$AJ10),"x","") | AT10: =IF(AND(AT$6>=$AI10,AT$6<=$AJ10),"x","") | AU10: =IF(AND(AU$6>=$AI10,AU$6<=$AJ10),"x","") | AV10: =IF(AND(AV$6>=$AI10,AV$6<=$AJ10),"x","") | AW10: =IF(AND(AW$6>=$AI10,AW$6<=$AJ10),"x","") | AX10: =IF(AND(AX$6>=$AI10,AX$6<=$AJ10),"x","") | AY10: =IF(AND(AY$6>=$AI10,AY$6<=$AJ10),"x","") | ... BC10: =IF(AND(BC$6>=$AI10,BC$6<=$AJ10),"x","") | BG10: =IF(BE10="","",ROUND((BF10-BE10)/30,0)) | BM10: =SUM(BH10:BL10) -> 0 | BN10: =IF(AND(BN$6>=$BE10,BN$6<=$BF10),"x","") -> x | BO10: =IF(AND(BO$6>=$BE10,BO$6<=$BF10),"x","") -> #VALUE! | BP10: =IF(AND(BP$6>=$BE10,BP$6<=$BF10),"x","") -> #VALUE! | BQ10: =IF(AND(BQ$6>=$BE10,BQ$6<=$BF10),"x","") -> #VALUE! | BR10: =IF(AND(BR$6>=$BE10,BR$6<=$BF10),"x","") -> #VALUE! | BS10: =IF(AND(BS$6>=$BE10,BS$6<=$BF10),"x","") -> #VALUE! | BT10: =IF(AND(BT$6>=$BE10,BT$6<=$BF10),"x","") -> #VALUE! | BU10: =IF(AND(BU$6>=$BE10,BU$6<=$BF10),"x","") -> #VALUE! | ... BY10: =IF(AND(BY$6>=$BE10,BY$6<=$BF10),"x","") -> #VALUE! | CA10: =A10 -> 2.2 | CB10: =B10 -> Analyse Marktpotential/Patentprüfung
A11: 3 | B11: Erstellung AP für FuE-Projekt | D11: 45231 | E11: 45260 | F11: =IF(D11="","",ROUND((E11-D11)/30,0)) -> 1 | G11: 0.5 | H11: =$G11*'Ermittl.-Stunden J1'!$T$5 -> 86.666667 | I11: =SUMIF('Tippl M. J1'!$B$17:$AK$511,'AP Übersicht'!$A11,'Tippl M. J1'!$AK$17:$AK$511) -> 21 | J11: =H11-I11 -> 65.666667 | L11: =$K11*'Ermittl.-Stunden J1'!$T$15 -> 0 | M11: =SUMIF('Socha J1'!$B$17:$AK$511,'AP Übersicht'!$A11,'Socha J1'!$AK$17:$AK$511) -> 7.5 | N11: =L11-M11 -> -7.5 | P11: =$O11*'Ermittl.-Stunden J1'!$T$25 -> 0 | Q11: =SUMIF('Tippl K. J1'!$B$17:$AK$511,'AP Übersicht'!$A11,'Tippl K. J1'!$AK$17:$AK$511) -> 0 | R11: =P11-Q11 -> 0 | U11: =SUM(G11,K11,O11) -> 0.5 | V11: =IF(AND(V$6>=$D11,V$6<=$E11),"x","") | W11: =IF(AND(W$6>=$D11,W$6<=$E11),"x","") | X11: =IF(AND(X$6>=$D11,X$6<=$E11),"x","") | Y11: =IF(AND(Y$6>=$D11,Y$6<=$E11),"x","") | Z11: =IF(AND(Z$6>=$D11,Z$6<=$E11),"x","") | AA11: =IF(AND(AA$6>=$D11,AA$6<=$E11),"x","") | AB11: =IF(AND(AB$6>=$D11,AB$6<=$E11),"x","") | AC11: =IF(AND(AC$6>=$D11,AC$6<=$E11),"x","") | ... AG11: =IF(AND(AG$6>=$D11,AG$6<=$E11),"x","") | AK11: =IF(AI11="","",ROUND((AJ11-AI11)/30,0)) | AQ11: =SUM(AL11:AP11) -> 0 | AR11: =IF(AND(AR$6>=$AI11,AR$6<=$AJ11),"x","") | AS11: =IF(AND(AS$6>=$AI11,AS$6<=$AJ11),"x","") | AT11: =IF(AND(AT$6>=$AI11,AT$6<=$AJ11),"x","") | AU11: =IF(AND(AU$6>=$AI11,AU$6<=$AJ11),"x","") | AV11: =IF(AND(AV$6>=$AI11,AV$6<=$AJ11),"x","") | AW11: =IF(AND(AW$6>=$AI11,AW$6<=$AJ11),"x","") | AX11: =IF(AND(AX$6>=$AI11,AX$6<=$AJ11),"x","") | AY11: =IF(AND(AY$6>=$AI11,AY$6<=$AJ11),"x","") | ... BC11: =IF(AND(BC$6>=$AI11,BC$6<=$AJ11),"x","") | BG11: =IF(BE11="","",ROUND((BF11-BE11)/30,0)) | BM11: =SUM(BH11:BL11) -> 0 | BN11: =IF(AND(BN$6>=$BE11,BN$6<=$BF11),"x","") -> x | BO11: =IF(AND(BO$6>=$BE11,BO$6<=$BF11),"x","") -> #VALUE! | BP11: =IF(AND(BP$6>=$BE11,BP$6<=$BF11),"x","") -> #VALUE! | BQ11: =IF(AND(BQ$6>=$BE11,BQ$6<=$BF11),"x","") -> #VALUE! | BR11: =IF(AND(BR$6>=$BE11,BR$6<=$BF11),"x","") -> #VALUE! | BS11: =IF(AND(BS$6>=$BE11,BS$6<=$BF11),"x","") -> #VALUE! | BT11: =IF(AND(BT$6>=$BE11,BT$6<=$BF11),"x","") -> #VALUE! | BU11: =IF(AND(BU$6>=$BE11,BU$6<=$BF11),"x","") -> #VALUE! | ... BY11: =IF(AND(BY$6>=$BE11,BY$6<=$BF11),"x","") -> #VALUE! | CA11: =A11 -> 3 | CB11: =B11 -> Erstellung AP für FuE-Projekt
A12: 4.1 | B12: Recherche und Anforderungen an biobasierte Lösemittel, deren Parameter und Einsatzfähigkeit in Markierungs- und Kennzeichnungssystemen | C12: x | D12: 45078 | E12: 45107 | F12: =IF(D12="","",ROUND((E12-D12)/30,0)) -> 1 | G12: 0.5 | H12: =$G12*'Ermittl.-Stunden J1'!$T$5 -> 86.666667 | I12: =SUMIF('Tippl M. J1'!$B$17:$AK$511,'AP Übersicht'!$A12,'Tippl M. J1'!$AK$17:$AK$511) -> 86.666 | J12: =H12-I12 -> 0.00066666667 | L12: =$K12*'Ermittl.-Stunden J1'!$T$15 -> 0 | M12: =SUMIF('Socha J1'!$B$17:$AK$511,'AP Übersicht'!$A12,'Socha J1'!$AK$17:$AK$511) -> 173.33 | N12: =L12-M12 -> -173.33 | O12: 0.5 | P12: =$O12*'Ermittl.-Stunden J1'!$T$25 -> 43.333333 | Q12: =SUMIF('Tippl K. J1'!$B$17:$AK$511,'AP Übersicht'!$A12,'Tippl K. J1'!$AK$17:$AK$511) -> 106.66 | R12: =P12-Q12 -> -63.326667 | U12: =SUM(G12,K12,O12) -> 1 | V12: =IF(AND(V$6>=$D12,V$6<=$E12),"x","") | W12: =IF(AND(W$6>=$D12,W$6<=$E12),"x","") | X12: =IF(AND(X$6>=$D12,X$6<=$E12),"x","") | Y12: =IF(AND(Y$6>=$D12,Y$6<=$E12),"x","") | Z12: =IF(AND(Z$6>=$D12,Z$6<=$E12),"x","") | AA12: =IF(AND(AA$6>=$D12,AA$6<=$E12),"x","") -> x | AB12: =IF(AND(AB$6>=$D12,AB$6<=$E12),"x","") | AC12: =IF(AND(AC$6>=$D12,AC$6<=$E12),"x","") | ... AG12: =IF(AND(AG$6>=$D12,AG$6<=$E12),"x","") | AK12: =IF(AI12="","",ROUND((AJ12-AI12)/30,0)) | AQ12: =SUM(AL12:AP12) -> 0 | AR12: =IF(AND(AR$6>=$AI12,AR$6<=$AJ12),"x","") | AS12: =IF(AND(AS$6>=$AI12,AS$6<=$AJ12),"x","") | AT12: =IF(AND(AT$6>=$AI12,AT$6<=$AJ12),"x","") | AU12: =IF(AND(AU$6>=$AI12,AU$6<=$AJ12),"x","") | AV12: =IF(AND(AV$6>=$AI12,AV$6<=$AJ12),"x","") | AW12: =IF(AND(AW$6>=$AI12,AW$6<=$AJ12),"x","") | AX12: =IF(AND(AX$6>=$AI12,AX$6<=$AJ12),"x","") | AY12: =IF(AND(AY$6>=$AI12,AY$6<=$AJ12),"x","") | ... BC12: =IF(AND(BC$6>=$AI12,BC$6<=$AJ12),"x","") | BG12: =IF(BE12="","",ROUND((BF12-BE12)/30,0)) | BM12: =SUM(BH12:BL12) -> 0 | BN12: =IF(AND(BN$6>=$BE12,BN$6<=$BF12),"x","") -> x | BO12: =IF(AND(BO$6>=$BE12,BO$6<=$BF12),"x","") -> #VALUE! | BP12: =IF(AND(BP$6>=$BE12,BP$6<=$BF12),"x","") -> #VALUE! | BQ12: =IF(AND(BQ$6>=$BE12,BQ$6<=$BF12),"x","") -> #VALUE! | BR12: =IF(AND(BR$6>=$BE12,BR$6<=$BF12),"x","") -> #VALUE! | BS12: =IF(AND(BS$6>=$BE12,BS$6<=$BF12),"x","") -> #VALUE! | BT12: =IF(AND(BT$6>=$BE12,BT$6<=$BF12),"x","") -> #VALUE! | BU12: =IF(AND(BU$6>=$BE12,BU$6<=$BF12),"x","") -> #VALUE! | ... BY12: =IF(AND(BY$6>=$BE12,BY$6<=$BF12),"x","") -> #VALUE! | CA12: =A12 -> 4.1 | CB12: =B12 -> Recherche und Anforderungen an biobasierte Lösemittel, deren Parameter und Einsatzfähigkeit in Markierungs- und Kennzeichnungssystemen
A13: 4.2 | B13: Beschaffung verfügbarer biobasierter Lösemittel sowie Versuche zur Herstellung von Tinten mit diesen Rohstoffen | C13: x | D13: 45108 | E13: 45169 | F13: =IF(D13="","",ROUND((E13-D13)/30,0)) -> 2 | G13: 1 | H13: =$G13*'Ermittl.-Stunden J1'!$T$5 -> 173.33333 | I13: =SUMIF('Tippl M. J1'!$B$17:$AK$511,'AP Übersicht'!$A13,'Tippl M. J1'!$AK$17:$AK$511) -> 127.33 | J13: =H13-I13 -> 46.003333 | K13: 1 | L13: =$K13*'Ermittl.-Stunden J1'!$T$15 -> 173.33333 | M13: =SUMIF('Socha J1'!$B$17:$AK$511,'AP Übersicht'!$A13,'Socha J1'!$AK$17:$AK$511) -> 132.67 | N13: =L13-M13 -> 40.663333 | O13: 1 | P13: =$O13*'Ermittl.-Stunden J1'!$T$25 -> 86.666667 | Q13: =SUMIF('Tippl K. J1'!$B$17:$AK$511,'AP Übersicht'!$A13,'Tippl K. J1'!$AK$17:$AK$511) -> 18.67 | R13: =P13-Q13 -> 67.996667 | U13: =SUM(G13,K13,O13) -> 3 | V13: =IF(AND(V$6>=$D13,V$6<=$E13),"x","") | W13: =IF(AND(W$6>=$D13,W$6<=$E13),"x","") | X13: =IF(AND(X$6>=$D13,X$6<=$E13),"x","") | Y13: =IF(AND(Y$6>=$D13,Y$6<=$E13),"x","") | Z13: =IF(AND(Z$6>=$D13,Z$6<=$E13),"x","") | AA13: =IF(AND(AA$6>=$D13,AA$6<=$E13),"x","") | AB13: =IF(AND(AB$6>=$D13,AB$6<=$E13),"x","") -> x | AC13: =IF(AND(AC$6>=$D13,AC$6<=$E13),"x","") -> x | ... AG13: =IF(AND(AG$6>=$D13,AG$6<=$E13),"x","") | AK13: =IF(AI13="","",ROUND((AJ13-AI13)/30,0)) | AQ13: =SUM(AL13:AP13) -> 0 | AR13: =IF(AND(AR$6>=$AI13,AR$6<=$AJ13),"x","") | AS13: =IF(AND(AS$6>=$AI13,AS$6<=$AJ13),"x","") | AT13: =IF(AND(AT$6>=$AI13,AT$6<=$AJ13),"x","") | AU13: =IF(AND(AU$6>=$AI13,AU$6<=$AJ13),"x","") | AV13: =IF(AND(AV$6>=$AI13,AV$6<=$AJ13),"x","") | AW13: =IF(AND(AW$6>=$AI13,AW$6<=$AJ13),"x","") | AX13: =IF(AND(AX$6>=$AI13,AX$6<=$AJ13),"x","") | AY13: =IF(AND(AY$6>=$AI13,AY$6<=$AJ13),"x","") | ... BC13: =IF(AND(BC$6>=$AI13,BC$6<=$AJ13),"x","") | BG13: =IF(BE13="","",ROUND((BF13-BE13)/30,0)) | BM13: =SUM(BH13:BL13) -> 0 | BN13: =IF(AND(BN$6>=$BE13,BN$6<=$BF13),"x","") -> x | BO13: =IF(AND(BO$6>=$BE13,BO$6<=$BF13),"x","") -> #VALUE! | BP13: =IF(AND(BP$6>=$BE13,BP$6<=$BF13),"x","") -> #VALUE! | BQ13: =IF(AND(BQ$6>=$BE13,BQ$6<=$BF13),"x","") -> #VALUE! | BR13: =IF(AND(BR$6>=$BE13,BR$6<=$BF13),"x","") -> #VALUE! | BS13: =IF(AND(BS$6>=$BE13,BS$6<=$BF13),"x","") -> #VALUE! | BT13: =IF(AND(BT$6>=$BE13,BT$6<=$BF13),"x","") -> #VALUE! | BU13: =IF(AND(BU$6>=$BE13,BU$6<=$BF13),"x","") -> #VALUE! | ... BY13: =IF(AND(BY$6>=$BE13,BY$6<=$BF13),"x","") -> #VALUE! | CA13: =A13 -> 4.2 | CB13: =B13 -> Beschaffung verfügbarer biobasierter Lösemittel sowie Versuche zur Herstellung von Tinten mit diesen Rohstoffen
A14: 4.3 | B14: Versuche zur Einsatzfähigkeit und den Parametern (aufzutragende Menge, Temperatur, relative Luftfeuchtigkeit bzw. zum Einsatzbereich im industriellen Umfeld | C14: x | D14: 45170 | E14: 45230 | F14: =IF(D14="","",ROUND((E14-D14)/30,0)) -> 2 | G14: 1 | H14: =$G14*'Ermittl.-Stunden J1'!$T$5 -> 173.33333 | I14: =SUMIF('Tippl M. J1'!$B$17:$AK$511,'AP Übersicht'!$A14,'Tippl M. J1'!$AK$17:$AK$511) -> 264.67 | J14: =H14-I14 -> -91.336667 | L14: =$K14*'Ermittl.-Stunden J1'!$T$15 -> 0 | M14: =SUMIF('Socha J1'!$B$17:$AK$511,'AP Übersicht'!$A14,'Socha J1'!$AK$17:$AK$511) -> 152 | N14: =L14-M14 -> -152 | O14: 1 | P14: =$O14*'Ermittl.-Stunden J1'!$T$25 -> 86.666667 | Q14: =SUMIF('Tippl K. J1'!$B$17:$AK$511,'AP Übersicht'!$A14,'Tippl K. J1'!$AK$17:$AK$511) -> 148 | R14: =P14-Q14 -> -61.333333 | U14: =SUM(G14,K14,O14) -> 2 | V14: =IF(AND(V$6>=$D14,V$6<=$E14),"x","") | W14: =IF(AND(W$6>=$D14,W$6<=$E14),"x","") | X14: =IF(AND(X$6>=$D14,X$6<=$E14),"x","") | Y14: =IF(AND(Y$6>=$D14,Y$6<=$E14),"x","") | Z14: =IF(AND(Z$6>=$D14,Z$6<=$E14),"x","") | AA14: =IF(AND(AA$6>=$D14,AA$6<=$E14),"x","") | AB14: =IF(AND(AB$6>=$D14,AB$6<=$E14),"x","") | AC14: =IF(AND(AC$6>=$D14,AC$6<=$E14),"x","") | ... AG14: =IF(AND(AG$6>=$D14,AG$6<=$E14),"x","") | AK14: =IF(AI14="","",ROUND((AJ14-AI14)/30,0)) | AQ14: =SUM(AL14:AP14) -> 0 | AR14: =IF(AND(AR$6>=$AI14,AR$6<=$AJ14),"x","") | AS14: =IF(AND(AS$6>=$AI14,AS$6<=$AJ14),"x","") | AT14: =IF(AND(AT$6>=$AI14,AT$6<=$AJ14),"x","") | AU14: =IF(AND(AU$6>=$AI14,AU$6<=$AJ14),"x","") | AV14: =IF(AND(AV$6>=$AI14,AV$6<=$AJ14),"x","") | AW14: =IF(AND(AW$6>=$AI14,AW$6<=$AJ14),"x","") | AX14: =IF(AND(AX$6>=$AI14,AX$6<=$AJ14),"x","") | AY14: =IF(AND(AY$6>=$AI14,AY$6<=$AJ14),"x","") | ... BC14: =IF(AND(BC$6>=$AI14,BC$6<=$AJ14),"x","") | BG14: =IF(BE14="","",ROUND((BF14-BE14)/30,0)) | BM14: =SUM(BH14:BL14) -> 0 | BN14: =IF(AND(BN$6>=$BE14,BN$6<=$BF14),"x","") -> x | BO14: =IF(AND(BO$6>=$BE14,BO$6<=$BF14),"x","") -> #VALUE! | BP14: =IF(AND(BP$6>=$BE14,BP$6<=$BF14),"x","") -> #VALUE! | BQ14: =IF(AND(BQ$6>=$BE14,BQ$6<=$BF14),"x","") -> #VALUE! | BR14: =IF(AND(BR$6>=$BE14,BR$6<=$BF14),"x","") -> #VALUE! | BS14: =IF(AND(BS$6>=$BE14,BS$6<=$BF14),"x","") -> #VALUE! | BT14: =IF(AND(BT$6>=$BE14,BT$6<=$BF14),"x","") -> #VALUE! | BU14: =IF(AND(BU$6>=$BE14,BU$6<=$BF14),"x","") -> #VALUE! | ... BY14: =IF(AND(BY$6>=$BE14,BY$6<=$BF14),"x","") -> #VALUE! | CA14: =A14 -> 4.3 | CB14: =B14 -> Versuche zur Einsatzfähigkeit und den Parametern (aufzutragende Menge, Temperatur, relative Luftfeuchtigkeit bzw. zum Einsatzbereich im industriellen Umfeld
A15: 5 | B15: Ermittl. wissenschaftlich-technischer Ressourcen und möglicher Kooperationspartner | D15: 45231 | E15: 45289 | F15: =IF(D15="","",ROUND((E15-D15)/30,0)) -> 2 | G15: 0.5 | H15: =$G15*'Ermittl.-Stunden J1'!$T$5 -> 86.666667 | I15: =SUMIF('Tippl M. J1'!$B$17:$AK$511,'AP Übersicht'!$A15,'Tippl M. J1'!$AK$17:$AK$511) -> 59 | J15: =H15-I15 -> 27.666667 | L15: =$K15*'Ermittl.-Stunden J1'!$T$15 -> 0 | M15: =SUMIF('Socha J1'!$B$17:$AK$511,'AP Übersicht'!$A15,'Socha J1'!$AK$17:$AK$511) -> 0 | N15: =L15-M15 -> 0 | P15: =$O15*'Ermittl.-Stunden J1'!$T$25 -> 0 | Q15: =SUMIF('Tippl K. J1'!$B$17:$AK$511,'AP Übersicht'!$A15,'Tippl K. J1'!$AK$17:$AK$511) -> 0 | R15: =P15-Q15 -> 0 | U15: =SUM(G15,K15,O15) -> 0.5 | V15: =IF(AND(V$6>=$D15,V$6<=$E15),"x","") | W15: =IF(AND(W$6>=$D15,W$6<=$E15),"x","") | X15: =IF(AND(X$6>=$D15,X$6<=$E15),"x","") | Y15: =IF(AND(Y$6>=$D15,Y$6<=$E15),"x","") | Z15: =IF(AND(Z$6>=$D15,Z$6<=$E15),"x","") | AA15: =IF(AND(AA$6>=$D15,AA$6<=$E15),"x","") | AB15: =IF(AND(AB$6>=$D15,AB$6<=$E15),"x","") | AC15: =IF(AND(AC$6>=$D15,AC$6<=$E15),"x","") | ... AG15: =IF(AND(AG$6>=$D15,AG$6<=$E15),"x","") -> x | AK15: =IF(AI15="","",ROUND((AJ15-AI15)/30,0)) | AQ15: =SUM(AL15:AP15) -> 0 | AR15: =IF(AND(AR$6>=$AI15,AR$6<=$AJ15),"x","") | AS15: =IF(AND(AS$6>=$AI15,AS$6<=$AJ15),"x","") | AT15: =IF(AND(AT$6>=$AI15,AT$6<=$AJ15),"x","") | AU15: =IF(AND(AU$6>=$AI15,AU$6<=$AJ15),"x","") | AV15: =IF(AND(AV$6>=$AI15,AV$6<=$AJ15),"x","") | AW15: =IF(AND(AW$6>=$AI15,AW$6<=$AJ15),"x","") | AX15: =IF(AND(AX$6>=$AI15,AX$6<=$AJ15),"x","") | AY15: =IF(AND(AY$6>=$AI15,AY$6<=$AJ15),"x","") | ... BC15: =IF(AND(BC$6>=$AI15,BC$6<=$AJ15),"x","") | BG15: =IF(BE15="","",ROUND((BF15-BE15)/30,0)) | BM15: =SUM(BH15:BL15) -> 0 | BN15: =IF(AND(BN$6>=$BE15,BN$6<=$BF15),"x","") -> x | BO15: =IF(AND(BO$6>=$BE15,BO$6<=$BF15),"x","") -> #VALUE! | BP15: =IF(AND(BP$6>=$BE15,BP$6<=$BF15),"x","") -> #VALUE! | BQ15: =IF(AND(BQ$6>=$BE15,BQ$6<=$BF15),"x","") -> #VALUE! | BR15: =IF(AND(BR$6>=$BE15,BR$6<=$BF15),"x","") -> #VALUE! | BS15: =IF(AND(BS$6>=$BE15,BS$6<=$BF15),"x","") -> #VALUE! | BT15: =IF(AND(BT$6>=$BE15,BT$6<=$BF15),"x","") -> #VALUE! | BU15: =IF(AND(BU$6>=$BE15,BU$6<=$BF15),"x","") -> #VALUE! | ... BY15: =IF(AND(BY$6>=$BE15,BY$6<=$BF15),"x","") -> #VALUE! | CA15: =A15 -> 5 | CB15: =B15 -> Ermittl. wissenschaftlich-technischer Ressourcen und möglicher Kooperationspartner
F16: =IF(D16="","",ROUND((E16-D16)/30,0)) | U16: =SUM(G16,K16,O16) -> 0 | V16: =IF(AND(V$6>=$D16,V$6<=$E16),"x","") | W16: =IF(AND(W$6>=$D16,W$6<=$E16),"x","") | X16: =IF(AND(X$6>=$D16,X$6<=$E16),"x","") | Y16: =IF(AND(Y$6>=$D16,Y$6<=$E16),"x","") | Z16: =IF(AND(Z$6>=$D16,Z$6<=$E16),"x","") | AA16: =IF(AND(AA$6>=$D16,AA$6<=$E16),"x","") | AB16: =IF(AND(AB$6>=$D16,AB$6<=$E16),"x","") | AC16: =IF(AND(AC$6>=$D16,AC$6<=$E16),"x","") | ... AG16: =IF(AND(AG$6>=$D16,AG$6<=$E16),"x","") | AK16: =IF(AI16="","",ROUND((AJ16-AI16)/30,0)) | AQ16: =SUM(AL16:AP16) -> 0 | AR16: =IF(AND(AR$6>=$AI16,AR$6<=$AJ16),"x","") | AS16: =IF(AND(AS$6>=$AI16,AS$6<=$AJ16),"x","") | AT16: =IF(AND(AT$6>=$AI16,AT$6<=$AJ16),"x","") | AU16: =IF(AND(AU$6>=$AI16,AU$6<=$AJ16),"x","") | AV16: =IF(AND(AV$6>=$AI16,AV$6<=$AJ16),"x","") | AW16: =IF(AND(AW$6>=$AI16,AW$6<=$AJ16),"x","") | AX16: =IF(AND(AX$6>=$AI16,AX$6<=$AJ16),"x","") | AY16: =IF(AND(AY$6>=$AI16,AY$6<=$AJ16),"x","") | ... BC16: =IF(AND(BC$6>=$AI16,BC$6<=$AJ16),"x","") | BG16: =IF(BE16="","",ROUND((BF16-BE16)/30,0)) | BM16: =SUM(BH16:BL16) -> 0 | BN16: =IF(AND(BN$6>=$BE16,BN$6<=$BF16),"x","") -> x | BO16: =IF(AND(BO$6>=$BE16,BO$6<=$BF16),"x","") -> #VALUE! | BP16: =IF(AND(BP$6>=$BE16,BP$6<=$BF16),"x","") -> #VALUE! | BQ16: =IF(AND(BQ$6>=$BE16,BQ$6<=$BF16),"x","") -> #VALUE! | BR16: =IF(AND(BR$6>=$BE16,BR$6<=$BF16),"x","") -> #VALUE! | BS16: =IF(AND(BS$6>=$BE16,BS$6<=$BF16),"x","") -> #VALUE! | BT16: =IF(AND(BT$6>=$BE16,BT$6<=$BF16),"x","") -> #VALUE! | BU16: =IF(AND(BU$6>=$BE16,BU$6<=$BF16),"x","") -> #VALUE! | ... BY16: =IF(AND(BY$6>=$BE16,BY$6<=$BF16),"x","") -> #VALUE! | CA16: =A16 -> 0 | CB16: =B16 -> 0
F17: =IF(D17="","",ROUND((E17-D17)/30,0)) | U17: =SUM(G17,K17,O17) -> 0 | V17: =IF(AND(V$6>=$D17,V$6<=$E17),"x","") | W17: =IF(AND(W$6>=$D17,W$6<=$E17),"x","") | X17: =IF(AND(X$6>=$D17,X$6<=$E17),"x","") | Y17: =IF(AND(Y$6>=$D17,Y$6<=$E17),"x","") | Z17: =IF(AND(Z$6>=$D17,Z$6<=$E17),"x","") | AA17: =IF(AND(AA$6>=$D17,AA$6<=$E17),"x","") | AB17: =IF(AND(AB$6>=$D17,AB$6<=$E17),"x","") | AC17: =IF(AND(AC$6>=$D17,AC$6<=$E17),"x","") | ... AG17: =IF(AND(AG$6>=$D17,AG$6<=$E17),"x","") | AK17: =IF(AI17="","",ROUND((AJ17-AI17)/30,0)) | AQ17: =SUM(AL17:AP17) -> 0 | AR17: =IF(AND(AR$6>=$AI17,AR$6<=$AJ17),"x","") | AS17: =IF(AND(AS$6>=$AI17,AS$6<=$AJ17),"x","") | AT17: =IF(AND(AT$6>=$AI17,AT$6<=$AJ17),"x","") | AU17: =IF(AND(AU$6>=$AI17,AU$6<=$AJ17),"x","") | AV17: =IF(AND(AV$6>=$AI17,AV$6<=$AJ17),"x","") | AW17: =IF(AND(AW$6>=$AI17,AW$6<=$AJ17),"x","") | AX17: =IF(AND(AX$6>=$AI17,AX$6<=$AJ17),"x","") | AY17: =IF(AND(AY$6>=$AI17,AY$6<=$AJ17),"x","") | ... BC17: =IF(AND(BC$6>=$AI17,BC$6<=$AJ17),"x","") | BG17: =IF(BE17="","",ROUND((BF17-BE17)/30,0)) | BM17: =SUM(BH17:BL17) -> 0 | BN17: =IF(AND(BN$6>=$BE17,BN$6<=$BF17),"x","") -> x | BO17: =IF(AND(BO$6>=$BE17,BO$6<=$BF17),"x","") -> #VALUE! | BP17: =IF(AND(BP$6>=$BE17,BP$6<=$BF17),"x","") -> #VALUE! | BQ17: =IF(AND(BQ$6>=$BE17,BQ$6<=$BF17),"x","") -> #VALUE! | BR17: =IF(AND(BR$6>=$BE17,BR$6<=$BF17),"x","") -> #VALUE! | BS17: =IF(AND(BS$6>=$BE17,BS$6<=$BF17),"x","") -> #VALUE! | BT17: =IF(AND(BT$6>=$BE17,BT$6<=$BF17),"x","") -> #VALUE! | BU17: =IF(AND(BU$6>=$BE17,BU$6<=$BF17),"x","") -> #VALUE! | ... BY17: =IF(AND(BY$6>=$BE17,BY$6<=$BF17),"x","") -> #VALUE! | CA17: =A17 -> 0 | CB17: =B17 -> 0
F18: =IF(D18="","",ROUND((E18-D18)/30,0)) | U18: =SUM(G18,K18,O18) -> 0 | V18: =IF(AND(V$6>=$D18,V$6<=$E18),"x","") | W18: =IF(AND(W$6>=$D18,W$6<=$E18),"x","") | X18: =IF(AND(X$6>=$D18,X$6<=$E18),"x","") | Y18: =IF(AND(Y$6>=$D18,Y$6<=$E18),"x","") | Z18: =IF(AND(Z$6>=$D18,Z$6<=$E18),"x","") | AA18: =IF(AND(AA$6>=$D18,AA$6<=$E18),"x","") | AB18: =IF(AND(AB$6>=$D18,AB$6<=$E18),"x","") | AC18: =IF(AND(AC$6>=$D18,AC$6<=$E18),"x","") | ... AG18: =IF(AND(AG$6>=$D18,AG$6<=$E18),"x","") | AK18: =IF(AI18="","",ROUND((AJ18-AI18)/30,0)) | AQ18: =SUM(AL18:AP18) -> 0 | AR18: =IF(AND(AR$6>=$AI18,AR$6<=$AJ18),"x","") | AS18: =IF(AND(AS$6>=$AI18,AS$6<=$AJ18),"x","") | AT18: =IF(AND(AT$6>=$AI18,AT$6<=$AJ18),"x","") | AU18: =IF(AND(AU$6>=$AI18,AU$6<=$AJ18),"x","") | AV18: =IF(AND(AV$6>=$AI18,AV$6<=$AJ18),"x","") | AW18: =IF(AND(AW$6>=$AI18,AW$6<=$AJ18),"x","") | AX18: =IF(AND(AX$6>=$AI18,AX$6<=$AJ18),"x","") | AY18: =IF(AND(AY$6>=$AI18,AY$6<=$AJ18),"x","") | ... BC18: =IF(AND(BC$6>=$AI18,BC$6<=$AJ18),"x","") | BG18: =IF(BE18="","",ROUND((BF18-BE18)/30,0)) | BM18: =SUM(BH18:BL18) -> 0 | BN18: =IF(AND(BN$6>=$BE18,BN$6<=$BF18),"x","") -> x | BO18: =IF(AND(BO$6>=$BE18,BO$6<=$BF18),"x","") -> #VALUE! | BP18: =IF(AND(BP$6>=$BE18,BP$6<=$BF18),"x","") -> #VALUE! | BQ18: =IF(AND(BQ$6>=$BE18,BQ$6<=$BF18),"x","") -> #VALUE! | BR18: =IF(AND(BR$6>=$BE18,BR$6<=$BF18),"x","") -> #VALUE! | BS18: =IF(AND(BS$6>=$BE18,BS$6<=$BF18),"x","") -> #VALUE! | BT18: =IF(AND(BT$6>=$BE18,BT$6<=$BF18),"x","") -> #VALUE! | BU18: =IF(AND(BU$6>=$BE18,BU$6<=$BF18),"x","") -> #VALUE! | ... BY18: =IF(AND(BY$6>=$BE18,BY$6<=$BF18),"x","") -> #VALUE! | CA18: =A18 -> 0 | CB18: =B18 -> 0
F19: =IF(D19="","",ROUND((E19-D19)/30,0)) | U19: =SUM(G19,K19,O19) -> 0 | V19: =IF(AND(V$6>=$D19,V$6<=$E19),"x","") | W19: =IF(AND(W$6>=$D19,W$6<=$E19),"x","") | X19: =IF(AND(X$6>=$D19,X$6<=$E19),"x","") | Y19: =IF(AND(Y$6>=$D19,Y$6<=$E19),"x","") | Z19: =IF(AND(Z$6>=$D19,Z$6<=$E19),"x","") | AA19: =IF(AND(AA$6>=$D19,AA$6<=$E19),"x","") | AB19: =IF(AND(AB$6>=$D19,AB$6<=$E19),"x","") | AC19: =IF(AND(AC$6>=$D19,AC$6<=$E19),"x","") | ... AG19: =IF(AND(AG$6>=$D19,AG$6<=$E19),"x","") | AK19: =IF(AI19="","",ROUND((AJ19-AI19)/30,0)) | AQ19: =SUM(AL19:AP19) -> 0 | AR19: =IF(AND(AR$6>=$AI19,AR$6<=$AJ19),"x","") | AS19: =IF(AND(AS$6>=$AI19,AS$6<=$AJ19),"x","") | AT19: =IF(AND(AT$6>=$AI19,AT$6<=$AJ19),"x","") | AU19: =IF(AND(AU$6>=$AI19,AU$6<=$AJ19),"x","") | AV19: =IF(AND(AV$6>=$AI19,AV$6<=$AJ19),"x","") | AW19: =IF(AND(AW$6>=$AI19,AW$6<=$AJ19),"x","") | AX19: =IF(AND(AX$6>=$AI19,AX$6<=$AJ19),"x","") | AY19: =IF(AND(AY$6>=$AI19,AY$6<=$AJ19),"x","") | ... BC19: =IF(AND(BC$6>=$AI19,BC$6<=$AJ19),"x","") | BG19: =IF(BE19="","",ROUND((BF19-BE19)/30,0)) | BM19: =SUM(BH19:BL19) -> 0 | BN19: =IF(AND(BN$6>=$BE19,BN$6<=$BF19),"x","") -> x | BO19: =IF(AND(BO$6>=$BE19,BO$6<=$BF19),"x","") -> #VALUE! | BP19: =IF(AND(BP$6>=$BE19,BP$6<=$BF19),"x","") -> #VALUE! | BQ19: =IF(AND(BQ$6>=$BE19,BQ$6<=$BF19),"x","") -> #VALUE! | BR19: =IF(AND(BR$6>=$BE19,BR$6<=$BF19),"x","") -> #VALUE! | BS19: =IF(AND(BS$6>=$BE19,BS$6<=$BF19),"x","") -> #VALUE! | BT19: =IF(AND(BT$6>=$BE19,BT$6<=$BF19),"x","") -> #VALUE! | BU19: =IF(AND(BU$6>=$BE19,BU$6<=$BF19),"x","") -> #VALUE! | ... BY19: =IF(AND(BY$6>=$BE19,BY$6<=$BF19),"x","") -> #VALUE! | CA19: =A19 -> 0 | CB19: =B19 -> 0
F20: =IF(D20="","",ROUND((E20-D20)/30,0)) | U20: =SUM(G20,K20,O20) -> 0 | V20: =IF(AND(V$6>=$D20,V$6<=$E20),"x","") | W20: =IF(AND(W$6>=$D20,W$6<=$E20),"x","") | X20: =IF(AND(X$6>=$D20,X$6<=$E20),"x","") | Y20: =IF(AND(Y$6>=$D20,Y$6<=$E20),"x","") | Z20: =IF(AND(Z$6>=$D20,Z$6<=$E20),"x","") | AA20: =IF(AND(AA$6>=$D20,AA$6<=$E20),"x","") | AB20: =IF(AND(AB$6>=$D20,AB$6<=$E20),"x","") | AC20: =IF(AND(AC$6>=$D20,AC$6<=$E20),"x","") | ... AG20: =IF(AND(AG$6>=$D20,AG$6<=$E20),"x","") | AK20: =IF(AI20="","",ROUND((AJ20-AI20)/30,0)) | AQ20: =SUM(AL20:AP20) -> 0 | AR20: =IF(AND(AR$6>=$AI20,AR$6<=$AJ20),"x","") | AS20: =IF(AND(AS$6>=$AI20,AS$6<=$AJ20),"x","") | AT20: =IF(AND(AT$6>=$AI20,AT$6<=$AJ20),"x","") | AU20: =IF(AND(AU$6>=$AI20,AU$6<=$AJ20),"x","") | AV20: =IF(AND(AV$6>=$AI20,AV$6<=$AJ20),"x","") | AW20: =IF(AND(AW$6>=$AI20,AW$6<=$AJ20),"x","") | AX20: =IF(AND(AX$6>=$AI20,AX$6<=$AJ20),"x","") | AY20: =IF(AND(AY$6>=$AI20,AY$6<=$AJ20),"x","") | ... BC20: =IF(AND(BC$6>=$AI20,BC$6<=$AJ20),"x","") | BG20: =IF(BE20="","",ROUND((BF20-BE20)/30,0)) | BM20: =SUM(BH20:BL20) -> 0 | BN20: =IF(AND(BN$6>=$BE20,BN$6<=$BF20),"x","") -> x | BO20: =IF(AND(BO$6>=$BE20,BO$6<=$BF20),"x","") -> #VALUE! | BP20: =IF(AND(BP$6>=$BE20,BP$6<=$BF20),"x","") -> #VALUE! | BQ20: =IF(AND(BQ$6>=$BE20,BQ$6<=$BF20),"x","") -> #VALUE! | BR20: =IF(AND(BR$6>=$BE20,BR$6<=$BF20),"x","") -> #VALUE! | BS20: =IF(AND(BS$6>=$BE20,BS$6<=$BF20),"x","") -> #VALUE! | BT20: =IF(AND(BT$6>=$BE20,BT$6<=$BF20),"x","") -> #VALUE! | BU20: =IF(AND(BU$6>=$BE20,BU$6<=$BF20),"x","") -> #VALUE! | ... BY20: =IF(AND(BY$6>=$BE20,BY$6<=$BF20),"x","") -> #VALUE! | CA20: =A20 -> 0 | CB20: =B20 -> 0
F21: =IF(D21="","",ROUND((E21-D21)/30,0)) | U21: =SUM(G21,K21,O21) -> 0 | V21: =IF(AND(V$6>=$D21,V$6<=$E21),"x","") | W21: =IF(AND(W$6>=$D21,W$6<=$E21),"x","") | X21: =IF(AND(X$6>=$D21,X$6<=$E21),"x","") | Y21: =IF(AND(Y$6>=$D21,Y$6<=$E21),"x","") | Z21: =IF(AND(Z$6>=$D21,Z$6<=$E21),"x","") | AA21: =IF(AND(AA$6>=$D21,AA$6<=$E21),"x","") | AB21: =IF(AND(AB$6>=$D21,AB$6<=$E21),"x","") | AC21: =IF(AND(AC$6>=$D21,AC$6<=$E21),"x","") | ... AG21: =IF(AND(AG$6>=$D21,AG$6<=$E21),"x","") | AK21: =IF(AI21="","",ROUND((AJ21-AI21)/30,0)) | AQ21: =SUM(AL21:AP21) -> 0 | AR21: =IF(AND(AR$6>=$AI21,AR$6<=$AJ21),"x","") | AS21: =IF(AND(AS$6>=$AI21,AS$6<=$AJ21),"x","") | AT21: =IF(AND(AT$6>=$AI21,AT$6<=$AJ21),"x","") | AU21: =IF(AND(AU$6>=$AI21,AU$6<=$AJ21),"x","") | AV21: =IF(AND(AV$6>=$AI21,AV$6<=$AJ21),"x","") | AW21: =IF(AND(AW$6>=$AI21,AW$6<=$AJ21),"x","") | AX21: =IF(AND(AX$6>=$AI21,AX$6<=$AJ21),"x","") | AY21: =IF(AND(AY$6>=$AI21,AY$6<=$AJ21),"x","") | ... BC21: =IF(AND(BC$6>=$AI21,BC$6<=$AJ21),"x","") | BG21: =IF(BE21="","",ROUND((BF21-BE21)/30,0)) | BM21: =SUM(BH21:BL21) -> 0 | BN21: =IF(AND(BN$6>=$BE21,BN$6<=$BF21),"x","") -> x | BO21: =IF(AND(BO$6>=$BE21,BO$6<=$BF21),"x","") -> #VALUE! | BP21: =IF(AND(BP$6>=$BE21,BP$6<=$BF21),"x","") -> #VALUE! | BQ21: =IF(AND(BQ$6>=$BE21,BQ$6<=$BF21),"x","") -> #VALUE! | BR21: =IF(AND(BR$6>=$BE21,BR$6<=$BF21),"x","") -> #VALUE! | BS21: =IF(AND(BS$6>=$BE21,BS$6<=$BF21),"x","") -> #VALUE! | BT21: =IF(AND(BT$6>=$BE21,BT$6<=$BF21),"x","") -> #VALUE! | BU21: =IF(AND(BU$6>=$BE21,BU$6<=$BF21),"x","") -> #VALUE! | ... BY21: =IF(AND(BY$6>=$BE21,BY$6<=$BF21),"x","") -> #VALUE! | CA21: =A21 -> 0 | CB21: =B21 -> 0
F22: =IF(D22="","",ROUND((E22-D22)/30,0)) | U22: =SUM(G22,K22,O22) -> 0 | V22: =IF(AND(V$6>=$D22,V$6<=$E22),"x","") | W22: =IF(AND(W$6>=$D22,W$6<=$E22),"x","") | X22: =IF(AND(X$6>=$D22,X$6<=$E22),"x","") | Y22: =IF(AND(Y$6>=$D22,Y$6<=$E22),"x","") | Z22: =IF(AND(Z$6>=$D22,Z$6<=$E22),"x","") | AA22: =IF(AND(AA$6>=$D22,AA$6<=$E22),"x","") | AB22: =IF(AND(AB$6>=$D22,AB$6<=$E22),"x","") | AC22: =IF(AND(AC$6>=$D22,AC$6<=$E22),"x","") | ... AG22: =IF(AND(AG$6>=$D22,AG$6<=$E22),"x","") | AK22: =IF(AI22="","",ROUND((AJ22-AI22)/30,0)) | AQ22: =SUM(AL22:AP22) -> 0 | AR22: =IF(AND(AR$6>=$AI22,AR$6<=$AJ22),"x","") | AS22: =IF(AND(AS$6>=$AI22,AS$6<=$AJ22),"x","") | AT22: =IF(AND(AT$6>=$AI22,AT$6<=$AJ22),"x","") | AU22: =IF(AND(AU$6>=$AI22,AU$6<=$AJ22),"x","") | AV22: =IF(AND(AV$6>=$AI22,AV$6<=$AJ22),"x","") | AW22: =IF(AND(AW$6>=$AI22,AW$6<=$AJ22),"x","") | AX22: =IF(AND(AX$6>=$AI22,AX$6<=$AJ22),"x","") | AY22: =IF(AND(AY$6>=$AI22,AY$6<=$AJ22),"x","") | ... BC22: =IF(AND(BC$6>=$AI22,BC$6<=$AJ22),"x","") | BG22: =IF(BE22="","",ROUND((BF22-BE22)/30,0)) | BM22: =SUM(BH22:BL22) -> 0 | BN22: =IF(AND(BN$6>=$BE22,BN$6<=$BF22),"x","") -> x | BO22: =IF(AND(BO$6>=$BE22,BO$6<=$BF22),"x","") -> #VALUE! | BP22: =IF(AND(BP$6>=$BE22,BP$6<=$BF22),"x","") -> #VALUE! | BQ22: =IF(AND(BQ$6>=$BE22,BQ$6<=$BF22),"x","") -> #VALUE! | BR22: =IF(AND(BR$6>=$BE22,BR$6<=$BF22),"x","") -> #VALUE! | BS22: =IF(AND(BS$6>=$BE22,BS$6<=$BF22),"x","") -> #VALUE! | BT22: =IF(AND(BT$6>=$BE22,BT$6<=$BF22),"x","") -> #VALUE! | BU22: =IF(AND(BU$6>=$BE22,BU$6<=$BF22),"x","") -> #VALUE! | ... BY22: =IF(AND(BY$6>=$BE22,BY$6<=$BF22),"x","") -> #VALUE! | CA22: =A22 -> 0 | CB22: =B22 -> 0
F23: =IF(D23="","",ROUND((E23-D23)/30,0)) | U23: =SUM(G23,K23,O23) -> 0 | V23: =IF(AND(V$6>=$D23,V$6<=$E23),"x","") | W23: =IF(AND(W$6>=$D23,W$6<=$E23),"x","") | X23: =IF(AND(X$6>=$D23,X$6<=$E23),"x","") | Y23: =IF(AND(Y$6>=$D23,Y$6<=$E23),"x","") | Z23: =IF(AND(Z$6>=$D23,Z$6<=$E23),"x","") | AA23: =IF(AND(AA$6>=$D23,AA$6<=$E23),"x","") | AB23: =IF(AND(AB$6>=$D23,AB$6<=$E23),"x","") | AC23: =IF(AND(AC$6>=$D23,AC$6<=$E23),"x","") | ... AG23: =IF(AND(AG$6>=$D23,AG$6<=$E23),"x","") | AK23: =IF(AI23="","",ROUND((AJ23-AI23)/30,0)) | AQ23: =SUM(AL23:AP23) -> 0 | AR23: =IF(AND(AR$6>=$AI23,AR$6<=$AJ23),"x","") | AS23: =IF(AND(AS$6>=$AI23,AS$6<=$AJ23),"x","") | AT23: =IF(AND(AT$6>=$AI23,AT$6<=$AJ23),"x","") | AU23: =IF(AND(AU$6>=$AI23,AU$6<=$AJ23),"x","") | AV23: =IF(AND(AV$6>=$AI23,AV$6<=$AJ23),"x","") | AW23: =IF(AND(AW$6>=$AI23,AW$6<=$AJ23),"x","") | AX23: =IF(AND(AX$6>=$AI23,AX$6<=$AJ23),"x","") | AY23: =IF(AND(AY$6>=$AI23,AY$6<=$AJ23),"x","") | ... BC23: =IF(AND(BC$6>=$AI23,BC$6<=$AJ23),"x","") | BG23: =IF(BE23="","",ROUND((BF23-BE23)/30,0)) | BM23: =SUM(BH23:BL23) -> 0 | BN23: =IF(AND(BN$6>=$BE23,BN$6<=$BF23),"x","") -> x | BO23: =IF(AND(BO$6>=$BE23,BO$6<=$BF23),"x","") -> #VALUE! | BP23: =IF(AND(BP$6>=$BE23,BP$6<=$BF23),"x","") -> #VALUE! | BQ23: =IF(AND(BQ$6>=$BE23,BQ$6<=$BF23),"x","") -> #VALUE! | BR23: =IF(AND(BR$6>=$BE23,BR$6<=$BF23),"x","") -> #VALUE! | BS23: =IF(AND(BS$6>=$BE23,BS$6<=$BF23),"x","") -> #VALUE! | BT23: =IF(AND(BT$6>=$BE23,BT$6<=$BF23),"x","") -> #VALUE! | BU23: =IF(AND(BU$6>=$BE23,BU$6<=$BF23),"x","") -> #VALUE! | ... BY23: =IF(AND(BY$6>=$BE23,BY$6<=$BF23),"x","") -> #VALUE! | CA23: =A23 -> 0 | CB23: =B23 -> 0
F24: =IF(D24="","",ROUND((E24-D24)/30,0)) | U24: =SUM(G24,K24,O24) -> 0 | V24: =IF(AND(V$6>=$D24,V$6<=$E24),"x","") | W24: =IF(AND(W$6>=$D24,W$6<=$E24),"x","") | X24: =IF(AND(X$6>=$D24,X$6<=$E24),"x","") | Y24: =IF(AND(Y$6>=$D24,Y$6<=$E24),"x","") | Z24: =IF(AND(Z$6>=$D24,Z$6<=$E24),"x","") | AA24: =IF(AND(AA$6>=$D24,AA$6<=$E24),"x","") | AB24: =IF(AND(AB$6>=$D24,AB$6<=$E24),"x","") | AC24: =IF(AND(AC$6>=$D24,AC$6<=$E24),"x","") | ... AG24: =IF(AND(AG$6>=$D24,AG$6<=$E24),"x","") | AK24: =IF(AI24="","",ROUND((AJ24-AI24)/30,0)) | AQ24: =SUM(AL24:AP24) -> 0 | AR24: =IF(AND(AR$6>=$AI24,AR$6<=$AJ24),"x","") | AS24: =IF(AND(AS$6>=$AI24,AS$6<=$AJ24),"x","") | AT24: =IF(AND(AT$6>=$AI24,AT$6<=$AJ24),"x","") | AU24: =IF(AND(AU$6>=$AI24,AU$6<=$AJ24),"x","") | AV24: =IF(AND(AV$6>=$AI24,AV$6<=$AJ24),"x","") | AW24: =IF(AND(AW$6>=$AI24,AW$6<=$AJ24),"x","") | AX24: =IF(AND(AX$6>=$AI24,AX$6<=$AJ24),"x","") | AY24: =IF(AND(AY$6>=$AI24,AY$6<=$AJ24),"x","") | ... BC24: =IF(AND(BC$6>=$AI24,BC$6<=$AJ24),"x","") | BG24: =IF(BE24="","",ROUND((BF24-BE24)/30,0)) | BM24: =SUM(BH24:BL24) -> 0 | BN24: =IF(AND(BN$6>=$BE24,BN$6<=$BF24),"x","") -> x | BO24: =IF(AND(BO$6>=$BE24,BO$6<=$BF24),"x","") -> #VALUE! | BP24: =IF(AND(BP$6>=$BE24,BP$6<=$BF24),"x","") -> #VALUE! | BQ24: =IF(AND(BQ$6>=$BE24,BQ$6<=$BF24),"x","") -> #VALUE! | BR24: =IF(AND(BR$6>=$BE24,BR$6<=$BF24),"x","") -> #VALUE! | BS24: =IF(AND(BS$6>=$BE24,BS$6<=$BF24),"x","") -> #VALUE! | BT24: =IF(AND(BT$6>=$BE24,BT$6<=$BF24),"x","") -> #VALUE! | BU24: =IF(AND(BU$6>=$BE24,BU$6<=$BF24),"x","") -> #VALUE! | ... BY24: =IF(AND(BY$6>=$BE24,BY$6<=$BF24),"x","") -> #VALUE! | CA24: =A24 -> 0 | CB24: =B24 -> 0
F25: =IF(D25="","",ROUND((E25-D25)/30,0)) | U25: =SUM(G25,K25,O25) -> 0 | V25: =IF(AND(V$6>=$D25,V$6<=$E25),"x","") | W25: =IF(AND(W$6>=$D25,W$6<=$E25),"x","") | X25: =IF(AND(X$6>=$D25,X$6<=$E25),"x","") | Y25: =IF(AND(Y$6>=$D25,Y$6<=$E25),"x","") | Z25: =IF(AND(Z$6>=$D25,Z$6<=$E25),"x","") | AA25: =IF(AND(AA$6>=$D25,AA$6<=$E25),"x","") | AB25: =IF(AND(AB$6>=$D25,AB$6<=$E25),"x","") | AC25: =IF(AND(AC$6>=$D25,AC$6<=$E25),"x","") | ... AG25: =IF(AND(AG$6>=$D25,AG$6<=$E25),"x","") | AK25: =IF(AI25="","",ROUND((AJ25-AI25)/30,0)) | AQ25: =SUM(AL25:AP25) -> 0 | AR25: =IF(AND(AR$6>=$AI25,AR$6<=$AJ25),"x","") | AS25: =IF(AND(AS$6>=$AI25,AS$6<=$AJ25),"x","") | AT25: =IF(AND(AT$6>=$AI25,AT$6<=$AJ25),"x","") | AU25: =IF(AND(AU$6>=$AI25,AU$6<=$AJ25),"x","") | AV25: =IF(AND(AV$6>=$AI25,AV$6<=$AJ25),"x","") | AW25: =IF(AND(AW$6>=$AI25,AW$6<=$AJ25),"x","") | AX25: =IF(AND(AX$6>=$AI25,AX$6<=$AJ25),"x","") | AY25: =IF(AND(AY$6>=$AI25,AY$6<=$AJ25),"x","") | ... BC25: =IF(AND(BC$6>=$AI25,BC$6<=$AJ25),"x","") | BG25: =IF(BE25="","",ROUND((BF25-BE25)/30,0)) | BM25: =SUM(BH25:BL25) -> 0 | BN25: =IF(AND(BN$6>=$BE25,BN$6<=$BF25),"x","") -> x | BO25: =IF(AND(BO$6>=$BE25,BO$6<=$BF25),"x","") -> #VALUE! | BP25: =IF(AND(BP$6>=$BE25,BP$6<=$BF25),"x","") -> #VALUE! | BQ25: =IF(AND(BQ$6>=$BE25,BQ$6<=$BF25),"x","") -> #VALUE! | BR25: =IF(AND(BR$6>=$BE25,BR$6<=$BF25),"x","") -> #VALUE! | BS25: =IF(AND(BS$6>=$BE25,BS$6<=$BF25),"x","") -> #VALUE! | BT25: =IF(AND(BT$6>=$BE25,BT$6<=$BF25),"x","") -> #VALUE! | BU25: =IF(AND(BU$6>=$BE25,BU$6<=$BF25),"x","") -> #VALUE! | ... BY25: =IF(AND(BY$6>=$BE25,BY$6<=$BF25),"x","") -> #VALUE! | CA25: =A25 -> 0 | CB25: =B25 -> 0
F26: =IF(D26="","",ROUND((E26-D26)/30,0)) | U26: =SUM(G26,K26,O26) -> 0 | V26: =IF(AND(V$6>=$D26,V$6<=$E26),"x","") | W26: =IF(AND(W$6>=$D26,W$6<=$E26),"x","") | X26: =IF(AND(X$6>=$D26,X$6<=$E26),"x","") | Y26: =IF(AND(Y$6>=$D26,Y$6<=$E26),"x","") | Z26: =IF(AND(Z$6>=$D26,Z$6<=$E26),"x","") | AA26: =IF(AND(AA$6>=$D26,AA$6<=$E26),"x","") | AB26: =IF(AND(AB$6>=$D26,AB$6<=$E26),"x","") | AC26: =IF(AND(AC$6>=$D26,AC$6<=$E26),"x","") | ... AG26: =IF(AND(AG$6>=$D26,AG$6<=$E26),"x","") | AK26: =IF(AI26="","",ROUND((AJ26-AI26)/30,0)) | AQ26: =SUM(AL26:AP26) -> 0 | AR26: =IF(AND(AR$6>=$AI26,AR$6<=$AJ26),"x","") | AS26: =IF(AND(AS$6>=$AI26,AS$6<=$AJ26),"x","") | AT26: =IF(AND(AT$6>=$AI26,AT$6<=$AJ26),"x","") | AU26: =IF(AND(AU$6>=$AI26,AU$6<=$AJ26),"x","") | AV26: =IF(AND(AV$6>=$AI26,AV$6<=$AJ26),"x","") | AW26: =IF(AND(AW$6>=$AI26,AW$6<=$AJ26),"x","") | AX26: =IF(AND(AX$6>=$AI26,AX$6<=$AJ26),"x","") | AY26: =IF(AND(AY$6>=$AI26,AY$6<=$AJ26),"x","") | ... BC26: =IF(AND(BC$6>=$AI26,BC$6<=$AJ26),"x","") | BG26: =IF(BE26="","",ROUND((BF26-BE26)/30,0)) | BM26: =SUM(BH26:BL26) -> 0 | BN26: =IF(AND(BN$6>=$BE26,BN$6<=$BF26),"x","") -> x | BO26: =IF(AND(BO$6>=$BE26,BO$6<=$BF26),"x","") -> #VALUE! | BP26: =IF(AND(BP$6>=$BE26,BP$6<=$BF26),"x","") -> #VALUE! | BQ26: =IF(AND(BQ$6>=$BE26,BQ$6<=$BF26),"x","") -> #VALUE! | BR26: =IF(AND(BR$6>=$BE26,BR$6<=$BF26),"x","") -> #VALUE! | BS26: =IF(AND(BS$6>=$BE26,BS$6<=$BF26),"x","") -> #VALUE! | BT26: =IF(AND(BT$6>=$BE26,BT$6<=$BF26),"x","") -> #VALUE! | BU26: =IF(AND(BU$6>=$BE26,BU$6<=$BF26),"x","") -> #VALUE! | ... BY26: =IF(AND(BY$6>=$BE26,BY$6<=$BF26),"x","") -> #VALUE! | CA26: =A26 -> 0 | CB26: =B26 -> 0
F27: =IF(D27="","",ROUND((E27-D27)/30,0)) | U27: =SUM(G27,K27,O27) -> 0 | V27: =IF(AND(V$6>=$D27,V$6<=$E27),"x","") | W27: =IF(AND(W$6>=$D27,W$6<=$E27),"x","") | X27: =IF(AND(X$6>=$D27,X$6<=$E27),"x","") | Y27: =IF(AND(Y$6>=$D27,Y$6<=$E27),"x","") | Z27: =IF(AND(Z$6>=$D27,Z$6<=$E27),"x","") | AA27: =IF(AND(AA$6>=$D27,AA$6<=$E27),"x","") | AB27: =IF(AND(AB$6>=$D27,AB$6<=$E27),"x","") | AC27: =IF(AND(AC$6>=$D27,AC$6<=$E27),"x","") | ... AG27: =IF(AND(AG$6>=$D27,AG$6<=$E27),"x","") | AK27: =IF(AI27="","",ROUND((AJ27-AI27)/30,0)) | AQ27: =SUM(AL27:AP27) -> 0 | AR27: =IF(AND(AR$6>=$AI27,AR$6<=$AJ27),"x","") | AS27: =IF(AND(AS$6>=$AI27,AS$6<=$AJ27),"x","") | AT27: =IF(AND(AT$6>=$AI27,AT$6<=$AJ27),"x","") | AU27: =IF(AND(AU$6>=$AI27,AU$6<=$AJ27),"x","") | AV27: =IF(AND(AV$6>=$AI27,AV$6<=$AJ27),"x","") | AW27: =IF(AND(AW$6>=$AI27,AW$6<=$AJ27),"x","") | AX27: =IF(AND(AX$6>=$AI27,AX$6<=$AJ27),"x","") | AY27: =IF(AND(AY$6>=$AI27,AY$6<=$AJ27),"x","") | ... BC27: =IF(AND(BC$6>=$AI27,BC$6<=$AJ27),"x","") | BG27: =IF(BE27="","",ROUND((BF27-BE27)/30,0)) | BM27: =SUM(BH27:BL27) -> 0 | BN27: =IF(AND(BN$6>=$BE27,BN$6<=$BF27),"x","") -> x | BO27: =IF(AND(BO$6>=$BE27,BO$6<=$BF27),"x","") -> #VALUE! | BP27: =IF(AND(BP$6>=$BE27,BP$6<=$BF27),"x","") -> #VALUE! | BQ27: =IF(AND(BQ$6>=$BE27,BQ$6<=$BF27),"x","") -> #VALUE! | BR27: =IF(AND(BR$6>=$BE27,BR$6<=$BF27),"x","") -> #VALUE! | BS27: =IF(AND(BS$6>=$BE27,BS$6<=$BF27),"x","") -> #VALUE! | BT27: =IF(AND(BT$6>=$BE27,BT$6<=$BF27),"x","") -> #VALUE! | BU27: =IF(AND(BU$6>=$BE27,BU$6<=$BF27),"x","") -> #VALUE! | ... BY27: =IF(AND(BY$6>=$BE27,BY$6<=$BF27),"x","") -> #VALUE! | CA27: =A27 -> 0 | CB27: =B27 -> 0
... F36: =IF(D36="","",ROUND((E36-D36)/30,0)) | U36: =SUM(G36,K36,O36) -> 0 | V36: =IF(AND(V$6>=$D36,V$6<=$E36),"x","") | W36: =IF(AND(W$6>=$D36,W$6<=$E36),"x","") | X36: =IF(AND(X$6>=$D36,X$6<=$E36),"x","") | Y36: =IF(AND(Y$6>=$D36,Y$6<=$E36),"x","") | Z36: =IF(AND(Z$6>=$D36,Z$6<=$E36),"x","") | AA36: =IF(AND(AA$6>=$D36,AA$6<=$E36),"x","") | AB36: =IF(AND(AB$6>=$D36,AB$6<=$E36),"x","") | AC36: =IF(AND(AC$6>=$D36,AC$6<=$E36),"x","") | ... AG36: =IF(AND(AG$6>=$D36,AG$6<=$E36),"x","") | AK36: =IF(AI36="","",ROUND((AJ36-AI36)/30,0)) | AQ36: =SUM(AL36:AP36) -> 0 | AR36: =IF(AND(AR$6>=$AI36,AR$6<=$AJ36),"x","") | AS36: =IF(AND(AS$6>=$AI36,AS$6<=$AJ36),"x","") | AT36: =IF(AND(AT$6>=$AI36,AT$6<=$AJ36),"x","") | AU36: =IF(AND(AU$6>=$AI36,AU$6<=$AJ36),"x","") | AV36: =IF(AND(AV$6>=$AI36,AV$6<=$AJ36),"x","") | AW36: =IF(AND(AW$6>=$AI36,AW$6<=$AJ36),"x","") | AX36: =IF(AND(AX$6>=$AI36,AX$6<=$AJ36),"x","") | AY36: =IF(AND(AY$6>=$AI36,AY$6<=$AJ36),"x","") | ... BC36: =IF(AND(BC$6>=$AI36,BC$6<=$AJ36),"x","") | BG36: =IF(BE36="","",ROUND((BF36-BE36)/30,0)) | BM36: =SUM(BH36:BL36) -> 0 | BN36: =IF(AND(BN$6>=$BE36,BN$6<=$BF36),"x","") -> x | BO36: =IF(AND(BO$6>=$BE36,BO$6<=$BF36),"x","") -> #VALUE! | BP36: =IF(AND(BP$6>=$BE36,BP$6<=$BF36),"x","") -> #VALUE! | BQ36: =IF(AND(BQ$6>=$BE36,BQ$6<=$BF36),"x","") -> #VALUE! | BR36: =IF(AND(BR$6>=$BE36,BR$6<=$BF36),"x","") -> #VALUE! | BS36: =IF(AND(BS$6>=$BE36,BS$6<=$BF36),"x","") -> #VALUE! | BT36: =IF(AND(BT$6>=$BE36,BT$6<=$BF36),"x","") -> #VALUE! | BU36: =IF(AND(BU$6>=$BE36,BU$6<=$BF36),"x","") -> #VALUE! | ... BY36: =IF(AND(BY$6>=$BE36,BY$6<=$BF36),"x","") -> #VALUE! | CA36: =A36 -> 0 | CB36: =B36 -> 0
F37: Summe PM | G37: =SUM(G8:G36) -> 4 | K37: =SUM(K8:K36) -> 1.5 | O37: =SUM(O8:O36) -> 2.5 | S37: =SUM(S8:S36) -> 0 | T37: =SUM(T8:T36) -> 0 | U37: =SUM(U8:U36) -> 8 | V37: =SUM(V39:AG39) -> 0 | AK37: PM | AL37: =SUM(AL8:AL36) -> 0 | AM37: =SUM(AM8:AM36) -> 0 | AN37: =SUM(AN8:AN36) -> 0 | AO37: =SUM(AO8:AO36) -> 0 | AP37: =SUM(AP8:AP36) -> 0 | AQ37: =SUM(AQ8:AQ36) -> 0 | AR37: =SUM(AR39:BC39) -> 0 | BG37: PM | BH37: =SUM(BH8:BH36) -> 0 | BI37: =SUM(BI8:BI36) -> 0 | BJ37: =SUM(BJ8:BJ36) -> 0 | BK37: =SUM(BK8:BK36) -> 0 | BL37: =SUM(BL8:BL36) -> 0 | BM37: =SUM(BM8:BM36) -> 0 | BN37: =SUM(BN39:BY39) -> #VALUE!
F38: Summe h | H38: =SUM(H8:H36) -> 693.33333 | I38: =SUM(I8:I36) -> 645.336 | J38: =SUM(J8:J36) -> 47.997333 | L38: =SUM(L8:L36) -> 260 | M38: =SUM(M8:M36) -> 552.17 | N38: =SUM(N8:N36) -> -292.17 | P38: =SUM(P8:P36) -> 216.66667 | Q38: =SUM(Q8:Q36) -> 360 | R38: =SUM(R8:R36) -> -143.33333
F39: € | G39: =G37*G7 -> 40000 | H39: =H38*'Planung Personal'!$W$9 -> 39998.4 | I39: =I38*'Planung Personal'!$W$9 -> 37229.434 | J39: =J38*'Planung Personal'!$W$9 -> 2768.9662 | K39: =K37*K7 -> 4837.5 | L39: =L38*'Planung Personal'!$W$11 -> 4838.6 | M39: =M38*'Planung Personal'!$W$11 -> 10275.884 | N39: =N38*'Planung Personal'!$W$11 -> -5437.2837 | O39: =O37*O7 -> 7437.5 | P39: =P38*'Planung Personal'!$W$13 -> 7438.1667 | Q39: =Q38*'Planung Personal'!$W$13 -> 12358.8 | R39: =R38*'Planung Personal'!$W$13 -> -4920.6333 | S39: =S37*S7 -> 0 | T39: =T37*T7 -> 0 | V39: =SUM(V9:V12,V14:V17,V19:V24,V26:V30,V32:V36) -> 0 | W39: =SUM(W9:W12,W14:W17,W19:W24,W26:W30,W32:W36) -> 0 | X39: =SUM(X9:X12,X14:X17,X19:X24,X26:X30,X32:X36) -> 0 | Y39: =SUM(Y9:Y12,Y14:Y17,Y19:Y24,Y26:Y30,Y32:Y36) -> 0 | Z39: =SUM(Z9:Z12,Z14:Z17,Z19:Z24,Z26:Z30,Z32:Z36) -> 0 | AA39: =SUM(AA9:AA12,AA14:AA17,AA19:AA24,AA26:AA30,AA32:AA36) -> 0 | AB39: =SUM(AB9:AB12,AB14:AB17,AB19:AB24,AB26:AB30,AB32:AB36) -> 0 | AC39: =SUM(AC9:AC12,AC14:AC17,AC19:AC24,AC26:AC30,AC32:AC36) -> 0 | ... AG39: =SUM(AG9:AG12,AG14:AG17,AG19:AG24,AG26:AG30,AG32:AG36) -> 0 | AK39: € | AL39: =AL37*AL7 -> 0 | AM39: =AM37*AM7 -> 0 | AN39: =AN37*AN7 -> 0 | AO39: =AO37*AO7 -> 0 | AP39: =AP37*AP7 -> 0 | AR39: =SUM(AR9:AR12,AR14:AR17,AR19:AR24,AR26:AR30,AR32:AR36) -> 0 | AS39: =SUM(AS9:AS12,AS14:AS17,AS19:AS24,AS26:AS30,AS32:AS36) -> 0 | AT39: =SUM(AT9:AT12,AT14:AT17,AT19:AT24,AT26:AT30,AT32:AT36) -> 0 | AU39: =SUM(AU9:AU12,AU14:AU17,AU19:AU24,AU26:AU30,AU32:AU36) -> 0 | AV39: =SUM(AV9:AV12,AV14:AV17,AV19:AV24,AV26:AV30,AV32:AV36) -> 0 | AW39: =SUM(AW9:AW12,AW14:AW17,AW19:AW24,AW26:AW30,AW32:AW36) -> 0 | AX39: =SUM(AX9:AX12,AX14:AX17,AX19:AX24,AX26:AX30,AX32:AX36) -> 0 | AY39: =SUM(AY9:AY12,AY14:AY17,AY19:AY24,AY26:AY30,AY32:AY36) -> 0 | ... BC39: =SUM(BC9:BC12,BC14:BC17,BC19:BC24,BC26:BC30,BC32:BC36) -> 0 | BG39: € | BH39: =BH37*BH7 -> 0 | BI39: =BI37*BI7 -> 0 | BJ39: =BJ37*BJ7 -> 0 | BK39: =BK37*BK7 -> 0 | BL39: =BL37*BL7 -> 0 | BN39: =SUM(BN9:BN12,BN14:BN17,BN19:BN24,BN26:BN30,BN32:BN36) -> 0 | BO39: =SUM(BO9:BO12,BO14:BO17,BO19:BO24,BO26:BO30,BO32:BO36) -> #VALUE! | BP39: =SUM(BP9:BP12,BP14:BP17,BP19:BP24,BP26:BP30,BP32:BP36) -> #VALUE! | BQ39: =SUM(BQ9:BQ12,BQ14:BQ17,BQ19:BQ24,BQ26:BQ30,BQ32:BQ36) -> #VALUE! | BR39: =SUM(BR9:BR12,BR14:BR17,BR19:BR24,BR26:BR30,BR32:BR36) -> #VALUE! | BS39: =SUM(BS9:BS12,BS14:BS17,BS19:BS24,BS26:BS30,BS32:BS36) -> #VALUE! | BT39: =SUM(BT9:BT12,BT14:BT17,BT19:BT24,BT26:BT30,BT32:BT36) -> #VALUE! | BU39: =SUM(BU9:BU12,BU14:BU17,BU19:BU24,BU26:BU30,BU32:BU36) -> #VALUE! | ... BY39: =SUM(BY9:BY12,BY14:BY17,BY19:BY24,BY26:BY30,BY32:BY36) -> #VALUE!
F40: ZA gesamt | G40: =SUM(I39,M39,Q39) -> 59864.118 | V40: =SUM(V39:AG39) -> 0 | AK40: € gesamt | AL40: =SUM(AL39:AP39) -> 0 | AR40: =SUM(AR39:BC39) -> 0 | BG40: € gesamt | BH40: =SUM(BH39:BL39) -> 0 | BN40: =SUM(BN39:BY39) -> #VALUE!
F42: PM max | G42: 0 | K42: 0 | R42: T | U42: =SUMIF($C$8:$U$36,"x",$U$8:$U$36) -> 6 | AK42: PM max | AL42: 0 | AM42: 0 | BG42: PM max | BH42: 0 | BI42: 0
R43: NT | U43: =U37-U42 -> 2
A45: 1 | B45: 2 | C45: 3 | D45: 4 | E45: 5 | F45: 6 | G45: 7 | H45: 8 | I45: 9 | J45: 10 | K45: 11 | L45: 12 | M45: 13 | N45: 14 | O45: 15 | P45: 16 | Q45: 17 | R45: 18 | S45: 19 | T45: 20 | U45: 21 | V45: 22 | W45: 23 | X45: 24 | Y45: 25 | Z45: 26 | AA45: 27 | AB45: 28 | AC45: 29 | AD45: 30 | AE45: 31 | AF45: 32 | AG45: 33 | AH45: 34 | AI45: 35 | AJ45: 36 | AK45: 37 | AL45: 38 | AM45: 39 | AN45: 40 | AO45: 41 | AP45: 42 | AQ45: 43 | AR45: 44 | AS45: 45 | AT45: 46 | AU45: 47 | AV45: 48 | AW45: 49 | AX45: 50 | AY45: 51 | AZ45: 52 | BA45: 53 | BB45: 54 | BC45: 55 | BD45: 56 | BE45: 57 | BF45: 58 | BG45: 59 | BH45: 60 | BI45: 61 | BJ45: 62 | BK45: 63 | BL45: 64 | BM45: 65 | BN45: 66 | BO45: 67 | BP45: 68 | BQ45: 69 | BR45: 70 | BS45: 71 | BT45: 72 | BU45: 73 | BV45: 74 | BW45: 75 | BX45: 76 | BY45: 77 | BZ45: 78 | CA45: 79
G50: =G37*173.33 -> 693.32 | K50: =K37*173.33 -> 259.995 | O50: =2.5*173.33/2 -> 216.6625 | Q50: =SUM(G50:O50) -> 1169.9775
D83: 1 | E83: 2 | F83: 3 | G83: 4 | K83: 5 | O83: 6 | S83: 6 | T83: 6 | U83: 7 | V83: 8 | W83: 9 | X83: 10 | Y83: 11 | Z83: 12 | AA83: 13 | AB83: 14 | AC83: 15 | AD83: 16 | AE83: 17 | AF83: 18 | AG83: 19 | AH83: 20 | AI83: 21 | AJ83: 22 | AK83: 23 | AL83: 24 | AM83: 25 | AN83: 26 | AO83: 6 | AP83: 6 | AQ83: 27 | AR83: 28 | AS83: 29 | AT83: 30 | AU83: 31 | AV83: 32 | AW83: 33 | AX83: 34 | AY83: 35 | AZ83: 36 | BA83: 37 | BB83: 38 | BC83: 39 | BD83: 40 | BE83: 41 | BF83: 42 | BG83: 43 | BH83: 44 | BI83: 45 | BJ83: 46 | BK83: 6 | BL83: 6 | BM83: 47 | BN83: 48 | BO83: 49 | BP83: 50 | BQ83: 51 | BR83: 52 | BS83: 53 | BT83: 54 | BU83: 55 | BV83: 56 | BW83: 57 | BX83: 58 | BY83: 59 | BZ83: 60 | CA83: 61 | CB83: 62
T84: von | U84: bis | V84: Jan | W84: Feb | X84: Mrz | Y84: Apr | Z84: Mai | AA84: Jun | AB84: Jul | AC84: Aug | AD84: Sep | AE84: Okt | AF84: Nov | AG84: Dez | AH84: AP | AP84: von | AQ84: bis | AR84: Jan | AS84: Feb | AT84: Mrz | AU84: Apr | AV84: Mai | AW84: Jun | AX84: Jul | AY84: Aug | AZ84: Sep | BA84: Okt | BB84: Nov | BC84: Dez | BD84: AP | BL84: von | BM84: bis | BN84: Jan | BO84: Feb | BP84: Mrz | BQ84: Apr | BR84: Mai | BS84: Jun | BT84: Jul | BU84: Aug | BV84: Sep | BW84: Okt | BX84: Nov | BY84: Dez | BZ84: AP
V85: =V6 -> 44927 | W85: =W6 -> 44958 | X85: =X6 -> 44986 | Y85: =Y6 -> 45017 | Z85: =Z6 -> 45047 | AA85: =AA6 -> 45078 | AB85: =AB6 -> 45108 | AC85: =AC6 -> 45139 | ... AG85: =AG6 -> 45261 | AR85: =AR6 -> 45412 | AS85: =AS6 -> 45443 | AT85: =AT6 -> 45472 | AU85: =AU6 -> 45503 | AV85: =AV6 -> 45533 | AW85: =AW6 -> 45564 | AX85: =AX6 -> 45594 | AY85: =AY6 -> 45625 | ... BC85: =BC6 -> 45747 | BN85: =BN6 | BO85: =BO6 -> #VALUE! | BP85: =BP6 -> #VALUE! | BQ85: =BQ6 -> #VALUE! | BR85: =BR6 -> #VALUE! | BS85: =BS6 -> #VALUE! | BT85: =BT6 -> #VALUE! | BU85: =BU6 -> #VALUE! | ... BY85: =BY6 -> #VALUE! | BZ85: =$A7 -> 0
T86: =$D8 -> 45047 | U86: =$E8 -> 45077 | V86: =V8 | W86: =W8 | X86: =X8 | Y86: =Y8 | Z86: =Z8 -> x | AA86: =AA8 | AB86: =AB8 | AC86: =AC8 | ... AG86: =AG8 | AH86: =$A8 -> 1 | AP86: =$AI8 -> 0 | AQ86: =$AJ8 -> 0 | AR86: =AR8 | AS86: =AS8 | AT86: =AT8 | AU86: =AU8 | AV86: =AV8 | AW86: =AW8 | AX86: =AX8 | AY86: =AY8 | ... BC86: =BC8 | BD86: =$A8 -> 1 | BL86: =$BE8 -> 0 | BM86: =$BF8 -> 0 | BN86: =BN8 -> x | BO86: =BO8 -> #VALUE! | BP86: =BP8 -> #VALUE! | BQ86: =BQ8 -> #VALUE! | BR86: =BR8 -> #VALUE! | BS86: =BS8 -> #VALUE! | BT86: =BT8 -> #VALUE! | BU86: =BU8 -> #VALUE! | ... BY86: =BY8 -> #VALUE! | BZ86: =$A8 -> 1
T87: =$D9 -> 45047 | U87: =$E9 -> 45077 | V87: =V9 | W87: =W9 | X87: =X9 | Y87: =Y9 | Z87: =Z9 -> x | AA87: =AA9 | AB87: =AB9 | AC87: =AC9 | ... AG87: =AG9 | AH87: =$A9 -> 2.1 | AP87: =$AI9 -> 0 | AQ87: =$AJ9 -> 0 | AR87: =AR9 | AS87: =AS9 | AT87: =AT9 | AU87: =AU9 | AV87: =AV9 | AW87: =AW9 | AX87: =AX9 | AY87: =AY9 | ... BC87: =BC9 | BD87: =$A9 -> 2.1 | BL87: =$BE9 -> 0 | BM87: =$BF9 -> 0 | BN87: =BN9 -> x | BO87: =BO9 -> #VALUE! | BP87: =BP9 -> #VALUE! | BQ87: =BQ9 -> #VALUE! | BR87: =BR9 -> #VALUE! | BS87: =BS9 -> #VALUE! | BT87: =BT9 -> #VALUE! | BU87: =BU9 -> #VALUE! | ... BY87: =BY9 -> #VALUE! | BZ87: =$A9 -> 2.1
T88: =$D10 -> 45047 | U88: =$E10 -> 45077 | V88: =V10 | W88: =W10 | X88: =X10 | Y88: =Y10 | Z88: =Z10 -> x | AA88: =AA10 | AB88: =AB10 | AC88: =AC10 | ... AG88: =AG10 | AH88: =$A10 -> 2.2 | AP88: =$AI10 -> 0 | AQ88: =$AJ10 -> 0 | AR88: =AR10 | AS88: =AS10 | AT88: =AT10 | AU88: =AU10 | AV88: =AV10 | AW88: =AW10 | AX88: =AX10 | AY88: =AY10 | ... BC88: =BC10 | BD88: =$A10 -> 2.2 | BL88: =$BE10 -> 0 | BM88: =$BF10 -> 0 | BN88: =BN10 -> x | BO88: =BO10 -> #VALUE! | BP88: =BP10 -> #VALUE! | BQ88: =BQ10 -> #VALUE! | BR88: =BR10 -> #VALUE! | BS88: =BS10 -> #VALUE! | BT88: =BT10 -> #VALUE! | BU88: =BU10 -> #VALUE! | ... BY88: =BY10 -> #VALUE! | BZ88: =$A10 -> 2.2
T89: =$D11 -> 45231 | U89: =$E11 -> 45260 | V89: =V11 | W89: =W11 | X89: =X11 | Y89: =Y11 | Z89: =Z11 | AA89: =AA11 | AB89: =AB11 | AC89: =AC11 | ... AG89: =AG11 | AH89: =$A11 -> 3 | AP89: =$AI11 -> 0 | AQ89: =$AJ11 -> 0 | AR89: =AR11 | AS89: =AS11 | AT89: =AT11 | AU89: =AU11 | AV89: =AV11 | AW89: =AW11 | AX89: =AX11 | AY89: =AY11 | ... BC89: =BC11 | BD89: =$A11 -> 3 | BL89: =$BE11 -> 0 | BM89: =$BF11 -> 0 | BN89: =BN11 -> x | BO89: =BO11 -> #VALUE! | BP89: =BP11 -> #VALUE! | BQ89: =BQ11 -> #VALUE! | BR89: =BR11 -> #VALUE! | BS89: =BS11 -> #VALUE! | BT89: =BT11 -> #VALUE! | BU89: =BU11 -> #VALUE! | ... BY89: =BY11 -> #VALUE! | BZ89: =$A11 -> 3
T90: =$D12 -> 45078 | U90: =$E12 -> 45107 | V90: =V12 | W90: =W12 | X90: =X12 | Y90: =Y12 | Z90: =Z12 | AA90: =AA12 -> x | AB90: =AB12 | AC90: =AC12 | ... AG90: =AG12 | AH90: =$A12 -> 4.1 | AP90: =$AI12 -> 0 | AQ90: =$AJ12 -> 0 | AR90: =AR12 | AS90: =AS12 | AT90: =AT12 | AU90: =AU12 | AV90: =AV12 | AW90: =AW12 | AX90: =AX12 | AY90: =AY12 | ... BC90: =BC12 | BD90: =$A12 -> 4.1 | BL90: =$BE12 -> 0 | BM90: =$BF12 -> 0 | BN90: =BN12 -> x | BO90: =BO12 -> #VALUE! | BP90: =BP12 -> #VALUE! | BQ90: =BQ12 -> #VALUE! | BR90: =BR12 -> #VALUE! | BS90: =BS12 -> #VALUE! | BT90: =BT12 -> #VALUE! | BU90: =BU12 -> #VALUE! | ... BY90: =BY12 -> #VALUE! | BZ90: =$A12 -> 4.1
T91: =$D13 -> 45108 | U91: =$E13 -> 45169 | V91: =V13 | W91: =W13 | X91: =X13 | Y91: =Y13 | Z91: =Z13 | AA91: =AA13 | AB91: =AB13 -> x | AC91: =AC13 -> x | ... AG91: =AG13 | AH91: =$A13 -> 4.2 | AP91: =$AI13 -> 0 | AQ91: =$AJ13 -> 0 | AR91: =AR13 | AS91: =AS13 | AT91: =AT13 | AU91: =AU13 | AV91: =AV13 | AW91: =AW13 | AX91: =AX13 | AY91: =AY13 | ... BC91: =BC13 | BD91: =$A13 -> 4.2 | BL91: =$BE13 -> 0 | BM91: =$BF13 -> 0 | BN91: =BN13 -> x | BO91: =BO13 -> #VALUE! | BP91: =BP13 -> #VALUE! | BQ91: =BQ13 -> #VALUE! | BR91: =BR13 -> #VALUE! | BS91: =BS13 -> #VALUE! | BT91: =BT13 -> #VALUE! | BU91: =BU13 -> #VALUE! | ... BY91: =BY13 -> #VALUE! | BZ91: =$A13 -> 4.2
T92: =$D14 -> 45170 | U92: =$E14 -> 45230 | V92: =V14 | W92: =W14 | X92: =X14 | Y92: =Y14 | Z92: =Z14 | AA92: =AA14 | AB92: =AB14 | AC92: =AC14 | ... AG92: =AG14 | AH92: =$A14 -> 4.3 | AP92: =$AI14 -> 0 | AQ92: =$AJ14 -> 0 | AR92: =AR14 | AS92: =AS14 | AT92: =AT14 | AU92: =AU14 | AV92: =AV14 | AW92: =AW14 | AX92: =AX14 | AY92: =AY14 | ... BC92: =BC14 | BD92: =$A14 -> 4.3 | BL92: =$BE14 -> 0 | BM92: =$BF14 -> 0 | BN92: =BN14 -> x | BO92: =BO14 -> #VALUE! | BP92: =BP14 -> #VALUE! | BQ92: =BQ14 -> #VALUE! | BR92: =BR14 -> #VALUE! | BS92: =BS14 -> #VALUE! | BT92: =BT14 -> #VALUE! | BU92: =BU14 -> #VALUE! | ... BY92: =BY14 -> #VALUE! | BZ92: =$A14 -> 4.3
T93: =$D15 -> 45231 | U93: =$E15 -> 45289 | V93: =V15 | W93: =W15 | X93: =X15 | Y93: =Y15 | Z93: =Z15 | AA93: =AA15 | AB93: =AB15 | AC93: =AC15 | ... AG93: =AG15 -> x | AH93: =$A15 -> 5 | AP93: =$AI15 -> 0 | AQ93: =$AJ15 -> 0 | AR93: =AR15 | AS93: =AS15 | AT93: =AT15 | AU93: =AU15 | AV93: =AV15 | AW93: =AW15 | AX93: =AX15 | AY93: =AY15 | ... BC93: =BC15 | BD93: =$A15 -> 5 | BL93: =$BE15 -> 0 | BM93: =$BF15 -> 0 | BN93: =BN15 -> x | BO93: =BO15 -> #VALUE! | BP93: =BP15 -> #VALUE! | BQ93: =BQ15 -> #VALUE! | BR93: =BR15 -> #VALUE! | BS93: =BS15 -> #VALUE! | BT93: =BT15 -> #VALUE! | BU93: =BU15 -> #VALUE! | ... BY93: =BY15 -> #VALUE! | BZ93: =$A15 -> 5
T94: =$D16 -> 0 | U94: =$E16 -> 0 | V94: =V16 | W94: =W16 | X94: =X16 | Y94: =Y16 | Z94: =Z16 | AA94: =AA16 | AB94: =AB16 | AC94: =AC16 | ... AG94: =AG16 | AH94: =$A16 -> 0 | AP94: =$AI16 -> 0 | AQ94: =$AJ16 -> 0 | AR94: =AR16 | AS94: =AS16 | AT94: =AT16 | AU94: =AU16 | AV94: =AV16 | AW94: =AW16 | AX94: =AX16 | AY94: =AY16 | ... BC94: =BC16 | BD94: =$A16 -> 0 | BL94: =$BE16 -> 0 | BM94: =$BF16 -> 0 | BN94: =BN16 -> x | BO94: =BO16 -> #VALUE! | BP94: =BP16 -> #VALUE! | BQ94: =BQ16 -> #VALUE! | BR94: =BR16 -> #VALUE! | BS94: =BS16 -> #VALUE! | BT94: =BT16 -> #VALUE! | BU94: =BU16 -> #VALUE! | ... BY94: =BY16 -> #VALUE! | BZ94: =$A16 -> 0
T95: =$D17 -> 0 | U95: =$E17 -> 0 | V95: =V17 | W95: =W17 | X95: =X17 | Y95: =Y17 | Z95: =Z17 | AA95: =AA17 | AB95: =AB17 | AC95: =AC17 | ... AG95: =AG17 | AH95: =$A17 -> 0 | AP95: =$AI17 -> 0 | AQ95: =$AJ17 -> 0 | AR95: =AR17 | AS95: =AS17 | AT95: =AT17 | AU95: =AU17 | AV95: =AV17 | AW95: =AW17 | AX95: =AX17 | AY95: =AY17 | ... BC95: =BC17 | BD95: =$A17 -> 0 | BL95: =$BE17 -> 0 | BM95: =$BF17 -> 0 | BN95: =BN17 -> x | BO95: =BO17 -> #VALUE! | BP95: =BP17 -> #VALUE! | BQ95: =BQ17 -> #VALUE! | BR95: =BR17 -> #VALUE! | BS95: =BS17 -> #VALUE! | BT95: =BT17 -> #VALUE! | BU95: =BU17 -> #VALUE! | ... BY95: =BY17 -> #VALUE! | BZ95: =$A17 -> 0
T96: =$D18 -> 0 | U96: =$E18 -> 0 | V96: =V18 | W96: =W18 | X96: =X18 | Y96: =Y18 | Z96: =Z18 | AA96: =AA18 | AB96: =AB18 | AC96: =AC18 | ... AG96: =AG18 | AH96: =$A18 -> 0 | AP96: =$AI18 -> 0 | AQ96: =$AJ18 -> 0 | AR96: =AR18 | AS96: =AS18 | AT96: =AT18 | AU96: =AU18 | AV96: =AV18 | AW96: =AW18 | AX96: =AX18 | AY96: =AY18 | ... BC96: =BC18 | BD96: =$A18 -> 0 | BL96: =$BE18 -> 0 | BM96: =$BF18 -> 0 | BN96: =BN18 -> x | BO96: =BO18 -> #VALUE! | BP96: =BP18 -> #VALUE! | BQ96: =BQ18 -> #VALUE! | BR96: =BR18 -> #VALUE! | BS96: =BS18 -> #VALUE! | BT96: =BT18 -> #VALUE! | BU96: =BU18 -> #VALUE! | ... BY96: =BY18 -> #VALUE! | BZ96: =$A18 -> 0
T97: =$D19 -> 0 | U97: =$E19 -> 0 | V97: =V19 | W97: =W19 | X97: =X19 | Y97: =Y19 | Z97: =Z19 | AA97: =AA19 | AB97: =AB19 | AC97: =AC19 | ... AG97: =AG19 | AH97: =$A19 -> 0 | AP97: =$AI19 -> 0 | AQ97: =$AJ19 -> 0 | AR97: =AR19 | AS97: =AS19 | AT97: =AT19 | AU97: =AU19 | AV97: =AV19 | AW97: =AW19 | AX97: =AX19 | AY97: =AY19 | ... BC97: =BC19 | BD97: =$A19 -> 0 | BL97: =$BE19 -> 0 | BM97: =$BF19 -> 0 | BN97: =BN19 -> x | BO97: =BO19 -> #VALUE! | BP97: =BP19 -> #VALUE! | BQ97: =BQ19 -> #VALUE! | BR97: =BR19 -> #VALUE! | BS97: =BS19 -> #VALUE! | BT97: =BT19 -> #VALUE! | BU97: =BU19 -> #VALUE! | ... BY97: =BY19 -> #VALUE! | BZ97: =$A19 -> 0
... T114: =$D36 -> 0 | U114: =$E36 -> 0 | V114: =V36 | W114: =W36 | X114: =X36 | Y114: =Y36 | Z114: =Z36 | AA114: =AA36 | AB114: =AB36 | AC114: =AC36 | ... AG114: =AG36 | AH114: =$A36 -> 0 | AP114: =$AI36 -> 0 | AQ114: =$AJ36 -> 0 | AR114: =AR36 | AS114: =AS36 | AT114: =AT36 | AU114: =AU36 | AV114: =AV36 | AW114: =AW36 | AX114: =AX36 | AY114: =AY36 | ... BC114: =BC36 | BD114: =$A36 -> 0 | BL114: =$BE36 -> 0 | BM114: =$BF36 -> 0 | BN114: =BN36 -> x | BO114: =BO36 -> #VALUE! | BP114: =BP36 -> #VALUE! | BQ114: =BQ36 -> #VALUE! | BR114: =BR36 -> #VALUE! | BS114: =BS36 -> #VALUE! | BT114: =BT36 -> #VALUE! | BU114: =BU36 -> #VALUE! | ... BY114: =BY36 -> #VALUE! | BZ114: =$A36 -> 0

Sheet Planung Personal
A2: Jahresvorkalkulation Personalkosten
A4: =Nav!H16 -> 45047 | B4: =Nav!H16 -> 45047
B5: Name MA | D5: Monat
C6: tech-nisch | D6: =DATE(YEAR(B4),1,1) -> 44927 | E6: =D6+31 -> 44958 | F6: =IF((MOD(YEAR(E6),4)=0)-(MOD(YEAR(E6),100)=0)+(MOD(YEAR(E6),400)=0)=0,E6+28,E6+29) -> 44986 | G6: =F6+31 -> 45017 | H6: =G6+30 -> 45047 | I6: =H6+31 -> 45078 | J6: =I6+30 -> 45108 | K6: =J6+31 -> 45139 | L6: =K6+31 -> 45170 | M6: =L6+30 -> 45200 | N6: =M6+31 -> 45231 | O6: =N6+30 -> 45261 | P6: Summe PM/MA | R6: Kategorie bzw. Personalqualifikation | S6: Vorkalkulierter Personaleinsatz (Stunden) | T6: Jahresbruttogehalt | U6: Wochenarbeits-stunden | V6: Jahresarbeits-stunden | W6: Stundensatz | X6: Einzelkosten | Y6: Zuschlagsatz in % | Z6: Zuschlag | AA6: Gesamt
R7: Gehälter
B9: =Nav!B32 -> Tippl, Mario | C9: x | I9: 0.5 | J9: 0.5 | K9: 0.5 | L9: 0.5 | M9: 0.5 | P9: =SUM(D9:O9) -> 2.5 | R9: =$B$9 -> Tippl, Mario | S9: =(P9*V9/12) -> 433.33333 | T9: =10000*12 -> 120000 | U9: 40 | V9: =U9*52 -> 2080 | W9: =IF(V9=0,"0,00 €",ROUND(T9/V9,2)) -> 57.69 | X9: =(S9*W9) -> 24999 | Y9: =Nav!$M$12 -> 0.2842 | Z9: =ROUND(X9*Y9,2) -> 7104.72 | AA9: =Z9+X9 -> 32103.72
H10: 0.5 | N10: 0.5 | O10: 0.5 | P10: =SUM(D10:O10) -> 1.5 | S10: =(P10*V9/12) -> 260 | X10: =(S10*W9) -> 14999.4 | Y10: =Nav!$M$13 -> 0.2988 | Z10: =ROUND(X10*Y10,2) -> 4481.82 | AA10: =Z10+X10 -> 19481.22
B11: =Nav!B33 -> Socha, Pawel | C11: x | J11: 0.5 | K11: 0.5 | P11: =SUM(D11:O11) -> 1 | R11: =$B$11 -> Socha, Pawel | S11: =(P11*V11/12) -> 173.33333 | T11: =3225*12 -> 38700 | U11: 40 | V11: =U11*52 -> 2080 | W11: =IF(V11=0,"0,00 €",ROUND(T11/V11,2)) -> 18.61 | X11: =(S11*W11) -> 3225.7333 | Y11: =Nav!$M$12 -> 0.2842 | Z11: =ROUND(X11*Y11,2) -> 916.75 | AA11: =Z11+X11 -> 4142.4833
H12: 0.5 | P12: =SUM(D12:O12) -> 0.5 | S12: =(P12*V11/12) -> 86.666667 | X12: =(S12*W11) -> 1612.8667 | Y12: =Nav!$M$13 -> 0.2988 | Z12: =ROUND(X12*Y12,2) -> 481.92 | AA12: =Z12+X12 -> 2094.7867
B13: =Nav!B34 -> Tippl, Karen | C13: x | I13: 0.5 | J13: 0.5 | K13: 0.5 | L13: 0.5 | M13: 0.5 | P13: =SUM(D13:O13) -> 2.5 | R13: =$B$13 -> Tippl, Karen | S13: =(P13*V13/12) -> 216.66667 | T13: =2975*12 -> 35700 | U13: 20 | V13: =U13*52 -> 1040 | W13: =IF(V13=0,"0,00 €",ROUND(T13/V13,2)) -> 34.33 | X13: =(S13*W13) -> 7438.1667 | Y13: =Nav!$M$12 -> 0.2842 | Z13: =ROUND(X13*Y13,2) -> 2113.93 | AA13: =Z13+X13 -> 9552.0967
P14: =SUM(D14:O14) -> 0 | S14: =(P14*V13/12) -> 0 | X14: =(S14*W13) -> 0 | Y14: =Nav!$M$13 -> 0.2988 | Z14: =ROUND(X14*Y14,2) -> 0 | AA14: =Z14+X14 -> 0
B15: =Nav!B35 -> MA 4 | C15: x | P15: =SUM(D15:O15) -> 0 | R15: =$B$15 -> MA 4 | S15: =(P15*V15/12) -> 0 | V15: =U15*52 -> 0 | W15: =IF(V15=0,"0,00 €",ROUND(T15/V15,2)) -> 0,00 € | X15: =(S15*W15) -> 0 | Y15: =Nav!$M$12 -> 0.2842 | Z15: =ROUND(X15*Y15,2) -> 0 | AA15: =Z15+X15 -> 0
P16: =SUM(D16:O16) -> 0 | S16: =(P16*V15/12) -> 0 | X16: =(S16*W15) -> 0 | Y16: =Nav!$M$13 -> 0.2988 | Z16: =ROUND(X16*Y16,2) -> 0 | AA16: =Z16+X16 -> 0
B17: =Nav!B36 -> MA 5 | C17: x | P17: =SUM(D17:O17) -> 0 | R17: =$B$17 -> MA 5 | S17: =(P17*V17/12) -> 0 | V17: =U17*52 -> 0 | W17: =IF(V17=0,"0,00 €",ROUND(T17/V17,2)) -> 0,00 € | X17: =(S17*W17) -> 0 | Y17: =Nav!$M$12 -> 0.2842 | Z17: =ROUND(X17*Y17,2) -> 0 | AA17: =Z17+X17 -> 0
P18: =SUM(D18:O18) -> 0 | S18: =(P18*V17/12) -> 0 | X18: =(S18*W17) -> 0 | Y18: =Nav!$M$13 -> 0.2988 | Z18: =ROUND(X18*Y18,2) -> 0 | AA18: =Z18+X18 -> 0
P19: =SUM(P9:P17) -> 8 | Z19: Summe | AA19: =SUM(AA9:AA17) -> 67374.307
Z20: Förderquote | AA20: =Nav!$K$6 -> 0.7
Y21: Fördersumme Personal | AA21: =AA19*AA20 -> 47162.015
A23: =Nav!H17 | B23: =Nav!H17
B24: Name MA | D24: Monat
D25: =B23 | E25: =D25+31 -> #VALUE! | F25: =IF((MOD(YEAR(E25),4)=0)-(MOD(YEAR(E25),100)=0)+(MOD(YEAR(E25),400)=0)=0,E25+28,E25+29) -> #VALUE! | G25: =F25+31 -> #VALUE! | H25: =G25+30 -> #VALUE! | I25: =H25+31 -> #VALUE! | J25: =I25+30 -> #VALUE! | K25: =J25+31 -> #VALUE! | L25: =K25+31 -> #VALUE! | M25: =L25+30 -> #VALUE! | N25: =M25+31 -> #VALUE! | O25: =N25+30 -> #VALUE! | P25: Summe PM/MA | R25: Kategorie bzw. Personalqualifikation | S25: Vorkalkulierter Personaleinsatz (Stunden) | T25: Jahresbruttogehalt | U25: Wochenarbeits-stunden | V25: Jahresarbeits-stunden | W25: Stundensatz | X25: Einzelkosten | Y25: Zuschlagsatz in % | Z25: Zuschlag | AA25: Gesamt
R26: Gehälter
B28: =$B$9 -> Tippl, Mario | P28: =SUM(D28:O28) -> 0 | R28: =$B$9 -> Tippl, Mario | S28: =(P28*V28/12) -> 0 | T28: =T9 -> 120000 | U28: =U9 -> 40 | V28: =V9 -> 2080 | W28: =IF(V28=0, "0,00 €", (T28/V28)) -> 57.692308 | X28: =(S28*W28) -> 0 | Y28: =Nav!$M$12 -> 0.2842 | Z28: =(X28*Y28) -> 0 | AA28: =Z28+X28 -> 0
B29: =$B$11 -> Socha, Pawel | P29: =SUM(D29:O29) -> 0 | R29: =$B$11 -> Socha, Pawel | S29: =(P29*V29/12) -> 0 | T29: =T11 -> 38700 | U29: =U11 -> 40 | V29: =V11 -> 2080 | W29: =IF(V29=0, "0,00 €", (T29/V29)) -> 18.605769 | X29: =(S29*W29) -> 0 | Y29: =Nav!$M$12 -> 0.2842 | Z29: =(X29*Y29) -> 0 | AA29: =Z29+X29 -> 0
B30: =$B$13 -> Tippl, Karen | P30: =SUM(D30:O30) -> 0 | R30: =$B$13 -> Tippl, Karen | S30: =(P30*V30/12) -> 0 | T30: =T13 -> 35700 | U30: =U13 -> 20 | V30: =V13 -> 1040 | W30: =IF(V30=0, "0,00 €", (T30/V30)) -> 34.326923 | X30: =(S30*W30) -> 0 | Y30: =Nav!$M$12 -> 0.2842 | Z30: =(X30*Y30) -> 0 | AA30: =Z30+X30 -> 0
B31: =$B$15 -> MA 4 | P31: =SUM(D31:O31) -> 0 | R31: =$B$15 -> MA 4 | S31: =(P31*V31/12) -> 0 | T31: =T15 -> 0 | U31: =U15 -> 0 | V31: =V15 -> 0 | W31: =IF(V31=0, "0,00 €", (T31/V31)) -> 0,00 € | X31: =(S31*W31) -> 0 | Y31: =Nav!$M$12 -> 0.2842 | Z31: =(X31*Y31) -> 0 | AA31: =Z31+X31 -> 0
B32: =$B$17 -> MA 5 | P32: =SUM(D32:O32) -> 0 | R32: =$B$17 -> MA 5 | S32: =(P32*V32/12) -> 0 | T32: =T17 -> 0 | U32: =U17 -> 0 | V32: =V17 -> 0 | W32: =IF(V32=0, "0,00 €", (T32/V32)) -> 0,00 € | X32: =(S32*W32) -> 0 | Y32: =Nav!$M$12 -> 0.2842 | Z32: =(X32*Y32) -> 0 | AA32: =Z32+X32 -> 0
P33: =SUM(P28:P32) -> 0 | Z33: Summe | AA33: =SUM(AA28:AA32) -> 0
Z34: Förderquote | AA34: =IF(Nav!$O$6="-",0,Nav!$O$6) -> 0.7
Y35: Fördersumme Personal | AA35: =AA33*AA34 -> 0
A37: =Nav!H18 | B37: =Nav!H18
B38: Name MA | D38: Monat
D39: =B37 | E39: =D39+31 -> #VALUE! | F39: =IF((MOD(YEAR(E39),4)=0)-(MOD(YEAR(E39),100)=0)+(MOD(YEAR(E39),400)=0)=0,E39+28,E39+29) -> #VALUE! | G39: =F39+31 -> #VALUE! | H39: =G39+30 -> #VALUE! | I39: =H39+31 -> #VALUE! | J39: =I39+30 -> #VALUE! | K39: =J39+31 -> #VALUE! | L39: =K39+31 -> #VALUE! | M39: =L39+30 -> #VALUE! | N39: =M39+31 -> #VALUE! | O39: =N39+30 -> #VALUE! | P39: Summe PM/MA | R39: Kategorie bzw. Personalqualifikation | S39: Vorkalkulierter Personaleinsatz (Stunden) | T39: Jahresbruttogehalt | U39: Wochenarbeits-stunden | V39: Jahresarbeits-stunden | W39: Stundensatz | X39: Einzelkosten | Y39: Zuschlagsatz in % | Z39: Zuschlag | AA39: Gesamt
R40: Gehälter
B42: =$B$9 -> Tippl, Mario | P42: =SUM(D42:O42) -> 0 | R42: =$B$9 -> Tippl, Mario | S42: =(P42*V42/12) -> 0 | T42: =T28 -> 120000 | U42: =U28 -> 40 | V42: =V28 -> 2080 | W42: =IF(V42=0, "0,00 €", (T42/V42)) -> 57.692308 | X42: =(S42*W42) -> 0 | Y42: =Nav!$M$12 -> 0.2842 | Z42: =(X42*Y42) -> 0 | AA42: =Z42+X42 -> 0
B43: =$B$11 -> Socha, Pawel | P43: =SUM(D43:O43) -> 0 | R43: =$B$11 -> Socha, Pawel | S43: =(P43*V43/12) -> 0 | T43: =T29 -> 38700 | U43: =U29 -> 40 | V43: =V29 -> 2080 | W43: =IF(V43=0, "0,00 €", (T43/V43)) -> 18.605769 | X43: =(S43*W43) -> 0 | Y43: =Nav!$M$12 -> 0.2842 | Z43: =(X43*Y43) -> 0 | AA43: =Z43+X43 -> 0
B44: =$B$13 -> Tippl, Karen | P44: =SUM(D44:O44) -> 0 | R44: =$B$13 -> Tippl, Karen | S44: =(P44*V44/12) -> 0 | T44: =T30 -> 35700 | U44: =U30 -> 20 | V44: =V30 -> 1040 | W44: =IF(V44=0, "0,00 €", (T44/V44)) -> 34.326923 | X44: =(S44*W44) -> 0 | Y44: =Nav!$M$12 -> 0.2842 | Z44: =(X44*Y44) -> 0 | AA44: =Z44+X44 -> 0
B45: =$B$15 -> MA 4 | P45: =SUM(D45:O45) -> 0 | R45: =$B$15 -> MA 4 | S45: =(P45*V45/12) -> 0 | T45: =T31 -> 0 | U45: =U31 -> 0 | V45: =V31 -> 0 | W45: =IF(V45=0, "0,00 €", (T45/V45)) -> 0,00 € | X45: =(S45*W45) -> 0 | Y45: =Nav!$M$12 -> 0.2842 | Z45: =(X45*Y45) -> 0 | AA45: =Z45+X45 -> 0
B46: =$B$17 -> MA 5 | P46: =SUM(D46:O46) -> 0 | R46: =$B$17 -> MA 5 | S46: =(P46*V46/12) -> 0 | T46: =T32 -> 0 | U46: =U32 -> 0 | V46: =V32 -> 0 | W46: =IF(V46=0, "0,00 €", (T46/V46)) -> 0,00 € | X46: =(S46*W46) -> 0 | Y46: =Nav!$M$12 -> 0.2842 | Z46: =(X46*Y46) -> 0 | AA46: =Z46+X46 -> 0
P47: =SUM(P42:P46) -> 0 | Z47: Summe | AA47: =SUM(AA42:AA46) -> 0
Z48: Förderquote | AA48: =IF(Nav!$S$6="-",0,Nav!$S$6) -> 0.7
Y49: Fördersumme Personal | AA49: =AA47*AA48 -> 0
A51: =Nav!H19 | B51: =Nav!H19
B52: MA / Anzahl Stunden pro Monat | D52: Monat
D53: =B51 | E53: =IF($B$51="","",D53+31) | F53: =IF($B$51="","",IF((MOD(YEAR(E53),4)=0)-(MOD(YEAR(E53),100)=0)+(MOD(YEAR(E53),400)=0)=0,E53+28,E53+29)) | G53: =IF($B$51="","",F53+31) | H53: =IF($B$51="","",G53+30) | I53: =IF($B$51="","",H53+31) | J53: =IF($B$51="","",I53+30) | K53: =IF($B$51="","",J53+31) | L53: =IF($B$51="","",K53+31) | M53: =IF($B$51="","",L53+30) | N53: =IF($B$51="","",M53+31) | O53: =IF($B$51="","",N53+30) | P53: Summe PM/MA | R53: Kategorie bzw. Personalqualifikation | S53: Vorkalkulierter Personaleinsatz (Stunden) | T53: Jahresbruttogehalt | U53: Wochenarbeits-stunden | V53: Jahresarbeits-stunden | W53: Stundensatz | X53: Einzelkosten | Y53: Zuschlagsatz in % | Z53: Zuschlag | AA53: Gesamt
R54: Gehälter
B56: =$B$9 -> Tippl, Mario | P56: =SUM(D56:O56) -> 0 | R56: =$B$9 -> Tippl, Mario | S56: =(P56*V56/12) -> 0 | T56: =T42 -> 120000 | U56: =U42 -> 40 | V56: =V42 -> 2080 | W56: =IF(V56=0, "0,00 €", (T56/V56)) -> 57.692308 | X56: =(S56*W56) -> 0 | Y56: =Nav!$M$12 -> 0.2842 | Z56: =X56*Y56 -> 0 | AA56: =Z56+X56 -> 0
B57: =$B$11 -> Socha, Pawel | P57: =SUM(D57:O57) -> 0 | R57: =$B$11 -> Socha, Pawel | S57: =(P57*V57/12) -> 0 | T57: =T43 -> 38700 | U57: =U43 -> 40 | V57: =V43 -> 2080 | W57: =IF(V57=0, "0,00 €", (T57/V57)) -> 18.605769 | X57: =(S57*W57) -> 0 | Y57: =Nav!$M$12 -> 0.2842 | Z57: =X57*Y57 -> 0 | AA57: =Z57+X57 -> 0
B58: =$B$13 -> Tippl, Karen | P58: =SUM(D58:O58) -> 0 | R58: =$B$13 -> Tippl, Karen | S58: =(P58*V58/12) -> 0 | T58: =T44 -> 35700 | U58: =U44 -> 20 | V58: =V44 -> 1040 | W58: =IF(V58=0, "0,00 €", (T58/V58)) -> 34.326923 | X58: =(S58*W58) -> 0 | Y58: =Nav!$M$12 -> 0.2842 | Z58: =X58*Y58 -> 0 | AA58: =Z58+X58 -> 0
B59: =$B$15 -> MA 4 | P59: =SUM(D59:O59) -> 0 | R59: =$B$15 -> MA 4 | S59: =(P59*V59/12) -> 0 | T59: =T45 -> 0 | U59: =U45 -> 0 | V59: =V45 -> 0 | W59: =IF(V59=0, "0,00 €", (T59/V59)) -> 0,00 € | X59: =(S59*W59) -> 0 | Y59: =Nav!$M$12 -> 0.2842 | Z59: =X59*Y59 -> 0 | AA59: =Z59+X59 -> 0
B60: =$B$17 -> MA 5 | P60: =SUM(D60:O60) -> 0 | R60: =$B$17 -> MA 5 | S60: =(P60*V60/12) -> 0 | T60: =T46 -> 0 | U60: =U46 -> 0 | V60: =V46 -> 0 | W60: =IF(V60=0, "0,00 €", (T60/V60)) -> 0,00 € | X60: =(S60*W60) -> 0 | Y60: =Nav!$M$12 -> 0.2842 | Z60: =X60*Y60 -> 0 | AA60: =Z60+X60 -> 0
P61: =SUM(P56:P60) -> 0 | Z61: Summe | AA61: =SUM(AA56:AA60) -> 0
Z62: Förderquote | AA62: =IF(Nav!$W$6="-",0,Nav!$W$6) -> 0.7
Y63: Fördersumme Personal | AA63: =AA61*AA62 -> 0
A65: Gesamt | B65: Gesamt
B66: MA / Anzahl Stunden pro AP | D66: Jahre
D67: =Nav!H16 -> 45047 | E67: =Nav!H17 | F67: =Nav!H18 | G67: =Nav!H19 | H67: Summe PM/MA | R67: Kategorie bzw. Personalqualifikation | S67: Vorkalkulierter Personaleinsatz (Stunden) | T67: Jahresbruttogehalt | U67: Wochenarbeits-stunden | V67: Jahresarbeits-stunden | W67: Stundensatz | X67: Einzelkosten | Y67: Zuschlagsatz in % | Z67: Zuschlag | AA67: Gesamt
R68: Gehälter
B70: =$B$9 -> Tippl, Mario | D70: =P9 -> 2.5 | E70: =P28 -> 0 | F70: =P42 -> 0 | G70: =P56 -> 0 | H70: =SUM(D70:G70) -> 2.5 | R70: =$B$9 -> Tippl, Mario | S70: =H70*V70/12 -> 433.33333 | T70: =T56 -> 120000 | U70: =U56 -> 40 | V70: =V56 -> 2080 | W70: =IF(V70=0, "0,00 €", T70/V70) -> 57.692308 | X70: =W70*S70 -> 25000 | Y70: =Nav!$M$12 -> 0.2842 | Z70: =Z56+Z42+Z28+Z9 -> 7104.72 | AA70: =Z70+X70 -> 32104.72
B71: =$B$11 -> Socha, Pawel | D71: =P11 -> 1 | E71: =P29 -> 0 | F71: =P43 -> 0 | G71: =P57 -> 0 | H71: =SUM(D71:G71) -> 1 | R71: =$B$11 -> Socha, Pawel | S71: =H71*V71/12 -> 173.33333 | T71: =T57 -> 38700 | U71: =U57 -> 40 | V71: =V57 -> 2080 | W71: =IF(V71=0, "0,00 €", T71/V71) -> 18.605769 | X71: =W71*S71 -> 3225 | Y71: =Nav!$M$12 -> 0.2842 | Z71: =Z57+Z43+Z29+Z11 -> 916.75 | AA71: =Z71+X71 -> 4141.75
B72: =$B$13 -> Tippl, Karen | D72: =P13 -> 2.5 | E72: =P30 -> 0 | F72: =P44 -> 0 | G72: =P58 -> 0 | H72: =SUM(D72:G72) -> 2.5 | R72: =$B$13 -> Tippl, Karen | S72: =H72*V72/12 -> 216.66667 | T72: =T58 -> 35700 | U72: =U58 -> 20 | V72: =V58 -> 1040 | W72: =IF(V72=0, "0,00 €", T72/V72) -> 34.326923 | X72: =W72*S72 -> 7437.5 | Y72: =Nav!$M$12 -> 0.2842 | Z72: =Z58+Z44+Z30+Z13 -> 2113.93 | AA72: =Z72+X72 -> 9551.43
B73: =$B$15 -> MA 4 | D73: =P15 -> 0 | E73: =P31 -> 0 | F73: =P45 -> 0 | G73: =P59 -> 0 | H73: =SUM(D73:G73) -> 0 | R73: =$B$15 -> MA 4 | S73: =H73*V73/12 -> 0 | T73: =T59 -> 0 | U73: =U59 -> 0 | V73: =V59 -> 0 | W73: =IF(V73=0, "0,00 €", T73/V73) -> 0,00 € | X73: =W73*S73 -> 0 | Y73: =Nav!$M$12 -> 0.2842 | Z73: =Z59+Z45+Z31+Z15 -> 0 | AA73: =Z73+X73 -> 0
B74: =$B$17 -> MA 5 | D74: =P17 -> 0 | E74: =P32 -> 0 | F74: =P46 -> 0 | G74: =P60 -> 0 | H74: =SUM(D74:G74) -> 0 | R74: =$B$17 -> MA 5 | S74: =H74*V74/12 -> 0 | T74: =T60 -> 0 | U74: =U60 -> 0 | V74: =V60 -> 0 | W74: =IF(V74=0, "0,00 €", T74/V74) -> 0,00 € | X74: =W74*S74 -> 0 | Y74: =Nav!$M$12 -> 0.2842 | Z74: =Z60+Z46+Z32+Z17 -> 0 | AA74: =Z74+X74 -> 0
H75: =SUM(H70:H74) -> 6 | Z75: Summe | AA75: =SUM(AA70:AA74) -> 45797.9
Z76: Förderquote | AA76: =IF(AA75=0,"",AA77/AA75) -> 1.0297855
Y77: Fördersumme Personal | AA77: =AA63+AA49+AA35+AA21 -> 47162.015
AA78: =Nav!E20 -> 53855

Sheet Tippl M. J1
W2: Förderkennzeichen: | AB2: =Nav!$C$6 -> DS200424
O4: Stundennachweis
O5: für pauschalierte Abrechnung gemäß Nr. 2.4 NKBF 2017 (analog Anlage 1 zum Verwendungsnachweis)
A6: Zuwendungsempfänger (Firmenstempel) | O6: Der Stundennachweis verbleibt beim Zuwendungsempfänger und ist nur nach Aufforderung vorzulegen.
A7: Vorhabenthema
A8: =Nav!$C$3 -> Durchführbarkeitsstudie "BioInk"
A10: Monat | N10: Mitarbeiter(in): [Name, Vorname]
A11: =DATE(YEAR(Nav!$L$4),1,1) -> 44927 | N11: ='Planung Personal'!$B$9 -> Tippl, Mario
A13: Die zu Lasten des Vorhabens abzurechnenden Personalstunden sind täglich eigenhändig von der betreffenden Person zu erfassen. Nur die produktiven, für das Vorhaben geleisteten Stunden sind zuwendungsfähig.
D15: technisch | E15: nicht- technisch | F15: Arbeitszeiten in Stunden je Kalendertag: | AK15: Summe Monat | AL15: ZA | AM15: offen
A16: lfd. Nr. | F16: =A11 -> 44927 | G16: =F16+1 -> 44928 | H16: =G16+1 -> 44929 | I16: =H16+1 -> 44930 | J16: =I16+1 -> 44931 | K16: =J16+1 -> 44932 | L16: =K16+1 -> 44933 | M16: =L16+1 -> 44934 | N16: =M16+1 -> 44935 | ... AJ16: =AI16+1 -> 44957
A17: 1. | B17: AP | C17: förderbare Projektarbeiten (1)
B18: Nr. | C18: Kurzbezeichnung des Arbeitspakets
C19: =VLOOKUP(B19,'AP Übersicht'!$A$8:$B$36,2,FALSE) -> #N/A | E19: x | AK19: =SUM(F19:AJ19) -> 0 | AL19: =VLOOKUP($B19,'AP Übersicht'!$A$8:$R$36,9,FALSE) -> #N/A | AM19: =VLOOKUP($B19,'AP Übersicht'!$A$8:$R$36,10,FALSE) -> #N/A
C20: =VLOOKUP(B20,'AP Übersicht'!$A$8:$B$36,2,FALSE) -> #N/A | AK20: =SUM(F20:AJ20) -> 0
C21: =VLOOKUP(B21,'AP Übersicht'!$A$8:$B$36,2,FALSE) -> #N/A | AK21: =SUM(F21:AJ21) -> 0
C22: =VLOOKUP(B22,'AP Übersicht'!$A$8:$B$36,2,FALSE) -> #N/A | AK22: =SUM(F22:AJ22) -> 0
C23: =VLOOKUP(B23,'AP Übersicht'!$A$8:$B$36,2,FALSE) -> #N/A | AK23: =SUM(F23:AJ23) -> 0
C24: =VLOOKUP(B24,'AP Übersicht'!$A$8:$B$36,2,FALSE) -> #N/A | AK24: =SUM(F24:AJ24) -> 0
C25: =VLOOKUP(B25,'AP Übersicht'!$A$8:$B$36,2,FALSE) -> #N/A | AK25: =SUM(F25:AJ25) -> 0
C26: =VLOOKUP(B26,'AP Übersicht'!$A$8:$B$36,2,FALSE) -> #N/A | AK26: =SUM(F26:AJ26) -> 0
C27: =VLOOKUP(B27,'AP Übersicht'!$A$8:$B$36,2,FALSE) -> #N/A | AK27: =SUM(F27:AJ27) -> 0
C28: =VLOOKUP(B28,'AP Übersicht'!$A$8:$B$36,2,FALSE) -> #N/A | AK28: =SUM(F28:AJ28) -> 0
C29: =VLOOKUP(B29,'AP Übersicht'!$A$8:$B$36,2,FALSE) -> #N/A | AK29: =SUM(F29:AJ29) -> 0
C30: =VLOOKUP(B30,'AP Übersicht'!$A$8:$B$36,2,FALSE) -> #N/A | AK30: =SUM(F30:AJ30) -> 0
C31: Summe der förderbaren Stunden (2) | D31: x | F31: =SUMIF($D19:$D30,$D31,F19:F30) -> 0 | G31: =SUMIF($D19:$D30,$D31,G19:G30) -> 0 | H31: =SUMIF($D19:$D30,$D31,H19:H30) -> 0 | I31: =SUMIF($D19:$D30,$D31,I19:I30) -> 0 | J31: =SUMIF($D19:$D30,$D31,J19:J30) -> 0 | K31: =SUMIF($D19:$D30,$D31,K19:K30) -> 0 | L31: =SUMIF($D19:$D30,$D31,L19:L30) -> 0 | M31: =SUMIF($D19:$D30,$D31,M19:M30) -> 0 | ... AJ31: =SUMIF($D19:$D30,$D31,AJ19:AJ30) -> 0 | AK31: =SUM(F31:AJ31) -> 0
E32: x | F32: =SUMIF($E19:$E30,$E32,F19:F30) -> 0 | G32: =SUMIF($E19:$E30,$E32,G19:G30) -> 0 | H32: =SUMIF($E19:$E30,$E32,H19:H30) -> 0 | I32: =SUMIF($E19:$E30,$E32,I19:I30) -> 0 | J32: =SUMIF($E19:$E30,$E32,J19:J30) -> 0 | K32: =SUMIF($E19:$E30,$E32,K19:K30) -> 0 | L32: =SUMIF($E19:$E30,$E32,L19:L30) -> 0 | M32: =SUMIF($E19:$E30,$E32,M19:M30) -> 0 | ... AJ32: =SUMIF($E19:$E30,$E32,AJ19:AJ30) -> 0 | AK32: =SUM(F32:AJ32) -> 0
A33: 2. | C33: Sonstige Arbeiten | AK33: =SUM(F33:AJ33) -> 0
A34: 3. | C34: Zeitausgleich | AK34: =SUM(E34:AJ34) -> 0
C35: Urlaub (nur bezahlten Urlaub aufführen) | AK35: =SUM(F35:AJ35) -> 0
C36: Krankheit (nur bei Lohn- und Gehaltsfortzahlung) | AK36: =SUM(F36:AJ36) -> 0
C37: Sonstige bezahlte Ausfallzeiten (z. B. Feiertage) | AK37: =SUM(F37:AJ37) -> 0 | AL37: Ah | AM37: Netto Ah
AL38: =SUM(AK31:AK37) -> 0 | AM38: =NETWORKDAYS(F16,EOMONTH(A11,0))*8 -> 176
A39: (1) Die geleisteten Bearbeitungsstunden sind für den gesamten Bewilligungszeitraum eigenhändig und zeitnah, d. h. mindestens innerhalb einer Woche zu erfassen. Die Angaben sind subventionserheblich im Sinne des § 264 Strafgesetzbuch.
Q40: =IF(WEEKDAY(EOMONTH(A11,0),2)=7,EOMONTH(A11,0)-2,IF(WEEKDAY(EOMONTH(11,0),2)=6,EOMONTH(A11,0)-1,EOMONTH(A11,0))) -> 44957
Q41: Datum / Unterschrift des Mitarbeiters
A42: (2) Förderbar pro Monat sind die tatsächlich für das Projekt geleisteten Stunden, jedoch nicht mehr als arbeitsvertraglich, betrieblich oder tariflich vereinbart, maximal in Höhe von 52 (Wochen) / 12 (Monate) x Wochenarbeitszeit. Überstunden sind nicht förderbar. | Q42: =Q40 -> 44957
Q43: Datum / Unterschrift Geschäftsführer bzw. FuE-Verantwortlicher (in öffentlichen Forschungseinrichtungen)
W46: Förderkennzeichen: | AB46: =Nav!$C$6 -> DS200424
O48: Stundennachweis
O49: für pauschalierte Abrechnung gemäß Nr. 2.4 NKBF 2017 (analog Anlage 1 zum Verwendungsnachweis)
A50: Zuwendungsempfänger (Firmenstempel) | O50: Der Stundennachweis verbleibt beim Zuwendungsempfänger und ist nur nach Aufforderung vorzulegen.
A51: Vorhabenthema
A52: =Nav!$C$3 -> Durchführbarkeitsstudie "BioInk"
A54: Monat | N54: Mitarbeiter(in): [Name, Vorname]
A55: =A11+31 -> 44958 | N55: =N11 -> Tippl, Mario
A57: Die zu Lasten des Vorhabens abzurechnenden Personalstunden sind täglich eigenhändig von der betreffenden Person zu erfassen. Nur die produktiven, für das Vorhaben geleisteten Stunden sind zuwendungsfähig.
D59: technisch | E59: nicht- technisch | F59: Arbeitszeiten in Stunden je Kalendertag: | AK59: Summe Monat | AL59: ZA | AM59: offen
A60: lfd. Nr. | F60: =A55 -> 44958 | G60: =F60+1 -> 44959 | H60: =G60+1 -> 44960 | I60: =H60+1 -> 44961 | J60: =I60+1 -> 44962 | K60: =J60+1 -> 44963 | L60: =K60+1 -> 44964 | M60: =L60+1 -> 44965 | N60: =M60+1 -> 44966 | ... AG60: =AF60+1 -> 44985 | AH60: =IF(AND(DAY(DATE(YEAR($A$11),3,0))=29,YEAR($A$11)<>1900),29,"") | AP60: =IF(AND(DAY(DATE(YEAR($A$11),3,0))=29,YEAR($A$11)<>1900),29,"")
A61: 1. | B61: AP | C61: förderbare Projektarbeiten (1)
B62: Nr. | C62: Kurzbezeichnung des Arbeitspakets
C63: =VLOOKUP(B63,'AP Übersicht'!$A$8:$B$36,2,FALSE) -> #N/A | AK63: =SUM(F63:AJ63) -> 0 | AL63: =VLOOKUP($B63,'AP Übersicht'!$A$8:$R$36,9,FALSE) -> #N/A | AM63: =VLOOKUP($B63,'AP Übersicht'!$A$8:$R$36,10,FALSE) -> #N/A
C64: =VLOOKUP(B64,'AP Übersicht'!$A$8:$B$36,2,FALSE) -> #N/A | AK64: =SUM(F64:AJ64) -> 0
C65: =VLOOKUP(B65,'AP Übersicht'!$A$8:$B$36,2,FALSE) -> #N/A | AK65: =SUM(F65:AJ65) -> 0
C66: =VLOOKUP(B66,'AP Übersicht'!$A$8:$B$36,2,FALSE) -> #N/A | AK66: =SUM(F66:AJ66) -> 0
C67: =VLOOKUP(B67,'AP Übersicht'!$A$8:$B$36,2,FALSE) -> #N/A | AK67: =SUM(F67:AJ67) -> 0
C68: =VLOOKUP(B68,'AP Übersicht'!$A$8:$B$36,2,FALSE) -> #N/A | AK68: =SUM(F68:AJ68) -> 0
C69: =VLOOKUP(B69,'AP Übersicht'!$A$8:$B$36,2,FALSE) -> #N/A | AK69: =SUM(F69:AJ69) -> 0
C70: =VLOOKUP(B70,'AP Übersicht'!$A$8:$B$36,2,FALSE) -> #N/A | AK70: =SUM(F70:AJ70) -> 0
C71: =VLOOKUP(B71,'AP Übersicht'!$A$8:$B$36,2,FALSE) -> #N/A | AK71: =SUM(F71:AJ71) -> 0
C72: =VLOOKUP(B72,'AP Übersicht'!$A$8:$B$36,2,FALSE) -> #N/A | AK72: =SUM(F72:AJ72) -> 0
C73: =VLOOKUP(B73,'AP Übersicht'!$A$8:$B$36,2,FALSE) -> #N/A | AK73: =SUM(F73:AJ73) -> 0
C74: =VLOOKUP(B74,'AP Übersicht'!$A$8:$B$36,2,FALSE) -> #N/A | AK74: =SUM(F74:AJ74) -> 0
C75: Summe der förderbaren Stunden (2) | D75: x | F75: =SUMIF($D63:$D74,$D75,F63:F74) -> 0 | G75: =SUMIF($D63:$D74,$D75,G63:G74) -> 0 | H75: =SUMIF($D63:$D74,$D75,H63:H74) -> 0 | I75: =SUMIF($D63:$D74,$D75,I63:I74) -> 0 | J75: =SUMIF($D63:$D74,$D75,J63:J74) -> 0 | K75: =SUMIF($D63:$D74,$D75,K63:K74) -> 0 | L75: =SUMIF($D63:$D74,$D75,L63:L74) -> 0 | M75: =SUMIF($D63:$D74,$D75,M63:M74) -> 0 | ... AI75: =SUMIF($D63:$D74,$D75,AI63:AI74) -> 0 | AJ75: =SUMIF($D63:AH74,$D75,AJ63:AJ74) -> 0 | AK75: =SUM(F75:AJ75) -> 0
E76: x | F76: =SUMIF($E63:$E74,$E76,F63:F74) -> 0 | G76: =SUMIF($E63:$E74,$E76,G63:G74) -> 0 | H76: =SUMIF($E63:$E74,$E76,H63:H74) -> 0 | I76: =SUMIF($E63:$E74,$E76,I63:I74) -> 0 | J76: =SUMIF($E63:$E74,$E76,J63:J74) -> 0 | K76: =SUMIF($E63:$E74,$E76,K63:K74) -> 0 | L76: =SUMIF($E63:$E74,$E76,L63:L74) -> 0 | M76: =SUMIF($E63:$E74,$E76,M63:M74) -> 0 | ... AJ76: =SUMIF($E63:$E74,$E76,AJ63:AJ74) -> 0 | AK76: =SUM(F76:AJ76) -> 0
A77: 2. | C77: Sonstige Arbeiten | AK77: =SUM(F77:AJ77) -> 0
A78: 3. | C78: Zeitausgleich | AK78: =SUM(E78:AJ78) -> 0
C79: Urlaub (nur bezahlten Urlaub aufführen) | AK79: =SUM(F79:AJ79) -> 0
C80: Krankheit (nur bei Lohn- und Gehaltsfortzahlung) | AK80: =SUM(F80:AJ80) -> 0
C81: Sonstige bezahlte Ausfallzeiten (z. B. Feiertage) | AK81: =SUM(F81:AJ81) -> 0 | AL81: Ah | AM81: Netto Ah
AL82: =SUM(AK75:AK81) -> 0 | AM82: =NETWORKDAYS(F60,EOMONTH(A55,0))*8 -> 160
A83: (1) Die geleisteten Bearbeitungsstunden sind für den gesamten Bewilligungszeitraum eigenhändig und zeitnah, d. h. mindestens innerhalb einer Woche zu erfassen. Die Angaben sind subventionserheblich im Sinne des § 264 Strafgesetzbuch.
Q84: =IF(WEEKDAY(EOMONTH(A55,0),2)=7,EOMONTH(A55,0)-2,IF(WEEKDAY(EOMONTH(11,0),2)=6,EOMONTH(A55,0)-1,EOMONTH(A55,0))) -> 44985
Q85: Datum / Unterschrift des Mitarbeiters
A86: (2) Förderbar pro Monat sind die tatsächlich für das Projekt geleisteten Stunden, jedoch nicht mehr als arbeitsvertraglich, betrieblich oder tariflich vereinbart, maximal in Höhe von 52 (Wochen) / 12 (Monate) x Wochenarbeitszeit. Überstunden sind nicht förderbar. | Q86: =Q84 -> 44985
Q87: Datum / Unterschrift Geschäftsführer bzw. FuE-Verantwortlicher (in öffentlichen Forschungseinrichtungen)
W90: Förderkennzeichen: | AB90: =Nav!$C$6 -> DS200424
O92: Stundennachweis
O93: für pauschalierte Abrechnung gemäß Nr. 2.4 NKBF 2017 (analog Anlage 1 zum Verwendungsnachweis)
A94: Zuwendungsempfänger (Firmenstempel) | O94: Der Stundennachweis verbleibt beim Zuwendungsempfänger und ist nur nach Aufforderung vorzulegen.
A95: Vorhabenthema
A96: =Nav!$C$3 -> Durchführbarkeitsstudie "BioInk"
A98: Monat | N98: Mitarbeiter(in): [Name, Vorname]
A99: =IF(AND(DAY(DATE(YEAR($A$11),3,0))=29,YEAR($A$11)<>1900),A55+29,A55+28) -> 44986 | N99: =N55 -> Tippl, Mario
A101: Die zu Lasten des Vorhabens abzurechnenden Personalstunden sind täglich eigenhändig von der betreffenden Person zu erfassen. Nur die produktiven, für das Vorhaben geleisteten Stunden sind zuwendungsfähig.
D103: technisch | E103: nicht- technisch | F103: Arbeitszeiten in Stunden je Kalendertag: | AK103: Summe Monat | AL103: ZA | AM103: offen
A104: lfd. Nr. | F104: =A99 -> 44986 | G104: =F104+1 -> 44987 | H104: =G104+1 -> 44988 | I104: =H104+1 -> 44989 | J104: =I104+1 -> 44990 | K104: =J104+1 -> 44991 | L104: =K104+1 -> 44992 | M104: =L104+1 -> 44993 | N104: =M104+1 -> 44994 | ... AJ104: =AI104+1 -> 45016
A105: 1. | B105: AP | C105: förderbare Projektarbeiten (1)
B106: Nr. | C106: Kurzbezeichnung des Arbeitspakets
C107: =VLOOKUP(B107,'AP Übersicht'!$A$8:$B$36,2,FALSE) -> #N/A | AK107: =SUM(F107:AJ107) -> 0 | AL107: =VLOOKUP($B107,'AP Übersicht'!$A$8:$R$36,9,FALSE) -> #N/A | AM107: =VLOOKUP($B107,'AP Übersicht'!$A$8:$R$36,10,FALSE) -> #N/A
C108: =VLOOKUP(B108,'AP Übersicht'!$A$8:$B$36,2,FALSE) -> #N/A | AK108: =SUM(F108:AJ108) -> 0
C109: =VLOOKUP(B109,'AP Übersicht'!$A$8:$B$36,2,FALSE) -> #N/A | AK109: =SUM(F109:AJ109) -> 0
C110: =VLOOKUP(B110,'AP Übersicht'!$A$8:$B$36,2,FALSE) -> #N/A | AK110: =SUM(F110:AJ110) -> 0
C111: =VLOOKUP(B111,'AP Übersicht'!$A$8:$B$36,2,FALSE) -> #N/A | AK111: =SUM(F111:AJ111) -> 0
C112: =VLOOKUP(B112,'AP Übersicht'!$A$8:$B$36,2,FALSE) -> #N/A | AK112: =SUM(F112:AJ112) -> 0
C113: =VLOOKUP(B113,'AP Übersicht'!$A$8:$B$36,2,FALSE) -> #N/A | AK113: =SUM(F113:AJ113) -> 0
C114: =VLOOKUP(B114,'AP Übersicht'!$A$8:$B$36,2,FALSE) -> #N/A | AK114: =SUM(F114:AJ114) -> 0
C115: =VLOOKUP(B115,'AP Übersicht'!$A$8:$B$36,2,FALSE) -> #N/A | AK115: =SUM(F115:AJ115) -> 0
C116: =VLOOKUP(B116,'AP Übersicht'!$A$8:$B$36,2,FALSE) -> #N/A | AK116: =SUM(F116:AJ116) -> 0
C117: =VLOOKUP(B117,'AP Übersicht'!$A$8:$B$36,2,FALSE) -> #N/A | AK117: =SUM(F117:AJ117) -> 0
...

Sheet Socha J1
W2: Förderkennzeichen: | AB2: =Nav!$C$6 -> DS200424
O4: Stundennachweis
O5: für pauschalierte Abrechnung gemäß Nr. 2.4 NKBF 2017 (analog Anlage 1 zum Verwendungsnachweis)
A6: Zuwendungsempfänger (Firmenstempel) | O6: Der Stundennachweis verbleibt beim Zuwendungsempfänger und ist nur nach Aufforderung vorzulegen.
A7: Vorhabenthema
A8: =Nav!$C$3 -> Durchführbarkeitsstudie "BioInk"
A10: Monat | N10: Mitarbeiter(in): [Name, Vorname]
A11: =DATE(YEAR(Nav!$L$4),1,1) -> 44927 | N11: ='Planung Personal'!$B$11 -> Socha, Pawel
A13: Die zu Lasten des Vorhabens abzurechnenden Personalstunden sind täglich eigenhändig von der betreffenden Person zu erfassen. Nur die produktiven, für das Vorhaben geleisteten Stunden sind zuwendungsfähig.
D15: technisch | E15: nicht- technisch | F15: Arbeitszeiten in Stunden je Kalendertag: | AK15: Summe Monat | AL15: ZA | AM15: offen
A16: lfd. Nr. | F16: =A11 -> 44927 | G16: =F16+1 -> 44928 | H16: =G16+1 -> 44929 | I16: =H16+1 -> 44930 | J16: =I16+1 -> 44931 | K16: =J16+1 -> 44932 | L16: =K16+1 -> 44933 | M16: =L16+1 -> 44934 | N16: =M16+1 -> 44935 | ... AJ16: =AI16+1 -> 44957
A17: 1. | B17: AP | C17: förderbare Projektarbeiten (1)
B18: Nr. | C18: Kurzbezeichnung des Arbeitspakets
C19: =VLOOKUP(B19,'AP Übersicht'!$A$8:$B$36,2,FALSE) -> #N/A | AK19: =SUM(F19:AJ19) -> 0 | AL19: =VLOOKUP($B19,'AP Übersicht'!$A$8:$R$36,13,FALSE) -> #N/A | AM19: =VLOOKUP($B19,'AP Übersicht'!$A$8:$R$36,14,FALSE) -> #N/A
C20: =VLOOKUP(B20,'AP Übersicht'!$A$8:$B$36,2,FALSE) -> #N/A | AK20: =SUM(F20:AJ20) -> 0
C21: =VLOOKUP(B21,'AP Übersicht'!$A$8:$B$36,2,FALSE) -> #N/A | AK21: =SUM(F21:AJ21) -> 0
C22: =VLOOKUP(B22,'AP Übersicht'!$A$8:$B$36,2,FALSE) -> #N/A | AK22: =SUM(F22:AJ22) -> 0
C23: =VLOOKUP(B23,'AP Übersicht'!$A$8:$B$36,2,FALSE) -> #N/A | AK23: =SUM(F23:AJ23) -> 0
C24: =VLOOKUP(B24,'AP Übersicht'!$A$8:$B$36,2,FALSE) -> #N/A | AK24: =SUM(F24:AJ24) -> 0
C25: =VLOOKUP(B25,'AP Übersicht'!$A$8:$B$36,2,FALSE) -> #N/A | AK25: =SUM(F25:AJ25) -> 0
C26: =VLOOKUP(B26,'AP Übersicht'!$A$8:$B$36,2,FALSE) -> #N/A | AK26: =SUM(F26:AJ26) -> 0
C27: =VLOOKUP(B27,'AP Übersicht'!$A$8:$B$36,2,FALSE) -> #N/A | AK27: =SUM(F27:AJ27) -> 0
C28: =VLOOKUP(B28,'AP Übersicht'!$A$8:$B$36,2,FALSE) -> #N/A | AK28: =SUM(F28:AJ28) -> 0
C29: =VLOOKUP(B29,'AP Übersicht'!$A$8:$B$36,2,FALSE) -> #N/A | AK29: =SUM(F29:AJ29) -> 0
C30: =VLOOKUP(B30,'AP Übersicht'!$A$8:$B$36,2,FALSE) -> #N/A | AK30: =SUM(F30:AJ30) -> 0
C31: Summe der förderbaren Stunden (2) | D31: x | F31: =SUMIF($D19:$D30,$D31,F19:F30) -> 0 | G31: =SUMIF($D19:$D30,$D31,G19:G30) -> 0 | H31: =SUMIF($D19:$D30,$D31,H19:H30) -> 0 | I31: =SUMIF($D19:$D30,$D31,I19:I30) -> 0 | J31: =SUMIF($D19:$D30,$D31,J19:J30) -> 0 | K31: =SUMIF($D19:$D30,$D31,K19:K30) -> 0 | L31: =SUMIF($D19:$D30,$D31,L19:L30) -> 0 | M31: =SUMIF($D19:$D30,$D31,M19:M30) -> 0 | ... AI31: =SUMIF($D19:$D30,$D31,AI19:AI30) -> 0 | AJ31: =SUMIF($D19:AH30,$D31,AJ19:AJ30) -> 0 | AK31: =SUM(F31:AJ31) -> 0
E32: x | F32: =SUMIF($E19:$E30,$E32,F19:F30) -> 0 | G32: =SUMIF($E19:$E30,$E32,G19:G30) -> 0 | H32: =SUMIF($E19:$E30,$E32,H19:H30) -> 0 | I32: =SUMIF($E19:$E30,$E32,I19:I30) -> 0 | J32: =SUMIF($E19:$E30,$E32,J19:J30) -> 0 | K32: =SUMIF($E19:$E30,$E32,K19:K30) -> 0 | L32: =SUMIF($E19:$E30,$E32,L19:L30) -> 0 | M32: =SUMIF($E19:$E30,$E32,M19:M30) -> 0 | ... AJ32: =SUMIF($E19:$E30,$E32,AJ19:AJ30) -> 0 | AK32: =SUM(F32:AJ32) -> 0
A33: 2. | C33: Nicht zuschussfähige Arbeiten | AK33: =SUM(F33:AJ33) -> 0
A34: 3. | C34: Zeitausgleich | AK34: =SUM(E34:AJ34) -> 0
C35: Urlaub (nur bezahlten Urlaub aufführen) | AK35: =SUM(F35:AJ35) -> 0
C36: Krankheit (nur bei Lohn- und Gehaltsfortzahlung) | AK36: =SUM(F36:AJ36) -> 0
C37: Sonstige bezahlte Ausfallzeiten (z. B. Feiertage) | AK37: =SUM(F37:AJ37) -> 0 | AL37: Ah | AM37: Netto Ah
AL38: =SUM(AK31:AK37) -> 0 | AM38: =NETWORKDAYS(F16,EOMONTH(A11,0))*8 -> 176
A39: (1) Die geleisteten Bearbeitungsstunden sind für den gesamten Bewilligungszeitraum eigenhändig und zeitnah, d. h. mindestens innerhalb einer Woche zu erfassen. Die Angaben sind subventionserheblich im Sinne des § 264 Strafgesetzbuch.
Q41: Datum / Unterschrift des Mitarbeiters
A42: (2) Förderbar pro Monat sind die tatsächlich für das Projekt geleisteten Stunden, jedoch nicht mehr als arbeitsvertraglich, betrieblich oder tariflich vereinbart, maximal in Höhe von 52 (Wochen) / 12 (Monate) x Wochenarbeitszeit. Überstunden sind nicht förderbar.
Q43: Datum / Unterschrift Geschäftsführer bzw. FuE-Verantwortlicher (in öffentlichen Forschungseinrichtungen)
W46: Förderkennzeichen: | AB46: =Nav!$C$6 -> DS200424
O48: Stundennachweis
O49: für pauschalierte Abrechnung gemäß Nr. 2.4 NKBF 2017 (analog Anlage 1 zum Verwendungsnachweis)
A50: Zuwendungsempfänger (Firmenstempel) | O50: Der Stundennachweis verbleibt beim Zuwendungsempfänger und ist nur nach Aufforderung vorzulegen.
A51: Vorhabenthema
A52: =Nav!$C$3 -> Durchführbarkeitsstudie "BioInk"
A54: Monat | N54: Mitarbeiter(in): [Name, Vorname]
A55: =A11+31 -> 44958 | N55: =N11 -> Socha, Pawel
A57: Die zu Lasten des Vorhabens abzurechnenden Personalstunden sind täglich eigenhändig von der betreffenden Person zu erfassen. Nur die produktiven, für das Vorhaben geleisteten Stunden sind zuwendungsfähig.
D59: technisch | E59: nicht- technisch | F59: Arbeitszeiten in Stunden je Kalendertag: | AK59: Summe Monat | AL59: ZA | AM59: offen
A60: lfd. Nr. | F60: =A55 -> 44958 | G60: =F60+1 -> 44959 | H60: =G60+1 -> 44960 | I60: =H60+1 -> 44961 | J60: =I60+1 -> 44962 | K60: =J60+1 -> 44963 | L60: =K60+1 -> 44964 | M60: =L60+1 -> 44965 | N60: =M60+1 -> 44966 | ... AG60: =AF60+1 -> 44985 | AH60: =IF(AND(DAY(DATE(YEAR($A$11),3,0))=29,YEAR($A$11)<>1900),29,"")
A61: 1. | B61: AP | C61: förderbare Projektarbeiten (1)
B62: Nr. | C62: Kurzbezeichnung des Arbeitspakets
C63: =VLOOKUP(B63,'AP Übersicht'!$A$8:$B$36,2,FALSE) -> #N/A | AK63: =SUM(F63:AJ63) -> 0 | AL63: =VLOOKUP($B63,'AP Übersicht'!$A$8:$R$36,13,FALSE) -> #N/A | AM63: =VLOOKUP($B63,'AP Übersicht'!$A$8:$R$36,14,FALSE) -> #N/A
C64: =VLOOKUP(B64,'AP Übersicht'!$A$8:$B$36,2,FALSE) -> #N/A | AK64: =SUM(F64:AJ64) -> 0
C65: =VLOOKUP(B65,'AP Übersicht'!$A$8:$B$36,2,FALSE) -> #N/A | AK65: =SUM(F65:AJ65) -> 0
C66: =VLOOKUP(B66,'AP Übersicht'!$A$8:$B$36,2,FALSE) -> #N/A | AK66: =SUM(F66:AJ66) -> 0
C67: =VLOOKUP(B67,'AP Übersicht'!$A$8:$B$36,2,FALSE) -> #N/A | AK67: =SUM(F67:AJ67) -> 0
C68: =VLOOKUP(B68,'AP Übersicht'!$A$8:$B$36,2,FALSE) -> #N/A | AK68: =SUM(F68:AJ68) -> 0
C69: =VLOOKUP(B69,'AP Übersicht'!$A$8:$B$36,2,FALSE) -> #N/A | AK69: =SUM(F69:AJ69) -> 0
C70: =VLOOKUP(B70,'AP Übersicht'!$A$8:$B$36,2,FALSE) -> #N/A | AK70: =SUM(F70:AJ70) -> 0
C71: =VLOOKUP(B71,'AP Übersicht'!$A$8:$B$36,2,FALSE) -> #N/A | AK71: =SUM(F71:AJ71) -> 0
C72: =VLOOKUP(B72,'AP Übersicht'!$A$8:$B$36,2,FALSE) -> #N/A | AK72: =SUM(F72:AJ72) -> 0
C73: =VLOOKUP(B73,'AP Übersicht'!$A$8:$B$36,2,FALSE) -> #N/A | AK73: =SUM(F73:AJ73) -> 0
C74: =VLOOKUP(B74,'AP Übersicht'!$A$8:$B$36,2,FALSE) -> #N/A | AK74: =SUM(F74:AJ74) -> 0
C75: Summe der förderbaren Stunden (2) | D75: x | F75: =SUMIF($D63:$D74,$D75,F63:F74) -> 0 | G75: =SUMIF($D63:$D74,$D75,G63:G74) -> 0 | H75: =SUMIF($D63:$D74,$D75,H63:H74) -> 0 | I75: =SUMIF($D63:$D74,$D75,I63:I74) -> 0 | J75: =SUMIF($D63:$D74,$D75,J63:J74) -> 0 | K75: =SUMIF($D63:$D74,$D75,K63:K74) -> 0 | L75: =SUMIF($D63:$D74,$D75,L63:L74) -> 0 | M75: =SUMIF($D63:$D74,$D75,M63:M74) -> 0 | ... AI75: =SUMIF($D63:$D74,$D75,AI63:AI74) -> 0 | AJ75: =SUMIF($D63:AH74,$D75,AJ63:AJ74) -> 0 | AK75: =SUM(F75:AJ75) -> 0
E76: x | F76: =SUMIF($E63:$E74,$E76,F63:F74) -> 0 | G76: =SUMIF($E63:$E74,$E76,G63:G74) -> 0 | H76: =SUMIF($E63:$E74,$E76,H63:H74) -> 0 | I76: =SUMIF($E63:$E74,$E76,I63:I74) -> 0 | J76: =SUMIF($E63:$E74,$E76,J63:J74) -> 0 | K76: =SUMIF($E63:$E74,$E76,K63:K74) -> 0 | L76: =SUMIF($E63:$E74,$E76,L63:L74) -> 0 | M76: =SUMIF($E63:$E74,$E76,M63:M74) -> 0 | ... AJ76: =SUMIF($E63:$E74,$E76,AJ63:AJ74) -> 0 | AK76: =SUM(F76:AJ76) -> 0
A77: 2. | C77: Nicht zuschussfähige Arbeiten | AK77: =SUM(F77:AJ77) -> 0
A78: 3. | C78: Zeitausgleich | AK78: =SUM(E78:AJ78) -> 0
C79: Urlaub (nur bezahlten Urlaub aufführen) | AK79: =SUM(F79:AJ79) -> 0
C80: Krankheit (nur bei Lohn- und Gehaltsfortzahlung) | AK80: =SUM(F80:AJ80) -> 0
C81: Sonstige bezahlte Ausfallzeiten (z. B. Feiertage) | AK81: =SUM(F81:AJ81) -> 0 | AL81: Ah | AM81: Netto Ah
AL82: =SUM(AK75:AK81) -> 0 | AM82: =NETWORKDAYS(F60,EOMONTH(A55,0))*8 -> 160
A83: (1) Die geleisteten Bearbeitungsstunden sind für den gesamten Bewilligungszeitraum eigenhändig und zeitnah, d. h. mindestens innerhalb einer Woche zu erfassen. Die Angaben sind subventionserheblich im Sinne des § 264 Strafgesetzbuch.
Q85: Datum / Unterschrift des Mitarbeiters
A86: (2) Förderbar pro Monat sind die tatsächlich für das Projekt geleisteten Stunden, jedoch nicht mehr als arbeitsvertraglich, betrieblich oder tariflich vereinbart, maximal in Höhe von 52 (Wochen) / 12 (Monate) x Wochenarbeitszeit. Überstunden sind nicht förderbar.
Q87: Datum / Unterschrift Geschäftsführer bzw. FuE-Verantwortlicher (in öffentlichen Forschungseinrichtungen)
W90: Förderkennzeichen: | AB90: =Nav!$C$6 -> DS200424
O92: Stundennachweis
O93: für pauschalierte Abrechnung gemäß Nr. 2.4 NKBF 2017 (analog Anlage 1 zum Verwendungsnachweis)
A94: Zuwendungsempfänger (Firmenstempel) | O94: Der Stundennachweis verbleibt beim Zuwendungsempfänger und ist nur nach Aufforderung vorzulegen.
A95: Vorhabenthema
A96: =Nav!$C$3 -> Durchführbarkeitsstudie "BioInk"
A98: Monat | N98: Mitarbeiter(in): [Name, Vorname]
A99: =IF(AND(DAY(DATE(YEAR($A$11),3,0))=29,YEAR($A$11)<>1900),A55+29,A55+28) -> 44986 | N99: =N55 -> Socha, Pawel
A101: Die zu Lasten des Vorhabens abzurechnenden Personalstunden sind täglich eigenhändig von der betreffenden Person zu erfassen. Nur die produktiven, für das Vorhaben geleisteten Stunden sind zuwendungsfähig.
D103: technisch | E103: nicht- technisch | F103: Arbeitszeiten in Stunden je Kalendertag: | AK103: Summe Monat | AL103: ZA | AM103: offen
A104: lfd. Nr. | F104: =A99 -> 44986 | G104: =F104+1 -> 44987 | H104: =G104+1 -> 44988 | I104: =H104+1 -> 44989 | J104: =I104+1 -> 44990 | K104: =J104+1 -> 44991 | L104: =K104+1 -> 44992 | M104: =L104+1 -> 44993 | N104: =M104+1 -> 44994 | ... AJ104: =AI104+1 -> 45016
A105: 1. | B105: AP | C105: förderbare Projektarbeiten (1)
B106: Nr. | C106: Kurzbezeichnung des Arbeitspakets
C107: =VLOOKUP(B107,'AP Übersicht'!$A$8:$B$36,2,FALSE) -> #N/A | AK107: =SUM(F107:AJ107) -> 0 | AL107: =VLOOKUP($B107,'AP Übersicht'!$A$8:$R$36,13,FALSE) -> #N/A | AM107: =VLOOKUP($B107,'AP Übersicht'!$A$8:$R$36,14,FALSE) -> #N/A
C108: =VLOOKUP(B108,'AP Übersicht'!$A$8:$B$36,2,FALSE) -> #N/A | AK108: =SUM(F108:AJ108) -> 0
C109: =VLOOKUP(B109,'AP Übersicht'!$A$8:$B$36,2,FALSE) -> #N/A | AK109: =SUM(F109:AJ109) -> 0
C110: =VLOOKUP(B110,'AP Übersicht'!$A$8:$B$36,2,FALSE) -> #N/A | AK110: =SUM(F110:AJ110) -> 0
C111: =VLOOKUP(B111,'AP Übersicht'!$A$8:$B$36,2,FALSE) -> #N/A | AK111: =SUM(F111:AJ111) -> 0
C112: =VLOOKUP(B112,'AP Übersicht'!$A$8:$B$36,2,FALSE) -> #N/A | AK112: =SUM(F112:AJ112) -> 0
C113: =VLOOKUP(B113,'AP Übersicht'!$A$8:$B$36,2,FALSE) -> #N/A | AK113: =SUM(F113:AJ113) -> 0
C114: =VLOOKUP(B114,'AP Übersicht'!$A$8:$B$36,2,FALSE) -> #N/A | AK114: =SUM(F114:AJ114) -> 0
C115: =VLOOKUP(B115,'AP Übersicht'!$A$8:$B$36,2,FALSE) -> #N/A | AK115: =SUM(F115:AJ115) -> 0
C116: =VLOOKUP(B116,'AP Übersicht'!$A$8:$B$36,2,FALSE) -> #N/A | AK116: =SUM(F116:AJ116) -> 0
C117: =VLOOKUP(B117,'AP Übersicht'!$A$8:$B$36,2,FALSE) -> #N/A | AK117: =SUM(F117:AJ117) -> 0
C118: =VLOOKUP(B118,'AP Übersicht'!$A$8:$B$36,2,FALSE) -> #N/A | AK118: =SUM(F118:AJ118) -> 0
C119: Summe der förderbaren Stunden (2) | D119: x | F119: =SUMIF($D107:$D118,$D119,F107:F118) -> 0 | G119: =SUMIF($D107:$D118,$D119,G107:G118) -> 0 | H119: =SUMIF($D107:$D118,$D119,H107:H118) -> 0 | I119: =SUMIF($D107:$D118,$D119,I107:I118) -> 0 | J119: =SUMIF($D107:$D118,$D119,J107:J118) -> 0 | K119: =SUMIF($D107:$D118,$D119,K107:K118) -> 0 | L119: =SUMIF($D107:$D118,$D119,L107:L118) -> 0 | M119: =SUMIF($D107:$D118,$D119,M107:M118) -> 0 | ... AI119: =SUMIF($D107:$D118,$D119,AI107:AI118) -> 0 | AJ119: =SUMIF($D107:AH118,$D119,AJ107:AJ118) -> 0 | AK119: =SUM(F119:AJ119) -> 0
...

Sheet Tippl K. J1
W2: Förderkennzeichen: | AB2: =Nav!$C$6 -> DS200424
O4: Stundennachweis
O5: für pauschalierte Abrechnung gemäß Nr. 2.4 NKBF 2017 (analog Anlage 1 zum Verwendungsnachweis)
A6: Zuwendungsempfänger (Firmenstempel) | O6: Der Stundennachweis verbleibt beim Zuwendungsempfänger und ist nur nach Aufforderung vorzulegen.
A7: Vorhabenthema
A8: =Nav!$C$3 -> Durchführbarkeitsstudie "BioInk"
A10: Monat | N10: Mitarbeiter(in): [Name, Vorname]
A11: =DATE(YEAR(Nav!$L$4),1,1) -> 44927 | N11: ='Planung Personal'!$B$13 -> Tippl, Karen
A13: Die zu Lasten des Vorhabens abzurechnenden Personalstunden sind täglich eigenhändig von der betreffenden Person zu erfassen. Nur die produktiven, für das Vorhaben geleisteten Stunden sind zuwendungsfähig.
D15: technisch | E15: nicht- technisch | F15: Arbeitszeiten in Stunden je Kalendertag: | AK15: Summe Monat | AL15: ZA | AM15: offen
A16: lfd. Nr. | F16: =A11 -> 44927 | G16: =F16+1 -> 44928 | H16: =G16+1 -> 44929 | I16: =H16+1 -> 44930 | J16: =I16+1 -> 44931 | K16: =J16+1 -> 44932 | L16: =K16+1 -> 44933 | M16: =L16+1 -> 44934 | N16: =M16+1 -> 44935 | ... AJ16: =AI16+1 -> 44957
A17: 1. | B17: AP | C17: förderbare Projektarbeiten (1)
B18: Nr. | C18: Kurzbezeichnung des Arbeitspakets
C19: =VLOOKUP(B19,'AP Übersicht'!$A$8:$B$36,2,FALSE) -> #N/A | AK19: =SUM(F19:AJ19) -> 0 | AL19: =VLOOKUP($B19,'AP Übersicht'!$A$8:$R$36,17,FALSE) -> #N/A | AM19: =VLOOKUP($B19,'AP Übersicht'!$A$8:$R$36,18,FALSE) -> #N/A
C20: =VLOOKUP(B20,'AP Übersicht'!$A$8:$B$36,2,FALSE) -> #N/A | AK20: =SUM(F20:AJ20) -> 0 | AL20: =VLOOKUP($B20,'AP Übersicht'!$A$8:$R$36,17,FALSE) -> #N/A | AM20: =VLOOKUP($B20,'AP Übersicht'!$A$8:$R$36,18,FALSE) -> #N/A
C21: =VLOOKUP(B21,'AP Übersicht'!$A$8:$B$36,2,FALSE) -> #N/A | AK21: =SUM(F21:AJ21) -> 0
C22: =VLOOKUP(B22,'AP Übersicht'!$A$8:$B$36,2,FALSE) -> #N/A | AK22: =SUM(F22:AJ22) -> 0
C23: =VLOOKUP(B23,'AP Übersicht'!$A$8:$B$36,2,FALSE) -> #N/A | AK23: =SUM(F23:AJ23) -> 0
C24: =VLOOKUP(B24,'AP Übersicht'!$A$8:$B$36,2,FALSE) -> #N/A | AK24: =SUM(F24:AJ24) -> 0
C25: =VLOOKUP(B25,'AP Übersicht'!$A$8:$B$36,2,FALSE) -> #N/A | AK25: =SUM(F25:AJ25) -> 0
C26: =VLOOKUP(B26,'AP Übersicht'!$A$8:$B$36,2,FALSE) -> #N/A | AK26: =SUM(F26:AJ26) -> 0
C27: =VLOOKUP(B27,'AP Übersicht'!$A$8:$B$36,2,FALSE) -> #N/A | AK27: =SUM(F27:AJ27) -> 0
C28: =VLOOKUP(B28,'AP Übersicht'!$A$8:$B$36,2,FALSE) -> #N/A | AK28: =SUM(F28:AJ28) -> 0
C29: =VLOOKUP(B29,'AP Übersicht'!$A$8:$B$36,2,FALSE) -> #N/A | AK29: =SUM(F29:AJ29) -> 0
C30: =VLOOKUP(B30,'AP Übersicht'!$A$8:$B$36,2,FALSE) -> #N/A | AK30: =SUM(F30:AJ30) -> 0
C31: Summe der förderbaren Stunden (2) | D31: x | F31: =SUMIF($D19:$D30,$D31,F19:F30) -> 0 | G31: =SUMIF($D19:$D30,$D31,G19:G30) -> 0 | H31: =SUMIF($D19:$D30,$D31,H19:H30) -> 0 | I31: =SUMIF($D19:$D30,$D31,I19:I30) -> 0 | J31: =SUMIF($D19:$D30,$D31,J19:J30) -> 0 | K31: =SUMIF($D19:$D30,$D31,K19:K30) -> 0 | L31: =SUMIF($D19:$D30,$D31,L19:L30) -> 0 | M31: =SUMIF($D19:$D30,$D31,M19:M30) -> 0 | ... AJ31: =SUMIF($D19:$D30,$D31,AJ19:AJ30) -> 0 | AK31: =SUM(F31:AJ31) -> 0
E32: x | F32: =SUMIF($E19:$E30,$E32,F19:F30) -> 0 | G32: =SUMIF($E19:$E30,$E32,G19:G30) -> 0 | H32: =SUMIF($E19:$E30,$E32,H19:H30) -> 0 | I32: =SUMIF($E19:$E30,$E32,I19:I30) -> 0 | J32: =SUMIF($E19:$E30,$E32,J19:J30) -> 0 | K32: =SUMIF($E19:$E30,$E32,K19:K30) -> 0 | L32: =SUMIF($E19:$E30,$E32,L19:L30) -> 0 | M32: =SUMIF($E19:$E30,$E32,M19:M30) -> 0 | ... AJ32: =SUMIF($E19:$E30,$E32,AJ19:AJ30) -> 0 | AK32: =SUM(F32:AJ32) -> 0
A33: 2. | C33: Nicht zuschussfähige Arbeiten | AK33: =SUM(F33:AJ33) -> 0
A34: 3. | C34: Zeitausgleich | AK34: =SUM(E34:AJ34) -> 0
C35: Urlaub (nur bezahlten Urlaub aufführen) | AK35: =SUM(F35:AJ35) -> 0
C36: Krankheit (nur bei Lohn- und Gehaltsfortzahlung) | AK36: =SUM(F36:AJ36) -> 0
C37: Sonstige bezahlte Ausfallzeiten (z. B. Feiertage) | AK37: =SUM(F37:AJ37) -> 0 | AL37: Ah | AM37: Netto Ah
AL38: =SUM(AK31:AK37) -> 0 | AM38: =NETWORKDAYS(F16,EOMONTH(A11,0))*8 -> 176
A39: (1) Die geleisteten Bearbeitungsstunden sind für den gesamten Bewilligungszeitraum eigenhändig und zeitnah, d. h. mindestens innerhalb einer Woche zu erfassen. Die Angaben sind subventionserheblich im Sinne des § 264 Strafgesetzbuch.
Q40: =IF(WEEKDAY(EOMONTH(A11,0),2)=7,EOMONTH(A11,0)-2,IF(WEEKDAY(EOMONTH(11,0),2)=6,EOMONTH(A11,0)-1,EOMONTH(A11,0))) -> 44957
Q41: Datum / Unterschrift des Mitarbeiters
A42: (2) Förderbar pro Monat sind die tatsächlich für das Projekt geleisteten Stunden, jedoch nicht mehr als arbeitsvertraglich, betrieblich oder tariflich vereinbart, maximal in Höhe von 52 (Wochen) / 12 (Monate) x Wochenarbeitszeit. Überstunden sind nicht förderbar. | Q42: =Q40 -> 44957
Q43: Datum / Unterschrift Geschäftsführer bzw. FuE-Verantwortlicher (in öffentlichen Forschungseinrichtungen)
W46: Förderkennzeichen: | AB46: =Nav!$C$6 -> DS200424
O48: Stundennachweis
O49: für pauschalierte Abrechnung gemäß Nr. 2.4 NKBF 2017 (analog Anlage 1 zum Verwendungsnachweis)
A50: Zuwendungsempfänger (Firmenstempel) | O50: Der Stundennachweis verbleibt beim Zuwendungsempfänger und ist nur nach Aufforderung vorzulegen.
A51: Vorhabenthema
A52: =Nav!$C$3 -> Durchführbarkeitsstudie "BioInk"
A54: Monat | N54: Mitarbeiter(in): [Name, Vorname]
A55: =A11+31 -> 44958 | N55: =N11 -> Tippl, Karen
A57: Die zu Lasten des Vorhabens abzurechnenden Personalstunden sind täglich eigenhändig von der betreffenden Person zu erfassen. Nur die produktiven, für das Vorhaben geleisteten Stunden sind zuwendungsfähig.
D59: technisch | E59: nicht- technisch | F59: Arbeitszeiten in Stunden je Kalendertag: | AK59: Summe Monat | AL59: ZA | AM59: offen
A60: lfd. Nr. | F60: =A55 -> 44958 | G60: =F60+1 -> 44959 | H60: =G60+1 -> 44960 | I60: =H60+1 -> 44961 | J60: =I60+1 -> 44962 | K60: =J60+1 -> 44963 | L60: =K60+1 -> 44964 | M60: =L60+1 -> 44965 | N60: =M60+1 -> 44966 | ... AG60: =AF60+1 -> 44985 | AH60: =IF(AND(DAY(DATE(YEAR($A$11),3,0))=29,YEAR($A$11)<>1900),29,"")
A61: 1. | B61: AP | C61: förderbare Projektarbeiten (1)
B62: Nr. | C62: Kurzbezeichnung des Arbeitspakets
C63: =VLOOKUP(B63,'AP Übersicht'!$A$8:$B$36,2,FALSE) -> #N/A | AK63: =SUM(F63:AJ63) -> 0 | AL63: =VLOOKUP($B63,'AP Übersicht'!$A$8:$R$36,17,FALSE) -> #N/A | AM63: =VLOOKUP($B63,'AP Übersicht'!$A$8:$R$36,18,FALSE) -> #N/A
C64: =VLOOKUP(B64,'AP Übersicht'!$A$8:$B$36,2,FALSE) -> #N/A | AK64: =SUM(F64:AJ64) -> 0 | AL64: =VLOOKUP($B64,'AP Übersicht'!$A$8:$R$36,17,FALSE) -> #N/A | AM64: =VLOOKUP($B64,'AP Übersicht'!$A$8:$R$36,18,FALSE) -> #N/A
C65: =VLOOKUP(B65,'AP Übersicht'!$A$8:$B$36,2,FALSE) -> #N/A | AK65: =SUM(F65:AJ65) -> 0
C66: =VLOOKUP(B66,'AP Übersicht'!$A$8:$B$36,2,FALSE) -> #N/A | AK66: =SUM(F66:AJ66) -> 0
C67: =VLOOKUP(B67,'AP Übersicht'!$A$8:$B$36,2,FALSE) -> #N/A | AK67: =SUM(F67:AJ67) -> 0
C68: =VLOOKUP(B68,'AP Übersicht'!$A$8:$B$36,2,FALSE) -> #N/A | AK68: =SUM(F68:AJ68) -> 0
C69: =VLOOKUP(B69,'AP Übersicht'!$A$8:$B$36,2,FALSE) -> #N/A | AK69: =SUM(F69:AJ69) -> 0
C70: =VLOOKUP(B70,'AP Übersicht'!$A$8:$B$36,2,FALSE) -> #N/A | AK70: =SUM(F70:AJ70) -> 0
C71: =VLOOKUP(B71,'AP Übersicht'!$A$8:$B$36,2,FALSE) -> #N/A | AK71: =SUM(F71:AJ71) -> 0
C72: =VLOOKUP(B72,'AP Übersicht'!$A$8:$B$36,2,FALSE) -> #N/A | AK72: =SUM(F72:AJ72) -> 0
C73: =VLOOKUP(B73,'AP Übersicht'!$A$8:$B$36,2,FALSE) -> #N/A | AK73: =SUM(F73:AJ73) -> 0
C74: =VLOOKUP(B74,'AP Übersicht'!$A$8:$B$36,2,FALSE) -> #N/A | AK74: =SUM(F74:AJ74) -> 0
C75: Summe der förderbaren Stunden (2) | D75: x | F75: =SUMIF($D63:$D74,$D75,F63:F74) -> 0 | G75: =SUMIF($D63:$D74,$D75,G63:G74) -> 0 | H75: =SUMIF($D63:$D74,$D75,H63:H74) -> 0 | I75: =SUMIF($D63:$D74,$D75,I63:I74) -> 0 | J75: =SUMIF($D63:$D74,$D75,J63:J74) -> 0 | K75: =SUMIF($D63:$D74,$D75,K63:K74) -> 0 | L75: =SUMIF($D63:$D74,$D75,L63:L74) -> 0 | M75: =SUMIF($D63:$D74,$D75,M63:M74) -> 0 | ... AJ75: =SUMIF($D63:$D74,$D75,AJ63:AJ74) -> 0 | AK75: =SUM(F75:AJ75) -> 0
E76: x | F76: =SUMIF($E63:$E74,$E76,F63:F74) -> 0 | G76: =SUMIF($E63:$E74,$E76,G63:G74) -> 0 | H76: =SUMIF($E63:$E74,$E76,H63:H74) -> 0 | I76: =SUMIF($E63:$E74,$E76,I63:I74) -> 0 | J76: =SUMIF($E63:$E74,$E76,J63:J74) -> 0 | K76: =SUMIF($E63:$E74,$E76,K63:K74) -> 0 | L76: =SUMIF($E63:$E74,$E76,L63:L74) -> 0 | M76: =SUMIF($E63:$E74,$E76,M63:M74) -> 0 | ... AJ76: =SUMIF($E63:$E74,$E76,AJ63:AJ74) -> 0 | AK76: =SUM(F76:AJ76) -> 0
A77: 2. | C77: Nicht zuschussfähige Arbeiten | AK77: =SUM(F77:AJ77) -> 0
A78: 3. | C78: Zeitausgleich | AK78: =SUM(E78:AJ78) -> 0
C79: Urlaub (nur bezahlten Urlaub aufführen) | AK79: =SUM(F79:AJ79) -> 0
C80: Krankheit (nur bei Lohn- und Gehaltsfortzahlung) | AK80: =SUM(F80:AJ80) -> 0
C81: Sonstige bezahlte Ausfallzeiten (z. B. Feiertage) | AK81: =SUM(F81:AJ81) -> 0 | AL81: Ah | AM81: Netto Ah
AL82: =SUM(AK75:AK81) -> 0 | AM82: =NETWORKDAYS(F60,EOMONTH(A55,0))*8 -> 160
A83: (1) Die geleisteten Bearbeitungsstunden sind für den gesamten Bewilligungszeitraum eigenhändig und zeitnah, d. h. mindestens innerhalb einer Woche zu erfassen. Die Angaben sind subventionserheblich im Sinne des § 264 Strafgesetzbuch.
Q84: =IF(WEEKDAY(EOMONTH(A55,0),2)=7,EOMONTH(A55,0)-2,IF(WEEKDAY(EOMONTH(11,0),2)=6,EOMONTH(A55,0)-1,EOMONTH(A55,0))) -> 44985
Q85: Datum / Unterschrift des Mitarbeiters
A86: (2) Förderbar pro Monat sind die tatsächlich für das Projekt geleisteten Stunden, jedoch nicht mehr als arbeitsvertraglich, betrieblich oder tariflich vereinbart, maximal in Höhe von 52 (Wochen) / 12 (Monate) x Wochenarbeitszeit. Überstunden sind nicht förderbar. | Q86: =Q84 -> 44985
Q87: Datum / Unterschrift Geschäftsführer bzw. FuE-Verantwortlicher (in öffentlichen Forschungseinrichtungen)
W90: Förderkennzeichen: | AB90: =Nav!$C$6 -> DS200424
O92: Stundennachweis
O93: für pauschalierte Abrechnung gemäß Nr. 2.4 NKBF 2017 (analog Anlage 1 zum Verwendungsnachweis)
A94: Zuwendungsempfänger (Firmenstempel) | O94: Der Stundennachweis verbleibt beim Zuwendungsempfänger und ist nur nach Aufforderung vorzulegen.
A95: Vorhabenthema
A96: =Nav!$C$3 -> Durchführbarkeitsstudie "BioInk"
A98: Monat | N98: Mitarbeiter(in): [Name, Vorname]
A99: =IF(AND(DAY(DATE(YEAR($A$11),3,0))=29,YEAR($A$11)<>1900),A55+29,A55+28) -> 44986 | N99: =N55 -> Tippl, Karen
A101: Die zu Lasten des Vorhabens abzurechnenden Personalstunden sind täglich eigenhändig von der betreffenden Person zu erfassen. Nur die produktiven, für das Vorhaben geleisteten Stunden sind zuwendungsfähig.
D103: technisch | E103: nicht- technisch | F103: Arbeitszeiten in Stunden je Kalendertag: | AK103: Summe Monat | AL103: ZA | AM103: offen
A104: lfd. Nr. | F104: =A99 -> 44986 | G104: =F104+1 -> 44987 | H104: =G104+1 -> 44988 | I104: =H104+1 -> 44989 | J104: =I104+1 -> 44990 | K104: =J104+1 -> 44991 | L104: =K104+1 -> 44992 | M104: =L104+1 -> 44993 | N104: =M104+1 -> 44994 | ... AJ104: =AI104+1 -> 45016
A105: 1. | B105: AP | C105: förderbare Projektarbeiten (1)
B106: Nr. | C106: Kurzbezeichnung des Arbeitspakets
C107: =VLOOKUP(B107,'AP Übersicht'!$A$8:$B$36,2,FALSE) -> #N/A | AK107: =SUM(F107:AJ107) -> 0 | AL107: =VLOOKUP($B107,'AP Übersicht'!$A$8:$R$36,17,FALSE) -> #N/A | AM107: =VLOOKUP($B107,'AP Übersicht'!$A$8:$R$36,18,FALSE) -> #N/A
C108: =VLOOKUP(B108,'AP Übersicht'!$A$8:$B$36,2,FALSE) -> #N/A | AK108: =SUM(F108:AJ108) -> 0 | AL108: =VLOOKUP($B108,'AP Übersicht'!$A$8:$R$36,17,FALSE) -> #N/A | AM108: =VLOOKUP($B108,'AP Übersicht'!$A$8:$R$36,18,FALSE) -> #N/A
C109: =VLOOKUP(B109,'AP Übersicht'!$A$8:$B$36,2,FALSE) -> #N/A | AK109: =SUM(F109:AJ109) -> 0
C110: =VLOOKUP(B110,'AP Übersicht'!$A$8:$B$36,2,FALSE) -> #N/A | AK110: =SUM(F110:AJ110) -> 0
C111: =VLOOKUP(B111,'AP Übersicht'!$A$8:$B$36,2,FALSE) -> #N/A | AK111: =SUM(F111:AJ111) -> 0
C112: =VLOOKUP(B112,'AP Übersicht'!$A$8:$B$36,2,FALSE) -> #N/A | AK112: =SUM(F112:AJ112) -> 0
C113: =VLOOKUP(B113,'AP Übersicht'!$A$8:$B$36,2,FALSE) -> #N/A | AK113: =SUM(F113:AJ113) -> 0
C114: =VLOOKUP(B114,'AP Übersicht'!$A$8:$B$36,2,FALSE) -> #N/A | AK114: =SUM(F114:AJ114) -> 0
C115: =VLOOKUP(B115,'AP Übersicht'!$A$8:$B$36,2,FALSE) -> #N/A | AK115: =SUM(F115:AJ115) -> 0
C116: =VLOOKUP(B116,'AP Übersicht'!$A$8:$B$36,2,FALSE) -> #N/A | AK116: =SUM(F116:AJ116) -> 0
C117: =VLOOKUP(B117,'AP Übersicht'!$A$8:$B$36,2,FALSE) -> #N/A | AK117: =SUM(F117:AJ117) -> 0
...

Sheet MA4 J1
W2: Förderkennzeichen: | AB2: =Nav!$C$6 -> DS200424
O4: Stundennachweis
O5: Fördermodul Netzwerkprojekte des Bundesministeriums für Wirtschaft und Energie (BMWi)
A6: Zuwendungsempfänger (Firmenstempel) | O6: Der Stundennachweis verbleibt beim Zuwendungsempfänger und ist nur nach Aufforderung vorzulegen.
A7: Vorhabenthema
A8: =Nav!$C$3 -> Durchführbarkeitsstudie "BioInk"
A10: Monat | N10: Mitarbeiter(in): [Name, Vorname]
A11: =DATE(YEAR(Nav!$L$4),1,1) -> 44927 | N11: ='Planung Personal'!$B$15 -> MA 4
A13: Die zu Lasten des Vorhabens abzurechnenden Personalstunden sind täglich eigenhändig von der betreffenden Person zu erfassen. Nur die produktiven, für das Vorhaben geleisteten Stunden sind zuwendungsfähig.
D15: technisch | E15: nicht- technisch | F15: Arbeitszeiten in Stunden je Kalendertag: | AK15: Summe Monat
A16: lfd. Nr. | F16: =A11 -> 44927 | G16: =F16+1 -> 44928 | H16: =G16+1 -> 44929 | I16: =H16+1 -> 44930 | J16: =I16+1 -> 44931 | K16: =J16+1 -> 44932 | L16: =K16+1 -> 44933 | M16: =L16+1 -> 44934 | N16: =M16+1 -> 44935 | ... AJ16: =AI16+1 -> 44957
A17: 1. | B17: AP | C17: förderbare Projektarbeiten (1)
B18: Nr. | C18: Kurzbezeichnung des Arbeitspakets
C19: =VLOOKUP(B19,'AP Übersicht'!$A$8:$B$36,2,FALSE) -> #N/A | AK19: =SUM(F19:AJ19) -> 0
C20: =VLOOKUP(B20,'AP Übersicht'!$A$8:$B$36,2,FALSE) -> #N/A | AK20: =SUM(F20:AJ20) -> 0
C21: =VLOOKUP(B21,'AP Übersicht'!$A$8:$B$36,2,FALSE) -> #N/A | AK21: =SUM(F21:AJ21) -> 0
C22: =VLOOKUP(B22,'AP Übersicht'!$A$8:$B$36,2,FALSE) -> #N/A | AK22: =SUM(F22:AJ22) -> 0
C23: =VLOOKUP(B23,'AP Übersicht'!$A$8:$B$36,2,FALSE) -> #N/A | AK23: =SUM(F23:AJ23) -> 0
C24: =VLOOKUP(B24,'AP Übersicht'!$A$8:$B$36,2,FALSE) -> #N/A | AK24: =SUM(F24:AJ24) -> 0
C25: =VLOOKUP(B25,'AP Übersicht'!$A$8:$B$36,2,FALSE) -> #N/A | AK25: =SUM(F25:AJ25) -> 0
C26: =VLOOKUP(B26,'AP Übersicht'!$A$8:$B$36,2,FALSE) -> #N/A | AK26: =SUM(F26:AJ26) -> 0
C27: =VLOOKUP(B27,'AP Übersicht'!$A$8:$B$36,2,FALSE) -> #N/A | AK27: =SUM(F27:AJ27) -> 0
C28: =VLOOKUP(B28,'AP Übersicht'!$A$8:$B$36,2,FALSE) -> #N/A | AK28: =SUM(F28:AJ28) -> 0
C29: =VLOOKUP(B29,'AP Übersicht'!$A$8:$B$36,2,FALSE) -> #N/A | AK29: =SUM(F29:AJ29) -> 0
C30: =VLOOKUP(B30,'AP Übersicht'!$A$8:$B$36,2,FALSE) -> #N/A | AK30: =SUM(F30:AJ30) -> 0
C31: Summe der förderbaren Stunden (2) | F31: =SUM(F17:F30) -> 0 | G31: =SUM(G17:G30) -> 0 | H31: =SUM(H17:H30) -> 0 | I31: =SUM(I17:I30) -> 0 | J31: =SUM(J17:J30) -> 0 | K31: =SUM(K17:K30) -> 0 | L31: =SUM(L17:L30) -> 0 | M31: =SUM(M17:M30) -> 0 | ... AJ31: =SUM(AJ17:AJ30) -> 0 | AK31: =SUM(AK19:AK30) -> 0
A32: 2. | C32: Nicht zuschussfähige Arbeiten | AK32: =SUM(F32:AJ32) -> 0
A33: 3. | C33: Zeitausgleich | AK33: =SUM(E33:AJ33) -> 0
C34: Urlaub (nur bezahlten Urlaub aufführen) | AK34: =SUM(F34:AJ34) -> 0
C35: Krankheit (nur bei Lohn- und Gehaltsfortzahlung) | AK35: =SUM(F35:AJ35) -> 0
C36: Sonstige bezahlte Ausfallzeiten (z. B. Feiertage) | AK36: =SUM(F36:AJ36) -> 0
AK37: =SUM(AK31:AK36) -> 0
A38: (1) Die geleisteten Bearbeitungsstunden sind für den gesamten Bewilligungszeitraum eigenhändig und zeitnah, d. h. mindestens innerhalb einer Woche zu erfassen. Die Angaben sind subventionserheblich im Sinne des § 264 Strafgesetzbuch.
Q40: Datum / Unterschrift des Mitarbeiters
A41: (2) Förderbar pro Monat sind die tatsächlich für das Projekt geleisteten Stunden, jedoch nicht mehr als arbeitsvertraglich, betrieblich oder tariflich vereinbart, maximal in Höhe von 52 (Wochen) / 12 (Monate) x Wochenarbeitszeit. Überstunden sind nicht förderbar.
Q42: Datum / Unterschrift Geschäftsführer bzw. FuE-Verantwortlicher (in öffentlichen Forschungseinrichtungen)
W45: Förderkennzeichen: | AB45: =Nav!$C$6 -> DS200424
O47: Stundennachweis
O48: Fördermodul Netzwerkprojekte des Bundesministeriums für Wirtschaft und Energie (BMWi)
A49: Zuwendungsempfänger (Firmenstempel) | O49: Der Stundennachweis verbleibt beim Zuwendungsempfänger und ist nur nach Aufforderung vorzulegen.
A50: Vorhabenthema
A51: =Nav!$C$3 -> Durchführbarkeitsstudie "BioInk"
A53: Monat | N53: Mitarbeiter(in): [Name, Vorname]
A54: =A11+31 -> 44958 | N54: =N11 -> MA 4
A56: Die zu Lasten des Vorhabens abzurechnenden Personalstunden sind täglich eigenhändig von der betreffenden Person zu erfassen. Nur die produktiven, für das Vorhaben geleisteten Stunden sind zuwendungsfähig.
D58: technisch | E58: nicht- technisch | F58: Arbeitszeiten in Stunden je Kalendertag: | AK58: Summe Monat
A59: lfd. Nr. | F59: =A54 -> 44958 | G59: =F59+1 -> 44959 | H59: =G59+1 -> 44960 | I59: =H59+1 -> 44961 | J59: =I59+1 -> 44962 | K59: =J59+1 -> 44963 | L59: =K59+1 -> 44964 | M59: =L59+1 -> 44965 | N59: =M59+1 -> 44966 | ... AG59: =AF59+1 -> 44985 | AH59: =IF(AND(DAY(DATE(YEAR($A$11),3,0))=29,YEAR($A$11)<>1900),29,"")
A60: 1. | B60: AP | C60: förderbare Projektarbeiten (1)
B61: Nr. | C61: Kurzbezeichnung des Arbeitspakets
C62: =VLOOKUP(B62,'AP Übersicht'!$A$8:$B$36,2,FALSE) -> #N/A | AK62: =SUM(F62:AJ62) -> 0
C63: =VLOOKUP(B63,'AP Übersicht'!$A$8:$B$36,2,FALSE) -> #N/A | AK63: =SUM(F63:AJ63) -> 0
C64: =VLOOKUP(B64,'AP Übersicht'!$A$8:$B$36,2,FALSE) -> #N/A | AK64: =SUM(F64:AJ64) -> 0
C65: =VLOOKUP(B65,'AP Übersicht'!$A$8:$B$36,2,FALSE) -> #N/A | AK65: =SUM(F65:AJ65) -> 0
C66: =VLOOKUP(B66,'AP Übersicht'!$A$8:$B$36,2,FALSE) -> #N/A | AK66: =SUM(F66:AJ66) -> 0
C67: =VLOOKUP(B67,'AP Übersicht'!$A$8:$B$36,2,FALSE) -> #N/A | AK67: =SUM(F67:AJ67) -> 0
C68: =VLOOKUP(B68,'AP Übersicht'!$A$8:$B$36,2,FALSE) -> #N/A | AK68: =SUM(F68:AJ68) -> 0
C69: =VLOOKUP(B69,'AP Übersicht'!$A$8:$B$36,2,FALSE) -> #N/A | AK69: =SUM(F69:AJ69) -> 0
C70: =VLOOKUP(B70,'AP Übersicht'!$A$8:$B$36,2,FALSE) -> #N/A | AK70: =SUM(F70:AJ70) -> 0
C71: =VLOOKUP(B71,'AP Übersicht'!$A$8:$B$36,2,FALSE) -> #N/A | AK71: =SUM(F71:AJ71) -> 0
C72: =VLOOKUP(B72,'AP Übersicht'!$A$8:$B$36,2,FALSE) -> #N/A | AK72: =SUM(F72:AJ72) -> 0
C73: =VLOOKUP(B73,'AP Übersicht'!$A$8:$B$36,2,FALSE) -> #N/A | AK73: =SUM(F73:AJ73) -> 0
C74: Summe der förderbaren Stunden (2) | F74: =SUM(F60:F73) -> 0 | G74: =SUM(G60:G73) -> 0 | H74: =SUM(H60:H73) -> 0 | I74: =SUM(I60:I73) -> 0 | J74: =SUM(J60:J73) -> 0 | K74: =SUM(K60:K73) -> 0 | L74: =SUM(L60:L73) -> 0 | M74: =SUM(M60:M73) -> 0 | ... AJ74: =SUM(AJ60:AJ73) -> 0 | AK74: =SUM(AK62:AK73) -> 0
A75: 2. | C75: Nicht zuschussfähige Arbeiten | AK75: =SUM(F75:AJ75) -> 0
A76: 3. | C76: Zeitausgleich | AK76: =SUM(E76:AJ76) -> 0
C77: Urlaub (nur bezahlten Urlaub aufführen) | AK77: =SUM(F77:AJ77) -> 0
C78: Krankheit (nur bei Lohn- und Gehaltsfortzahlung) | AK78: =SUM(F78:AJ78) -> 0
C79: Sonstige bezahlte Ausfallzeiten (z. B. Feiertage) | AK79: =SUM(F79:AJ79) -> 0
AK80: =SUM(AK74:AK79) -> 0
A81: (1) Die geleisteten Bearbeitungsstunden sind für den gesamten Bewilligungszeitraum eigenhändig und zeitnah, d. h. mindestens innerhalb einer Woche zu erfassen. Die Angaben sind subventionserheblich im Sinne des § 264 Strafgesetzbuch.
Q83: Datum / Unterschrift des Mitarbeiters
A84: (2) Förderbar pro Monat sind die tatsächlich für das Projekt geleisteten Stunden, jedoch nicht mehr als arbeitsvertraglich, betrieblich oder tariflich vereinbart, maximal in Höhe von 52 (Wochen) / 12 (Monate) x Wochenarbeitszeit. Überstunden sind nicht förderbar.
Q85: Datum / Unterschrift Geschäftsführer bzw. FuE-Verantwortlicher (in öffentlichen Forschungseinrichtungen)
W88: Förderkennzeichen: | AB88: =Nav!$C$6 -> DS200424
O90: Stundennachweis
O91: Fördermodul Netzwerkprojekte des Bundesministeriums für Wirtschaft und Energie (BMWi)
A92: Zuwendungsempfänger (Firmenstempel) | O92: Der Stundennachweis verbleibt beim Zuwendungsempfänger und ist nur nach Aufforderung vorzulegen.
A93: Vorhabenthema
A94: =Nav!$C$3 -> Durchführbarkeitsstudie "BioInk"
A96: Monat | N96: Mitarbeiter(in): [Name, Vorname]
A97: =IF(AND(DAY(DATE(YEAR($A$11),3,0))=29,YEAR($A$11)<>1900),A54+29,A54+28) -> 44986 | N97: =N54 -> MA 4
A99: Die zu Lasten des Vorhabens abzurechnenden Personalstunden sind täglich eigenhändig von der betreffenden Person zu erfassen. Nur die produktiven, für das Vorhaben geleisteten Stunden sind zuwendungsfähig.
D101: technisch | E101: nicht- technisch | F101: Arbeitszeiten in Stunden je Kalendertag: | AK101: Summe Monat
A102: lfd. Nr. | F102: =A97 -> 44986 | G102: =F102+1 -> 44987 | H102: =G102+1 -> 44988 | I102: =H102+1 -> 44989 | J102: =I102+1 -> 44990 | K102: =J102+1 -> 44991 | L102: =K102+1 -> 44992 | M102: =L102+1 -> 44993 | N102: =M102+1 -> 44994 | ... AJ102: =AI102+1 -> 45016
A103: 1. | B103: AP | C103: förderbare Projektarbeiten (1)
B104: Nr. | C104: Kurzbezeichnung des Arbeitspakets
C105: =VLOOKUP(B105,'AP Übersicht'!$A$8:$B$36,2,FALSE) -> #N/A | AK105: =SUM(F105:AJ105) -> 0
C106: =VLOOKUP(B106,'AP Übersicht'!$A$8:$B$36,2,FALSE) -> #N/A | AK106: =SUM(F106:AJ106) -> 0
C107: =VLOOKUP(B107,'AP Übersicht'!$A$8:$B$36,2,FALSE) -> #N/A | AK107: =SUM(F107:AJ107) -> 0
C108: =VLOOKUP(B108,'AP Übersicht'!$A$8:$B$36,2,FALSE) -> #N/A | AK108: =SUM(F108:AJ108) -> 0
C109: =VLOOKUP(B109,'AP Übersicht'!$A$8:$B$36,2,FALSE) -> #N/A | AK109: =SUM(F109:AJ109) -> 0
C110: =VLOOKUP(B110,'AP Übersicht'!$A$8:$B$36,2,FALSE) -> #N/A | AK110: =SUM(F110:AJ110) -> 0
C111: =VLOOKUP(B111,'AP Übersicht'!$A$8:$B$36,2,FALSE) -> #N/A | AK111: =SUM(F111:AJ111) -> 0
C112: =VLOOKUP(B112,'AP Übersicht'!$A$8:$B$36,2,FALSE) -> #N/A | AK112: =SUM(F112:AJ112) -> 0
C113: =VLOOKUP(B113,'AP Übersicht'!$A$8:$B$36,2,FALSE) -> #N/A | AK113: =SUM(F113:AJ113) -> 0
C114: =VLOOKUP(B114,'AP Übersicht'!$A$8:$B$36,2,FALSE) -> #N/A | AK114: =SUM(F114:AJ114) -> 0
C115: =VLOOKUP(B115,'AP Übersicht'!$A$8:$B$36,2,FALSE) -> #N/A | AK115: =SUM(F115:AJ115) -> 0
C116: =VLOOKUP(B116,'AP Übersicht'!$A$8:$B$36,2,FALSE) -> #N/A | AK116: =SUM(F116:AJ116) -> 0
C117: Summe der förderbaren Stunden (2) | F117: =SUM(F103:F116) -> 0 | G117: =SUM(G103:G116) -> 0 | H117: =SUM(H103:H116) -> 0 | I117: =SUM(I103:I116) -> 0 | J117: =SUM(J103:J116) -> 0 | K117: =SUM(K103:K116) -> 0 | L117: =SUM(L103:L116) -> 0 | M117: =SUM(M103:M116) -> 0 | ... AJ117: =SUM(AJ103:AJ116) -> 0 | AK117: =SUM(AK105:AK116) -> 0
A118: 2. | C118: Nicht zuschussfähige Arbeiten | AK118: =SUM(F118:AJ118) -> 0
A119: 3. | C119: Zeitausgleich | AK119: =SUM(E119:AJ119) -> 0
...

Sheet MA5 J1
W2: Förderkennzeichen: | AB2: =Nav!$C$6 -> DS200424
O4: Stundennachweis
O5: Fördermodul Netzwerkprojekte des Bundesministeriums für Wirtschaft und Energie (BMWi)
A6: Zuwendungsempfänger (Firmenstempel) | O6: Der Stundennachweis verbleibt beim Zuwendungsempfänger und ist nur nach Aufforderung vorzulegen.
A7: Vorhabenthema
A8: =Nav!$C$3 -> Durchführbarkeitsstudie "BioInk"
A10: Monat | N10: Mitarbeiter(in): [Name, Vorname]
A11: =DATE(YEAR(Nav!$L$4),1,1) -> 44927 | N11: ='Planung Personal'!$B$17 -> MA 5
A13: Die zu Lasten des Vorhabens abzurechnenden Personalstunden sind täglich eigenhändig von der betreffenden Person zu erfassen. Nur die produktiven, für das Vorhaben geleisteten Stunden sind zuwendungsfähig.
D15: technisch | E15: nicht- technisch | F15: Arbeitszeiten in Stunden je Kalendertag: | AK15: Summe Monat
A16: lfd. Nr. | F16: =A11 -> 44927 | G16: =F16+1 -> 44928 | H16: =G16+1 -> 44929 | I16: =H16+1 -> 44930 | J16: =I16+1 -> 44931 | K16: =J16+1 -> 44932 | L16: =K16+1 -> 44933 | M16: =L16+1 -> 44934 | N16: =M16+1 -> 44935 | ... AJ16: =AI16+1 -> 44957
A17: 1. | B17: AP | C17: förderbare Projektarbeiten (1)
B18: Nr. | C18: Kurzbezeichnung des Arbeitspakets
C19: =VLOOKUP(B19,'AP Übersicht'!$A$8:$B$36,2,FALSE) -> #N/A | AK19: =SUM(F19:AJ19) -> 0
C20: =VLOOKUP(B20,'AP Übersicht'!$A$8:$B$36,2,FALSE) -> #N/A | AK20: =SUM(F20:AJ20) -> 0
C21: =VLOOKUP(B21,'AP Übersicht'!$A$8:$B$36,2,FALSE) -> #N/A | AK21: =SUM(F21:AJ21) -> 0
C22: =VLOOKUP(B22,'AP Übersicht'!$A$8:$B$36,2,FALSE) -> #N/A | AK22: =SUM(F22:AJ22) -> 0
C23: =VLOOKUP(B23,'AP Übersicht'!$A$8:$B$36,2,FALSE) -> #N/A | AK23: =SUM(F23:AJ23) -> 0
C24: =VLOOKUP(B24,'AP Übersicht'!$A$8:$B$36,2,FALSE) -> #N/A | AK24: =SUM(F24:AJ24) -> 0
C25: =VLOOKUP(B25,'AP Übersicht'!$A$8:$B$36,2,FALSE) -> #N/A | AK25: =SUM(F25:AJ25) -> 0
C26: =VLOOKUP(B26,'AP Übersicht'!$A$8:$B$36,2,FALSE) -> #N/A | AK26: =SUM(F26:AJ26) -> 0
C27: =VLOOKUP(B27,'AP Übersicht'!$A$8:$B$36,2,FALSE) -> #N/A | AK27: =SUM(F27:AJ27) -> 0
C28: =VLOOKUP(B28,'AP Übersicht'!$A$8:$B$36,2,FALSE) -> #N/A | AK28: =SUM(F28:AJ28) -> 0
C29: =VLOOKUP(B29,'AP Übersicht'!$A$8:$B$36,2,FALSE) -> #N/A | AK29: =SUM(F29:AJ29) -> 0
C30: =VLOOKUP(B30,'AP Übersicht'!$A$8:$B$36,2,FALSE) -> #N/A | AK30: =SUM(F30:AJ30) -> 0
C31: Summe der förderbaren Stunden (2) | F31: =SUM(F17:F30) -> 0 | G31: =SUM(G17:G30) -> 0 | H31: =SUM(H17:H30) -> 0 | I31: =SUM(I17:I30) -> 0 | J31: =SUM(J17:J30) -> 0 | K31: =SUM(K17:K30) -> 0 | L31: =SUM(L17:L30) -> 0 | M31: =SUM(M17:M30) -> 0 | ... AJ31: =SUM(AJ17:AJ30) -> 0 | AK31: =SUM(AK19:AK30) -> 0
A32: 2. | C32: Nicht zuschussfähige Arbeiten | AK32: =SUM(F32:AJ32) -> 0
A33: 3. | C33: Zeitausgleich | AK33: =SUM(E33:AJ33) -> 0
C34: Urlaub (nur bezahlten Urlaub aufführen) | AK34: =SUM(F34:AJ34) -> 0
C35: Krankheit (nur bei Lohn- und Gehaltsfortzahlung) | AK35: =SUM(F35:AJ35) -> 0
C36: Sonstige bezahlte Ausfallzeiten (z. B. Feiertage) | AK36: =SUM(F36:AJ36) -> 0
AK37: =SUM(AK31:AK36) -> 0
A38: (1) Die geleisteten Bearbeitungsstunden sind für den gesamten Bewilligungszeitraum eigenhändig und zeitnah, d. h. mindestens innerhalb einer Woche zu erfassen. Die Angaben sind subventionserheblich im Sinne des § 264 Strafgesetzbuch.
Q40: Datum / Unterschrift des Mitarbeiters
A41: (2) Förderbar pro Monat sind die tatsächlich für das Projekt geleisteten Stunden, jedoch nicht mehr als arbeitsvertraglich, betrieblich oder tariflich vereinbart, maximal in Höhe von 52 (Wochen) / 12 (Monate) x Wochenarbeitszeit. Überstunden sind nicht förderbar.
Q42: Datum / Unterschrift Geschäftsführer bzw. FuE-Verantwortlicher (in öffentlichen Forschungseinrichtungen)
W45: Förderkennzeichen: | AB45: =Nav!$C$6 -> DS200424
O47: Stundennachweis
O48: Fördermodul Netzwerkprojekte des Bundesministeriums für Wirtschaft und Energie (BMWi)
A49: Zuwendungsempfänger (Firmenstempel) | O49: Der Stundennachweis verbleibt beim Zuwendungsempfänger und ist nur nach Aufforderung vorzulegen.
A50: Vorhabenthema
A51: =Nav!$C$3 -> Durchführbarkeitsstudie "BioInk"
A53: Monat | N53: Mitarbeiter(in): [Name, Vorname]
A54: =A11+31 -> 44958 | N54: =N11 -> MA 5
A56: Die zu Lasten des Vorhabens abzurechnenden Personalstunden sind täglich eigenhändig von der betreffenden Person zu erfassen. Nur die produktiven, für das Vorhaben geleisteten Stunden sind zuwendungsfähig.
D58: technisch | E58: nicht- technisch | F58: Arbeitszeiten in Stunden je Kalendertag: | AK58: Summe Monat
A59: lfd. Nr. | F59: =A54 -> 44958 | G59: =F59+1 -> 44959 | H59: =G59+1 -> 44960 | I59: =H59+1 -> 44961 | J59: =I59+1 -> 44962 | K59: =J59+1 -> 44963 | L59: =K59+1 -> 44964 | M59: =L59+1 -> 44965 | N59: =M59+1 -> 44966 | ... AG59: =AF59+1 -> 44985 | AH59: =IF(AND(DAY(DATE(YEAR($A$11),3,0))=29,YEAR($A$11)<>1900),29,"")
A60: 1. | B60: AP | C60: förderbare Projektarbeiten (1)
B61: Nr. | C61: Kurzbezeichnung des Arbeitspakets
C62: =VLOOKUP(B62,'AP Übersicht'!$A$8:$B$36,2,FALSE) -> #N/A | AK62: =SUM(F62:AJ62) -> 0
C63: =VLOOKUP(B63,'AP Übersicht'!$A$8:$B$36,2,FALSE) -> #N/A | AK63: =SUM(F63:AJ63) -> 0
C64: =VLOOKUP(B64,'AP Übersicht'!$A$8:$B$36,2,FALSE) -> #N/A | AK64: =SUM(F64:AJ64) -> 0
C65: =VLOOKUP(B65,'AP Übersicht'!$A$8:$B$36,2,FALSE) -> #N/A | AK65: =SUM(F65:AJ65) -> 0
C66: =VLOOKUP(B66,'AP Übersicht'!$A$8:$B$36,2,FALSE) -> #N/A | AK66: =SUM(F66:AJ66) -> 0
C67: =VLOOKUP(B67,'AP Übersicht'!$A$8:$B$36,2,FALSE) -> #N/A | AK67: =SUM(F67:AJ67) -> 0
C68: =VLOOKUP(B68,'AP Übersicht'!$A$8:$B$36,2,FALSE) -> #N/A | AK68: =SUM(F68:AJ68) -> 0
C69: =VLOOKUP(B69,'AP Übersicht'!$A$8:$B$36,2,FALSE) -> #N/A | AK69: =SUM(F69:AJ69) -> 0
C70: =VLOOKUP(B70,'AP Übersicht'!$A$8:$B$36,2,FALSE) -> #N/A | AK70: =SUM(F70:AJ70) -> 0
C71: =VLOOKUP(B71,'AP Übersicht'!$A$8:$B$36,2,FALSE) -> #N/A | AK71: =SUM(F71:AJ71) -> 0
C72: =VLOOKUP(B72,'AP Übersicht'!$A$8:$B$36,2,FALSE) -> #N/A | AK72: =SUM(F72:AJ72) -> 0
C73: =VLOOKUP(B73,'AP Übersicht'!$A$8:$B$36,2,FALSE) -> #N/A | AK73: =SUM(F73:AJ73) -> 0
C74: Summe der förderbaren Stunden (2) | F74: =SUM(F60:F73) -> 0 | G74: =SUM(G60:G73) -> 0 | H74: =SUM(H60:H73) -> 0 | I74: =SUM(I60:I73) -> 0 | J74: =SUM(J60:J73) -> 0 | K74: =SUM(K60:K73) -> 0 | L74: =SUM(L60:L73) -> 0 | M74: =SUM(M60:M73) -> 0 | ... AJ74: =SUM(AJ60:AJ73) -> 0 | AK74: =SUM(AK62:AK73) -> 0
A75: 2. | C75: Nicht zuschussfähige Arbeiten | AK75: =SUM(F75:AJ75) -> 0
A76: 3. | C76: Zeitausgleich | AK76: =SUM(E76:AJ76) -> 0
C77: Urlaub (nur bezahlten Urlaub aufführen) | AK77: =SUM(F77:AJ77) -> 0
C78: Krankheit (nur bei Lohn- und Gehaltsfortzahlung) | AK78: =SUM(F78:AJ78) -> 0
C79: Sonstige bezahlte Ausfallzeiten (z. B. Feiertage) | AK79: =SUM(F79:AJ79) -> 0
AK80: =SUM(AK74:AK79) -> 0
A81: (1) Die geleisteten Bearbeitungsstunden sind für den gesamten Bewilligungszeitraum eigenhändig und zeitnah, d. h. mindestens innerhalb einer Woche zu erfassen. Die Angaben sind subventionserheblich im Sinne des § 264 Strafgesetzbuch.
Q83: Datum / Unterschrift des Mitarbeiters
A84: (2) Förderbar pro Monat sind die tatsächlich für das Projekt geleisteten Stunden, jedoch nicht mehr als arbeitsvertraglich, betrieblich oder tariflich vereinbart, maximal in Höhe von 52 (Wochen) / 12 (Monate) x Wochenarbeitszeit. Überstunden sind nicht förderbar.
Q85: Datum / Unterschrift Geschäftsführer bzw. FuE-Verantwortlicher (in öffentlichen Forschungseinrichtungen)
W88: Förderkennzeichen: | AB88: =Nav!$C$6 -> DS200424
O90: Stundennachweis
O91: Fördermodul Netzwerkprojekte des Bundesministeriums für Wirtschaft und Energie (BMWi)
A92: Zuwendungsempfänger (Firmenstempel) | O92: Der Stundennachweis verbleibt beim Zuwendungsempfänger und ist nur nach Aufforderung vorzulegen.
A93: Vorhabenthema
A94: =Nav!$C$3 -> Durchführbarkeitsstudie "BioInk"
A96: Monat | N96: Mitarbeiter(in): [Name, Vorname]
A97: =IF(AND(DAY(DATE(YEAR($A$11),3,0))=29,YEAR($A$11)<>1900),A54+29,A54+28) -> 44986 | N97: =N54 -> MA 5
A99: Die zu Lasten des Vorhabens abzurechnenden Personalstunden sind täglich eigenhändig von der betreffenden Person zu erfassen. Nur die produktiven, für das Vorhaben geleisteten Stunden sind zuwendungsfähig.
D101: technisch | E101: nicht- technisch | F101: Arbeitszeiten in Stunden je Kalendertag: | AK101: Summe Monat
A102: lfd. Nr. | F102: =A97 -> 44986 | G102: =F102+1 -> 44987 | H102: =G102+1 -> 44988 | I102: =H102+1 -> 44989 | J102: =I102+1 -> 44990 | K102: =J102+1 -> 44991 | L102: =K102+1 -> 44992 | M102: =L102+1 -> 44993 | N102: =M102+1 -> 44994 | ... AJ102: =AI102+1 -> 45016
A103: 1. | B103: AP | C103: förderbare Projektarbeiten (1)
B104: Nr. | C104: Kurzbezeichnung des Arbeitspakets
C105: =VLOOKUP(B105,'AP Übersicht'!$A$8:$B$36,2,FALSE) -> #N/A | AK105: =SUM(F105:AJ105) -> 0
C106: =VLOOKUP(B106,'AP Übersicht'!$A$8:$B$36,2,FALSE) -> #N/A | AK106: =SUM(F106:AJ106) -> 0
C107: =VLOOKUP(B107,'AP Übersicht'!$A$8:$B$36,2,FALSE) -> #N/A | AK107: =SUM(F107:AJ107) -> 0
C108: =VLOOKUP(B108,'AP Übersicht'!$A$8:$B$36,2,FALSE) -> #N/A | AK108: =SUM(F108:AJ108) -> 0
C109: =VLOOKUP(B109,'AP Übersicht'!$A$8:$B$36,2,FALSE) -> #N/A | AK109: =SUM(F109:AJ109) -> 0
C110: =VLOOKUP(B110,'AP Übersicht'!$A$8:$B$36,2,FALSE) -> #N/A | AK110: =SUM(F110:AJ110) -> 0
C111: =VLOOKUP(B111,'AP Übersicht'!$A$8:$B$36,2,FALSE) -> #N/A | AK111: =SUM(F111:AJ111) -> 0
C112: =VLOOKUP(B112,'AP Übersicht'!$A$8:$B$36,2,FALSE) -> #N/A | AK112: =SUM(F112:AJ112) -> 0
C113: =VLOOKUP(B113,'AP Übersicht'!$A$8:$B$36,2,FALSE) -> #N/A | AK113: =SUM(F113:AJ113) -> 0
C114: =VLOOKUP(B114,'AP Übersicht'!$A$8:$B$36,2,FALSE) -> #N/A | AK114: =SUM(F114:AJ114) -> 0
C115: =VLOOKUP(B115,'AP Übersicht'!$A$8:$B$36,2,FALSE) -> #N/A | AK115: =SUM(F115:AJ115) -> 0
C116: =VLOOKUP(B116,'AP Übersicht'!$A$8:$B$36,2,FALSE) -> #N/A | AK116: =SUM(F116:AJ116) -> 0
C117: Summe der förderbaren Stunden (2) | F117: =SUM(F103:F116) -> 0 | G117: =SUM(G103:G116) -> 0 | H117: =SUM(H103:H116) -> 0 | I117: =SUM(I103:I116) -> 0 | J117: =SUM(J103:J116) -> 0 | K117: =SUM(K103:K116) -> 0 | L117: =SUM(L103:L116) -> 0 | M117: =SUM(M103:M116) -> 0 | ... AJ117: =SUM(AJ103:AJ116) -> 0 | AK117: =SUM(AK105:AK116) -> 0
A118: 2. | C118: Nicht zuschussfähige Arbeiten | AK118: =SUM(F118:AJ118) -> 0
A119: 3. | C119: Zeitausgleich | AK119: =SUM(E119:AJ119) -> 0
...

Sheet Ermittl.-Stunden J1
A1: Aufstellung der monatlich geleisteten Arbeitsstunden der einzelnen Mitarbeiter | Q1: FKZ: | R1: =Nav!$C$6 -> DS200424
A2: (für die Berechnung der Stunden in den einzelnen Monaten siehe Muster "Stundennachweis") | Q2: Jahr: | R2: =Nav!H16 -> 45047
T4: max. h/Monat
Q5: Wochenarbeitsstunden: 1) | R5: ='Planung Personal'!$U$9 -> 40 | S5: ='Planung Personal'!$V$9 -> 2080 | T5: =S5/12 -> 173.33333 | Z5: PK
A6: ='Planung Personal'!$B$9 -> Tippl, Mario | C6: Jan | D6: Feb | E6: Mrz | F6: Apr | G6: Mai | H6: Jun | I6: Jul | J6: Aug | K6: Sept | L6: Okt | M6: Nov | N6: Dez | O6: ∑ | Q6: Ermittlung des Jahresstundensatzes | V6: PM | Z6: Mai-Jul | AA6: Aug-Sep | AB6: Okt | AC6: Nov-Dez | AF6: ZA
A7: Vorhabenbezogen | B7: technisch | C7: ='Tippl M. J1'!$AK31 -> 0 | D7: ='Tippl M. J1'!$AK75 -> 0 | E7: ='Tippl M. J1'!$AK119 -> 0 | F7: ='Tippl M. J1'!$AK163 -> 0 | G7: ='Tippl M. J1'!$AK207 -> 0 | H7: ='Tippl M. J1'!$AK251 -> 86.666 | I7: ='Tippl M. J1'!$AK295 -> 87 | J7: ='Tippl M. J1'!$AK339 -> 91 | K7: ='Tippl M. J1'!$AK383 -> 126 | L7: ='Tippl M. J1'!$AK427 -> 88 | M7: ='Tippl M. J1'!$AK471 -> 0 | N7: ='Tippl M. J1'!$AK515 -> 0 | O7: =SUM(C7:N7) -> 478.666 | U7: technisch | V7: =O7/T5 -> 2.7615346 | W7: =SUM(V7:V8) -> 3.7230923 | X7: =SUM(O7:O8) -> 645.336 | Z7: =SUM(G7:I7)*S$11 -> 10018.792 | AA7: =SUM(J7:K7)*S$11 -> 12518.73 | AB7: =SUM(L7)*S$11 -> 5076.72 | AC7: =SUM(M7:N7)*S$11 -> 0 | AD7: 0.2842 | AE7: 0.7 | AF7: =SUM(Z7:AC7)*(1+AD7)*AE7 -> 24823.546
B8: nicht-techn. | C8: ='Tippl M. J1'!$AK32 -> 0 | D8: ='Tippl M. J1'!$AK76 -> 0 | E8: ='Tippl M. J1'!$AK120 -> 0 | F8: ='Tippl M. J1'!$AK164 -> 0 | G8: ='Tippl M. J1'!$AK208 -> 86.67 | H8: ='Tippl M. J1'!$AK252 -> 0 | I8: ='Tippl M. J1'!$AK296 -> 0 | J8: ='Tippl M. J1'!$AK340 -> 0 | K8: ='Tippl M. J1'!$AK384 -> 10 | L8: ='Tippl M. J1'!$AK428 -> 20 | M8: ='Tippl M. J1'!$AK472 -> 50 | N8: ='Tippl M. J1'!$AK516 -> 0 | O8: =SUM(C8:N8) -> 166.67 | U8: nicht technisch | V8: =O8/T5 -> 0.96155769 | Z8: =SUM(G8:I8)*S$11 -> 4999.9923 | AA8: =SUM(J8:K8)*S$11 -> 576.9 | AB8: =SUM(L8)*S$11 -> 1153.8 | AC8: =SUM(M8:N8)*S$11 -> 2884.5 | AD8: 0.2988 | AE8: 0.7 | AF8: =SUM(Z8:AC8)*(1+AD8)*AE8 -> 8741.7482
A9: Sonstige | C9: ='Tippl M. J1'!$AK$33 -> 0 | D9: ='Tippl M. J1'!$AK$77 -> 0 | E9: ='Tippl M. J1'!$AK$121 -> 0 | F9: ='Tippl M. J1'!$AK$165 -> 0 | G9: ='Tippl M. J1'!$AK$209 -> 65.33 | H9: ='Tippl M. J1'!$AK$253 -> 73.33 | I9: ='Tippl M. J1'!$AK$297 -> 35 | J9: ='Tippl M. J1'!$AK$341 -> 13 | K9: ='Tippl M. J1'!$AK$385 -> 32 | L9: ='Tippl M. J1'!$AK$429 -> 52 | M9: ='Tippl M. J1'!$AK$473 -> 102 | N9: ='Tippl M. J1'!$AK$517 -> 65 | O9: =SUM(C9:N9) -> 437.66 | Q9: Bruttojahres- | R9: Jahresarbeits- | S9: Jahresstd.- | AF9: =SUM(AF7:AF8) -> 33565.295
N10: Produktive Gesamtstunden: | O10: =SUM(O7:O9) -> 1082.996 | Q10: lohn/ -gehalt 1) | R10: stunden | S10: satz
A11: Fehlzeiten | C11: =SUM('Tippl M. J1'!$AK$35:$AK$37) -> 0 | D11: =SUM('Tippl M. J1'!$AK$79:$AK$81) -> 0 | E11: =SUM('Tippl M. J1'!$AK$123:$AK$125) -> 0 | F11: =SUM('Tippl M. J1'!$AK$167:$AK$169) -> 0 | G11: =SUM('Tippl M. J1'!$AK$211:$AK$213) -> 32 | H11: =SUM('Tippl M. J1'!$AK$255:$AK$257) -> 16 | I11: =SUM('Tippl M. J1'!$AK$299:$AK$301) -> 0 | J11: =SUM('Tippl M. J1'!$AK$343:$AK$345) -> 80 | K11: =SUM('Tippl M. J1'!$AK$387:$AK$389) -> 0 | L11: =SUM('Tippl M. J1'!$AK$430:$AK$432) -> 8 | M11: =SUM('Tippl M. J1'!$AK$475:$AK$477) -> 24 | N11: =SUM('Tippl M. J1'!$AK$519:$AK$521) -> 40 | O11: =SUM(C11:N11) -> 200 | Q11: ='Planung Personal'!$T$9 -> 120000 | R11: ='Planung Personal'!$V$9 -> 2080 | S11: ='Planung Personal'!$W$9 -> 57.69
A12: Zeitausgleich | C12: ='Tippl M. J1'!AK$34 -> 0 | D12: ='Tippl M. J1'!$AK$78 -> 0 | E12: ='Tippl M. J1'!$AK$122 -> 0 | F12: ='Tippl M. J1'!$AK$166 -> 0 | G12: ='Tippl M. J1'!$AK$210 -> 0 | H12: ='Tippl M. J1'!$AK$254 -> 0 | I12: ='Tippl M. J1'!$AK$298 -> 0 | J12: ='Tippl M. J1'!$AK$342 -> 0 | K12: ='Tippl M. J1'!$AK$386 -> 0 | L12: ='Tippl M. J1'!$AK$429 -> 52 | M12: ='Tippl M. J1'!$AK$474 -> 0 | N12: ='Tippl M. J1'!$AK$518 -> 0 | O12: =SUM(C12:N12) -> 52
A13: Summe | C13: =SUM(C7:C12) -> 0 | D13: =SUM(D7:D12) -> 0 | E13: =SUM(E7:E12) -> 0 | F13: =SUM(F7:F12) -> 0 | G13: =SUM(G7:G12) -> 184 | H13: =SUM(H7:H12) -> 175.996 | I13: =SUM(I7:I12) -> 122 | J13: =SUM(J7:J12) -> 184 | ... N13: =SUM(N7:N12) -> 105 | O13: =SUM(O10:O12) -> 1334.996
Q15: Wochenarbeitsstunden: 1) | R15: ='Planung Personal'!$U$11 -> 40 | S15: ='Planung Personal'!$V$11 -> 2080 | T15: =S15/12 -> 173.33333
A16: ='Planung Personal'!$B$11 -> Socha, Pawel | C16: Jan | D16: Feb | E16: Mrz | F16: Apr | G16: Mai | H16: Jun | I16: Jul | J16: Aug | K16: Sept | L16: Okt | M16: Nov | N16: Dez | O16: ∑ | Q16: Ermittlung des Jahresstundensatzes | V16: PM | Z16: PK | AF16: ZA
A17: Vorhabenbezogen | B17: technisch | C17: ='Socha J1'!$AK31 -> 0 | D17: ='Socha J1'!$AK75 -> 0 | E17: ='Socha J1'!$AK119 -> 0 | F17: ='Socha J1'!$AK163 -> 0 | G17: ='Socha J1'!$AK207 -> 0 | H17: ='Socha J1'!$AK251 -> 158 | I17: ='Socha J1'!$AK295 -> 148 | J17: ='Socha J1'!$AK339 -> 92 | K17: ='Socha J1'!$AK383 -> 40 | L17: ='Socha J1'!$AK427 -> 20 | M17: ='Socha J1'!$AK471 -> 0 | N17: ='Socha J1'!$AK515 -> 0 | O17: =SUM(C17:N17) -> 458 | U17: technisch | V17: =O17/T15 -> 2.6423077 | W17: =SUM(V17:V18) -> 3.1855962 | X17: =SUM(O17:O18) -> 552.17 | Z17: =SUM(G17:I17)*S$21 -> 5694.66 | AA17: =SUM(J17:K17)*S$21 -> 2456.52 | AB17: =SUM(L17)*S$21 -> 372.2 | AC17: =SUM(M17:N17)*S$11 -> 0 | AD17: 0.2842 | AE17: 0.7 | AF17: =SUM(Z17:AC17)*(1+AD17)*AE17 -> 7662.0072
B18: nicht-techn. | C18: ='Socha J1'!$AK32 -> 0 | D18: ='Socha J1'!$AK76 -> 0 | E18: ='Socha J1'!$AK120 -> 0 | F18: ='Socha J1'!$AK164 -> 0 | G18: ='Socha J1'!$AK208 -> 86.67 | H18: ='Socha J1'!$AK252 -> 0 | I18: ='Socha J1'!$AK296 -> 0 | J18: ='Socha J1'!$AK340 -> 0 | K18: ='Socha J1'!$AK384 -> 0 | L18: ='Socha J1'!$AK428 -> 0 | M18: ='Socha J1'!$AK472 -> 7.5 | N18: ='Socha J1'!$AK516 -> 0 | O18: =SUM(C18:N18) -> 94.17 | U18: nicht technisch | V18: =O18/T15 -> 0.54328846 | Z18: =SUM(G18:I18)*S$21 -> 1612.9287 | AA18: =SUM(J18:K18)*S$21 -> 0 | AB18: =SUM(L18)*S$21 -> 0 | AC18: =SUM(M18:N18)*S$11 -> 432.675 | AD18: 0.2988 | AE18: 0.7 | AF18: =SUM(Z18:AC18)*(1+AD18)*AE18 -> 1859.7811
A19: Sonstige | C19: ='Socha J1'!$AK$33 -> 0 | D19: ='Socha J1'!$AK$77 -> 0 | E19: ='Socha J1'!$AK$121 -> 0 | F19: ='Socha J1'!$AK$165 -> 0 | G19: ='Socha J1'!$AK$209 -> 57.33 | H19: ='Socha J1'!$AK$253 -> 2 | I19: ='Socha J1'!$AK$297 -> 20 | J19: ='Socha J1'!$AK$341 -> 92 | K19: ='Socha J1'!$AK$385 -> 120 | L19: ='Socha J1'!$AK$429 -> 116 | M19: ='Socha J1'!$AK$473 -> 104.5 | N19: ='Socha J1'!$AK$517 -> 0 | O19: =SUM(C19:N19) -> 511.83 | Q19: Bruttojahres- | R19: Jahresarbeits- | S19: Jahresstd.- | AF19: =SUM(AF17:AF18) -> 9521.7883
N20: Produktive Gesamtstunden: | O20: =SUM(O17:O19) -> 1064 | Q20: lohn/ -gehalt | R20: stunden | S20: satz
A21: Fehlzeiten | C21: =SUM('Socha J1'!$AK$35:$AK$37) -> 0 | D21: =SUM('Socha J1'!$AK$79:$AK$81) -> 0 | E21: =SUM('Socha J1'!$AK$123:$AK$125) -> 0 | F21: =SUM('Socha J1'!$AK$167:$AK$169) -> 0 | G21: =SUM('Socha J1'!$AK$211:$AK$213) -> 32 | H21: =SUM('Socha J1'!$AK$255:$AK$257) -> 16 | I21: =SUM('Socha J1'!$AK$299:$AK$301) -> 0 | J21: =SUM('Socha J1'!$AK$343:$AK$345) -> 0 | K21: =SUM('Socha J1'!$AK$387:$AK$389) -> 8 | L21: =SUM('Socha J1'!$AK$431:$AK$433) -> 40 | M21: =SUM('Socha J1'!$AK$475:$AK$477) -> 64 | N21: =SUM('Socha J1'!$AK$519:$AK$521) -> 0 | O21: =SUM(C21:N21) -> 160 | Q21: ='Planung Personal'!$T$11 -> 38700 | R21: ='Planung Personal'!$V$11 -> 2080 | S21: ='Planung Personal'!W11 -> 18.61
A22: Zeitausgleich | C22: ='Socha J1'!AK$34 -> 0 | D22: ='Socha J1'!$AK$78 -> 0 | E22: ='Socha J1'!$AK$122 -> 0 | F22: ='Socha J1'!$AK$166 -> 0 | G22: ='Socha J1'!$AK$210 -> 0 | H22: ='Socha J1'!$AK$254 -> 0 | I22: ='Socha J1'!$AK$298 -> 0 | J22: ='Socha J1'!$AK$342 -> 0 | K22: ='Socha J1'!$AK$386 -> 0 | L22: ='Socha J1'!$AK$430 -> 0 | M22: ='Socha J1'!$AK$474 -> 0 | N22: ='Socha J1'!$AK$518 -> 0 | O22: =SUM(C22:N22) -> 0
A23: Summe | C23: =SUM(C17:C22) -> 0 | D23: =SUM(D17:D22) -> 0 | E23: =SUM(E17:E22) -> 0 | F23: =SUM(F17:F22) -> 0 | G23: =SUM(G17:G22) -> 176 | H23: =SUM(H17:H22) -> 176 | I23: =SUM(I17:I22) -> 168 | J23: =SUM(J17:J22) -> 184 | ... N23: =SUM(N17:N22) -> 0 | O23: =SUM(O20:O22) -> 1224
Q25: Wochenarbeitsstunden: 1) | R25: ='Planung Personal'!$U$13 -> 20 | S25: ='Planung Personal'!$V$13 -> 1040 | T25: =S25/12 -> 86.666667
A26: ='Planung Personal'!$B$13 -> Tippl, Karen | C26: Jan | D26: Feb | E26: Mrz | F26: Apr | G26: Mai | H26: Jun | I26: Jul | J26: Aug | K26: Sept | L26: Okt | M26: Nov | N26: Dez | O26: ∑ | Q26: Ermittlung des Jahresstundensatzes | V26: PM | Z26: PK | AF26: ZA
A27: Vorhabenbezogen | B27: technisch | C27: ='Tippl K. J1'!$AK31 -> 0 | D27: ='Tippl K. J1'!$AK75 -> 0 | E27: ='Tippl K. J1'!$AK119 -> 0 | F27: ='Tippl K. J1'!$AK163 -> 0 | G27: ='Tippl K. J1'!$AK207 -> 0 | H27: ='Tippl K. J1'!$AK251 -> 53.33 | I27: ='Tippl K. J1'!$AK295 -> 72 | J27: ='Tippl K. J1'!$AK339 -> 48 | K27: ='Tippl K. J1'!$AK383 -> 80 | L27: ='Tippl K. J1'!$AK427 -> 20 | M27: ='Tippl K. J1'!$AK471 -> 0 | N27: ='Tippl K. J1'!$AK515 -> 0 | O27: =SUM(C27:N27) -> 273.33 | U27: technisch | V27: =O27/T25 -> 3.1538077 | W27: =SUM(V27:V28) -> 4.1538462 | X27: =SUM(O27:O28) -> 360 | Z27: =SUM(G27:I27)*S$31 -> 4302.5789 | AA27: =SUM(J27:K27)*S$31 -> 4394.24 | AB27: =SUM(L27)*S$31 -> 686.6 | AC27: =SUM(M27:N27)*S$11 -> 0 | AD27: 0.2842 | AE27: 0.7 | AF27: =SUM(Z27:AC27)*(1+AD27)*AE27 -> 8435.1306
B28: nicht-techn. | C28: ='Tippl K. J1'!$AK32 -> 0 | D28: ='Tippl K. J1'!$AK76 -> 0 | E28: ='Tippl K. J1'!$AK120 -> 0 | F28: ='Tippl K. J1'!$AK164 -> 0 | G28: ='Tippl K. J1'!$AK208 -> 64 | H28: ='Tippl K. J1'!$AK252 -> 22.67 | I28: ='Tippl K. J1'!$AK296 -> 0 | J28: ='Tippl K. J1'!$AK340 -> 0 | K28: ='Tippl K. J1'!AK384 -> 0 | L28: ='Tippl K. J1'!$AK428 -> 0 | M28: ='Tippl K. J1'!$AK472 -> 0 | N28: ='Tippl K. J1'!$AK516 -> 0 | O28: =SUM(C28:N28) -> 86.67 | U28: nicht technisch | V28: =O28/T25 -> 1.0000385 | Z28: =SUM(G28:I28)*S$31 -> 2975.3811 | AA28: =SUM(J28:K28)*S$31 -> 0 | AB28: =SUM(L28)*S$31 -> 0 | AC28: =SUM(M28:N28)*S$11 -> 0 | AD28: 0.2988 | AE28: 0.7 | AF28: =SUM(Z28:AC28)*(1+AD28)*AE28 -> 2705.0975
A29: Sonstige | C29: ='Tippl K. J1'!$AK$33 -> 0 | D29: ='Tippl K. J1'!$AK$77 -> 0 | E29: ='Tippl K. J1'!$AK$121 -> 0 | F29: ='Tippl K. J1'!$AK$165 -> 0 | G29: ='Tippl K. J1'!$AK$209 -> 12 | H29: ='Tippl K. J1'!$AK$253 -> 12 | I29: ='Tippl K. J1'!$AK$297 -> 14 | J29: ='Tippl K. J1'!$AK$341 -> 0 | K29: ='Tippl K. J1'!$AK$385 -> 0 | L29: ='Tippl K. J1'!$AK$429 -> 60 | M29: ='Tippl K. J1'!$AK$473 -> 0 | N29: ='Tippl K. J1'!$AK$517 -> 0 | O29: =SUM(C29:N29) -> 98 | Q29: Bruttojahres- | R29: Jahresarbeits- | S29: Jahresstd.- | AF29: =SUM(AF27:AF28) -> 11140.228
N30: Produktive Gesamtstunden: | O30: =SUM(O27:O29) -> 458 | Q30: lohn/ -gehalt | R30: stunden | S30: satz | V30: =SUM(V7:V28) -> 11.062535
A31: Fehlzeiten | C31: =SUM('Tippl K. J1'!$AK$35:$AK$37) -> 0 | D31: =SUM('Tippl K. J1'!$AK$79:$AK$81) -> 0 | E31: =SUM('Tippl K. J1'!$AK$123:$AK$125) -> 0 | F31: =SUM('Tippl K. J1'!$AK$167:$AK$169) -> 0 | G31: =SUM('Tippl K. J1'!$AK$211:$AK$213) -> 16 | H31: =SUM('Tippl K. J1'!$AK$255:$AK$257) -> 8 | I31: =SUM('Tippl K. J1'!$AK$299:$AK$301) -> 0 | J31: =SUM('Tippl K. J1'!$AK$343:$AK$345) -> 40 | K31: =SUM('Tippl K. J1'!$AK$387:$AK$389) -> 4 | L31: =SUM('Tippl K. J1'!$AK$431:$AK$433) -> 8 | M31: =SUM('Tippl K. J1'!$AK$475:$AK$477) -> 0 | N31: =SUM('Tippl K. J1'!$AK$519:$AK$521) -> 0 | O31: =SUM(C31:N31) -> 76 | Q31: ='Planung Personal'!$T$13 -> 35700 | R31: ='Planung Personal'!$V$13 -> 1040 | S31: ='Planung Personal'!$W$13 -> 34.33 | Z31: =(Z7+Z17+Z27)*(1+AD7)*AE7 -> 17993.21 | AF31: =AF9+AF19+AF29 -> 54227.311
A32: Zeitausgleich | C32: ='Tippl K. J1'!AK$34 -> 0 | D32: ='Tippl K. J1'!$AK$78 -> 0 | E32: ='Tippl K. J1'!$AK$122 -> 0 | F32: ='Tippl K. J1'!$AK$166 -> 0 | G32: ='Tippl K. J1'!$AK$210 -> 0 | H32: ='Tippl K. J1'!$AK$254 -> 0 | I32: ='Tippl K. J1'!$AK$298 -> 0 | J32: ='Tippl K. J1'!$AK$342 -> 0 | K32: ='Tippl K. J1'!$AK$386 -> 0 | L32: ='Tippl K. J1'!$AK$430 -> 0 | M32: ='Tippl K. J1'!$AK$474 -> 0 | N32: ='Tippl K. J1'!$AK$518 -> 0 | O32: =SUM(C32:N32) -> 0
A33: Summe | C33: =SUM(C27:C32) -> 0 | D33: =SUM(D27:D32) -> 0 | E33: =SUM(E27:E32) -> 0 | F33: =SUM(F27:F32) -> 0 | G33: =SUM(G27:G32) -> 92 | H33: =SUM(H27:H32) -> 96 | I33: =SUM(I27:I32) -> 86 | J33: =SUM(J27:J32) -> 88 | ... N33: =SUM(N27:N32) -> 0 | O33: =SUM(O30:O32) -> 534
Q35: Wochenarbeitsstunden: 1) | R35: ='Planung Personal'!$U$15 -> 0 | S35: ='Planung Personal'!$V$15 -> 0 | T35: =S35/12 -> 0
A36: ='Planung Personal'!$B$15 -> MA 4 | C36: Jan | D36: Feb | E36: Mrz | F36: Apr | G36: Mai | H36: Jun | I36: Jul | J36: Aug | K36: Sep | L36: Okt | M36: Nov | N36: Dez | O36: ∑ | Q36: Ermittlung des Jahresstundensatzes
A37: Vorhabenbezogen | B37: technisch | C37: ='MA4 J1'!$AK$31 -> 0 | D37: ='MA4 J1'!$AK$74 -> 0 | E37: ='MA4 J1'!$AK$117 -> 0 | F37: ='MA4 J1'!$AK$160 -> 0 | G37: ='MA4 J1'!$AK$203 -> 0 | H37: ='MA4 J1'!$AK$246 -> 0 | I37: ='MA4 J1'!$AK$289 -> 0 | J37: ='MA4 J1'!$AK$332 -> 0 | K37: ='MA4 J1'!$AK$376 -> 0 | L37: ='MA4 J1'!$AK$418 -> 0 | M37: ='MA4 J1'!$AK$461 -> 0 | N37: ='MA4 J1'!$AK$504 -> 0 | O37: =SUM(C37:N37) -> 0
B38: nicht-techn.
A39: Sonstige | C39: ='MA4 J1'!$AK$32 -> 0 | D39: ='MA4 J1'!$AK$75 -> 0 | E39: ='MA4 J1'!$AK$118 -> 0 | F39: ='MA4 J1'!$AK$161 -> 0 | G39: ='MA4 J1'!$AK$204 -> 0 | H39: ='MA4 J1'!$AK$247 -> 0 | I39: ='MA4 J1'!$AK$290 -> 0 | J39: ='MA4 J1'!$AK$333 -> 0 | K39: ='MA4 J1'!$AK$377 -> 0 | L39: ='MA4 J1'!$AK$419 -> 0 | M39: ='MA4 J1'!$AK$462 -> 0 | N39: ='MA4 J1'!$AK$505 -> 0 | O39: =SUM(C39:N39) -> 0 | Q39: Bruttojahres- | R39: Jahresarbeits- | S39: Jahresstd.-
N40: Produktive Gesamtstunden: | O40: =SUM(O37:O39) -> 0 | Q40: lohn/ -gehalt | R40: stunden | S40: satz
A41: Fehlzeiten | C41: =SUM('MA4 J1'!$AK$34:$AK$36) -> 0 | D41: =SUM('MA4 J1'!$AK$77:$AK$79) -> 0 | E41: =SUM('MA4 J1'!$AK$120:$AK$122) -> 0 | F41: =SUM('MA4 J1'!$AK$163:$AK$165) -> 0 | G41: =SUM('MA4 J1'!$AK$206:$AK$208) -> 0 | H41: =SUM('MA4 J1'!$AK$249:$AK$251) -> 0 | I41: =SUM('MA4 J1'!$AK$292:$AK$294) -> 0 | J41: =SUM('MA4 J1'!$AK$335:$AK$337) -> 0 | K41: =SUM('MA4 J1'!$AK$379:$AK$381) -> 0 | L41: =SUM('MA4 J1'!$AK$421:$AK$423) -> 0 | M41: =SUM('MA4 J1'!$AK$464:$AK$466) -> 0 | N41: =SUM('MA4 J1'!$AK$507:$AK$509) -> 0 | O41: =SUM(C41:N41) -> 0 | Q41: ='Planung Personal'!$T$15 -> 0 | R41: ='Planung Personal'!$V$15 -> 0 | S41: ='Planung Personal'!$W$15 -> 0,00 €
A42: Zeitausgleich | C42: ='MA4 J1'!AK$33 -> 0 | D42: ='MA4 J1'!$AK$76 -> 0 | E42: ='MA4 J1'!$AK$119 -> 0 | F42: ='MA4 J1'!$AK$162 -> 0 | G42: ='MA4 J1'!$AK$205 -> 0 | H42: ='MA4 J1'!$AK$248 -> 0 | I42: ='MA4 J1'!$AK$291 -> 0 | J42: ='MA4 J1'!$AK$334 -> 0 | K42: ='MA4 J1'!$AK$378 -> 0 | L42: ='MA4 J1'!$AK$420 -> 0 | M42: ='MA4 J1'!$AK$463 -> 0 | N42: ='MA4 J1'!$AK$506 -> 0 | O42: =SUM(C42:N42) -> 0
A43: Summe | C43: =SUM(C37:C42) -> 0 | D43: =SUM(D37:D42) -> 0 | E43: =SUM(E37:E42) -> 0 | F43: =SUM(F37:F42) -> 0 | G43: =SUM(G37:G42) -> 0 | H43: =SUM(H37:H42) -> 0 | I43: =SUM(I37:I42) -> 0 | J43: =SUM(J37:J42) -> 0 | ... N43: =SUM(N37:N42) -> 0 | O43: =SUM(O40:O42) -> 0
Q45: Wochenarbeitsstunden: 1) | R45: ='Planung Personal'!$U$17 -> 0 | S45: ='Planung Personal'!$V$17 -> 0 | T45: =S45/12 -> 0
A46: ='Planung Personal'!$B$17 -> MA 5 | C46: Jan | D46: Feb | E46: Mrz | F46: Apr | G46: Mai | H46: Jun | I46: Jul | J46: Aug | K46: Sept | L46: Okt | M46: Nov | N46: Dez | O46: ∑ | Q46: Ermittlung des Jahresstundensatzes
A47: Vorhabenbezogen | B47: technisch | C47: ='MA5 J1'!$AK$31 -> 0 | D47: ='MA5 J1'!$AK$74 -> 0 | E47: ='MA5 J1'!$AK$117 -> 0 | F47: ='MA5 J1'!$AK$160 -> 0 | G47: ='MA5 J1'!$AK$203 -> 0 | H47: ='MA5 J1'!$AK$246 -> 0 | I47: ='MA5 J1'!$AK$289 -> 0 | J47: ='MA5 J1'!$AK$332 -> 0 | K47: ='MA5 J1'!$AK$375 -> 0 | L47: ='MA5 J1'!$AK$418 -> 0 | M47: ='MA5 J1'!$AK$461 -> 0 | N47: ='MA5 J1'!$AK$504 -> 0 | O47: =SUM(C47:N47) -> 0
B48: nicht-techn.
A49: Sonstige | C49: ='MA5 J1'!$AK$32 -> 0 | D49: ='MA5 J1'!$AK$75 -> 0 | E49: ='MA5 J1'!$AK$118 -> 0 | F49: ='MA5 J1'!$AK$161 -> 0 | G49: ='MA5 J1'!$AK$204 -> 0 | H49: ='MA5 J1'!$AK$247 -> 0 | I49: ='MA5 J1'!$AK$290 -> 0 | J49: ='MA5 J1'!$AK$333 -> 0 | K49: ='MA5 J1'!$AK$376 -> 0 | L49: ='MA5 J1'!$AK$419 -> 0 | M49: ='MA5 J1'!$AK$462 -> 0 | N49: ='MA5 J1'!$AK$505 -> 0 | O49: =SUM(C49:N49) -> 0 | Q49: Bruttojahres- | R49: Jahresarbeits- | S49: Jahresstd.-
N50: Produktive Gesamtstunden: | O50: =SUM(O47:O49) -> 0 | Q50: lohn/ -gehalt | R50: stunden | S50: satz
A51: Fehlzeiten | C51: =SUM('MA5 J1'!$AK$34:$AK$36) -> 0 | D51: =SUM('MA5 J1'!$AK$77:$AK$79) -> 0 | E51: =SUM('MA5 J1'!$AK$120:$AK$122) -> 0 | F51: =SUM('MA5 J1'!$AK$163:$AK$165) -> 0 | G51: =SUM('MA5 J1'!$AK$206:$AK$208) -> 0 | H51: =SUM('MA5 J1'!$AK$249:$AK$251) -> 0 | I51: =SUM('MA5 J1'!$AK$292:$AK$294) -> 0 | J51: =SUM('MA5 J1'!$AK$335:$AK$337) -> 0 | K51: =SUM('MA5 J1'!$AK$378:$AK$380) -> 0 | L51: =SUM('MA5 J1'!$AK$421:$AK$423) -> 0 | M51: =SUM('MA5 J1'!$AK$464:$AK$466) -> 0 | N51: =SUM('MA5 J1'!$AK$507:$AK$509) -> 0 | O51: =SUM(C51:N51) -> 0 | Q51: ='Planung Personal'!$T$17 -> 0 | R51: ='Planung Personal'!$V$17 -> 0 | S51: ='Planung Personal'!$W$17 -> 0,00 €
A52: Zeitausgleich | C52: ='MA5 J1'!AK$33 -> 0 | D52: ='MA5 J1'!$AK$76 -> 0 | E52: ='MA5 J1'!$AK$119 -> 0 | F52: ='MA5 J1'!$AK$162 -> 0 | G52: ='MA5 J1'!$AK$205 -> 0 | H52: ='MA5 J1'!$AK$248 -> 0 | I52: ='MA5 J1'!$AK$291 -> 0 | J52: ='MA5 J1'!$AK$334 -> 0 | K52: ='MA5 J1'!$AK$377 -> 0 | L52: ='MA5 J1'!$AK$420 -> 0 | M52: ='MA5 J1'!$AK$463 -> 0 | N52: ='MA5 J1'!$AK$506 -> 0 | O52: =SUM(C52:N52) -> 0
A53: Summe | C53: =SUM(C47:C52) -> 0 | D53: =SUM(D47:D52) -> 0 | E53: =SUM(E47:E52) -> 0 | F53: =SUM(F47:F52) -> 0 | G53: =SUM(G47:G52) -> 0 | H53: =SUM(H47:H52) -> 0 | I53: =SUM(I47:I52) -> 0 | J53: =SUM(J47:J52) -> 0 | ... N53: =SUM(N47:N52) -> 0 | O53: =SUM(O50:O52) -> 0

Sheet Auswertung J1
A2: Auswertung Soll-Ist-Personalkosten | C2: =Nav!$H$16 -> 45047
A3: Förderkennzeichen | C3: =Nav!$C$6 -> DS200424
F4: Q1 | J4: Q2 | N4: Q3 | R4: Q4 | T4: Wochenarbeitsstunden: 1) | V4: ='Ermittl.-Stunden J1'!R5 -> 40 | W4: ='Ermittl.-Stunden J1'!S5 -> 2080
A5: ='Ermittl.-Stunden J1'!A6 -> Tippl, Mario | C5: Jan | D5: Feb | E5: Mrz | F5: Summe | G5: Apr | H5: Mai | I5: Jun | J5: Summe | K5: Jul | L5: Aug | M5: Sept | N5: Summe | O5: Okt | P5: Nov | Q5: Dez | R5: Summe | S5: ∑ | U5: Ermittlung des Jahresstundensatzes
A6: Soll / Planung | B6: technisch | C6: ='Planung Personal'!D9*'Auswertung J1'!$W4/12 -> 0 | D6: ='Planung Personal'!E9*'Auswertung J1'!$W4/12 -> 0 | E6: ='Planung Personal'!F9*'Auswertung J1'!$W4/12 -> 0 | F6: =SUM(C6:E6) -> 0 | G6: ='Planung Personal'!G9*'Auswertung J1'!$W4/12 -> 0 | H6: ='Planung Personal'!H9*'Auswertung J1'!$W4/12 -> 0 | I6: ='Planung Personal'!I9*'Auswertung J1'!$W4/12 -> 86.666667 | J6: =SUM(G6:I6) -> 86.666667 | K6: ='Planung Personal'!J9*'Auswertung J1'!$W4/12 -> 86.666667 | L6: ='Planung Personal'!K9*'Auswertung J1'!$W4/12 -> 86.666667 | M6: ='Planung Personal'!L9*'Auswertung J1'!$W4/12 -> 86.666667 | N6: =SUM(K6:M6) -> 260 | O6: ='Planung Personal'!M9*'Auswertung J1'!$W4/12 -> 86.666667 | P6: ='Planung Personal'!N9*'Auswertung J1'!$W4/12 -> 0 | Q6: ='Planung Personal'!O9*'Auswertung J1'!$W4/12 -> 0 | R6: =SUM(O6:Q6) -> 86.666667 | S6: =SUM(R6,N6,J6,F6) -> 433.33333
B7: nicht-techn. | C7: ='Planung Personal'!D10*'Auswertung J1'!$W4/12 -> 0 | D7: ='Planung Personal'!E10*'Auswertung J1'!$W4/12 -> 0 | E7: ='Planung Personal'!F10*'Auswertung J1'!$W4/12 -> 0 | F7: =SUM(C7:E7) -> 0 | G7: ='Planung Personal'!G10*'Auswertung J1'!$W4/12 -> 0 | H7: ='Planung Personal'!H10*'Auswertung J1'!$W4/12 -> 86.666667 | I7: ='Planung Personal'!I10*'Auswertung J1'!$W4/12 -> 0 | J7: =SUM(G7:I7) -> 86.666667 | K7: ='Planung Personal'!J10*'Auswertung J1'!$W4/12 -> 0 | L7: ='Planung Personal'!K10*'Auswertung J1'!$W4/12 -> 0 | M7: ='Planung Personal'!L10*'Auswertung J1'!$W4/12 -> 0 | N7: =SUM(K7:M7) -> 0 | O7: ='Planung Personal'!M10*'Auswertung J1'!$W4/12 -> 0 | P7: ='Planung Personal'!N10*'Auswertung J1'!$W4/12 -> 86.666667 | Q7: ='Planung Personal'!O10*'Auswertung J1'!$W4/12 -> 86.666667 | R7: =SUM(O7:Q7) -> 173.33333 | S7: =SUM(R7,N7,J7,F7) -> 260
A8: Ist / Abrechnung | B8: technisch | C8: ='Ermittl.-Stunden J1'!C7 -> 0 | D8: ='Ermittl.-Stunden J1'!D7 -> 0 | E8: ='Ermittl.-Stunden J1'!E7 -> 0 | F8: =SUM(C8:E8) -> 0 | G8: ='Ermittl.-Stunden J1'!F7 -> 0 | H8: ='Ermittl.-Stunden J1'!G7 -> 0 | I8: ='Ermittl.-Stunden J1'!H7 -> 86.666 | J8: =SUM(G8:I8) -> 86.666 | K8: ='Ermittl.-Stunden J1'!I7 -> 87 | L8: ='Ermittl.-Stunden J1'!J7 -> 91 | M8: ='Ermittl.-Stunden J1'!K7 -> 126 | N8: =SUM(K8:M8) -> 304 | O8: ='Ermittl.-Stunden J1'!L7 -> 88 | P8: ='Ermittl.-Stunden J1'!M7 -> 0 | Q8: ='Ermittl.-Stunden J1'!N7 -> 0 | R8: =SUM(O8:Q8) -> 88 | S8: =SUM(R8,N8,J8,F8) -> 478.666 | U8: Bruttojahres- | V8: Jahresarbeits- | W8: Jahresstd.-
B9: nicht-techn. | C9: ='Ermittl.-Stunden J1'!C8 -> 0 | D9: ='Ermittl.-Stunden J1'!D8 -> 0 | E9: ='Ermittl.-Stunden J1'!E8 -> 0 | F9: =SUM(C9:E9) -> 0 | G9: ='Ermittl.-Stunden J1'!F8 -> 0 | H9: ='Ermittl.-Stunden J1'!G8 -> 86.67 | I9: ='Ermittl.-Stunden J1'!H8 -> 0 | J9: =SUM(G9:I9) -> 86.67 | K9: ='Ermittl.-Stunden J1'!I8 -> 0 | L9: ='Ermittl.-Stunden J1'!J8 -> 0 | M9: ='Ermittl.-Stunden J1'!K8 -> 10 | N9: =SUM(K9:M9) -> 10 | O9: ='Ermittl.-Stunden J1'!L8 -> 20 | P9: ='Ermittl.-Stunden J1'!M8 -> 50 | Q9: ='Ermittl.-Stunden J1'!N8 -> 0 | R9: =SUM(O9:Q9) -> 70 | S9: =SUM(R9,N9,J9,F9) -> 166.67
A10: Differenz Stunden | C10: =C6+C7-C8-C9 -> 0 | D10: =D6+D7-D8-D9 -> 0 | E10: =E6+E7-E8-E9 -> 0 | F10: =SUM(C10:E10) -> 0 | G10: =G6+G7-G8-G9 -> 0 | H10: =H6+H7-H8-H9 -> -0.0033333333 | I10: =I6+I7-I8-I9 -> 0.00066666667 | J10: =SUM(G10:I10) -> -0.0026666667 | K10: =K6+K7-K8-K9 -> -0.33333333 | L10: =L6+L7-L8-L9 -> -4.3333333 | M10: =M6+M7-M8-M9 -> -49.333333 | N10: =SUM(K10:M10) -> -54 | O10: =O6+O7-O8-O9 -> -21.333333 | P10: =P6+P7-P8-P9 -> 36.666667 | Q10: =Q6+Q7-Q8-Q9 -> 86.666667 | R10: =SUM(O10:Q10) -> 102 | S10: =S6+S7-S8-S9 -> 47.997333 | U10: lohn/ -gehalt 1) | V10: stunden | W10: satz
A12: Soll € | B12: technisch | C12: =C6*$W$12 -> 0 | D12: =D6*$W12 -> 0 | E12: =E6*$W12 -> 0 | F12: =SUM(C12:E12) -> 0 | G12: =G6*$W12 -> 0 | H12: =H6*$W12 -> 0 | I12: =I6*$W12 -> 5000 | J12: =SUM(G12:I12) -> 5000 | K12: =K6*$W12 -> 5000 | L12: =L6*$W12 -> 5000 | M12: =M6*$W12 -> 5000 | N12: =SUM(K12:M12) -> 15000 | O12: =O6*$W12 -> 5000 | P12: =P6*$W12 -> 0 | Q12: =Q6*$W12 -> 0 | R12: =SUM(O12:Q12) -> 5000 | S12: =SUM(R12,N12,J12,F12) -> 25000 | U12: ='Ermittl.-Stunden J1'!Q11 -> 120000 | V12: =W4 -> 2080 | W12: =IF(U12=0,"0,00 €", U12/V12) -> 57.692308
B13: nicht-techn. | C13: =C7*$W$12 -> 0 | D13: =D7*$W$12 -> 0 | E13: =E7*$W$12 -> 0 | F13: =SUM(C13:E13) -> 0 | G13: =G7*$W$12 -> 0 | H13: =H7*$W$12 -> 5000 | I13: =I7*$W$12 -> 0 | J13: =SUM(G13:I13) -> 5000 | K13: =K7*$W$12 -> 0 | L13: =L7*$W$12 -> 0 | M13: =M7*$W$12 -> 0 | N13: =SUM(K13:M13) -> 0 | O13: =O7*$W$12 -> 0 | P13: =P7*$W$12 -> 5000 | Q13: =Q7*$W$12 -> 5000 | R13: =SUM(O13:Q13) -> 10000 | S13: =SUM(R13,N13,J13,F13) -> 15000
A14: Ist € | B14: technisch | C14: =C8*$W$12 -> 0 | D14: =D8*$W12 -> 0 | E14: =E8*$W12 -> 0 | F14: =SUM(C14:E14) -> 0 | G14: =G8*$W12 -> 0 | H14: =H8*$W12 -> 0 | I14: =I8*$W12 -> 4999.9615 | J14: =SUM(G14:I14) -> 4999.9615 | K14: =K8*$W12 -> 5019.2308 | L14: =L8*$W12 -> 5250 | M14: =M8*$W12 -> 7269.2308 | N14: =SUM(K14:M14) -> 17538.462 | O14: =O8*$W12 -> 5076.9231 | P14: =P8*$W12 -> 0 | Q14: =Q8*$W12 -> 0 | R14: =SUM(O14:Q14) -> 5076.9231 | S14: =SUM(C14:E14,G14:I14,K14) -> 10019.192
B15: nicht-techn. | C15: =C9*$W$12 -> 0 | D15: =D9*$W$12 -> 0 | E15: =E9*$W$12 -> 0 | F15: =SUM(C15:E15) -> 0 | G15: =G9*$W$12 -> 0 | H15: =H9*$W$12 -> 5000.1923 | I15: =I9*$W$12 -> 0 | J15: =SUM(G15:I15) -> 5000.1923 | K15: =K9*$W$12 -> 0 | L15: =L9*$W$12 -> 0 | M15: =M9*$W$12 -> 576.92308 | N15: =SUM(K15:M15) -> 576.92308 | O15: =O9*$W$12 -> 1153.8462 | P15: =P9*$W$12 -> 2884.6154 | Q15: =Q9*$W$12 -> 0 | R15: =SUM(O15:Q15) -> 4038.4615 | S15: =SUM(R15,N15,J15,F15) -> 9615.5769
A16: Differenz Euro | C16: =C12-C14 -> 0 | D16: =D12-D14 -> 0 | E16: =E12-E14 -> 0 | F16: =SUM(C16:E16) -> 0 | G16: =G12-G14 -> 0 | H16: =H12-H14 -> 0 | I16: =I12-I14 -> 0.038461538 | J16: =SUM(G16:I16) -> 0.038461538 | K16: =K12-K14 -> -19.230769 | L16: =L12-L14 -> -250 | M16: =M12-M14 -> -2269.2308 | N16: =SUM(K16:M16) -> -2538.4615 | O16: =O12-O14 -> -76.923077 | P16: =P12-P14 -> 0 | Q16: =Q12-Q14 -> 0 | R16: =SUM(O16:Q16) -> -76.923077 | S16: =S12+S13-S14-S15 -> 20365.231
F19: Q1 | J19: Q2 | N19: Q3 | R19: Q4 | T19: Wochenarbeitsstunden: 1) | V19: ='Ermittl.-Stunden J1'!R15 -> 40 | W19: ='Ermittl.-Stunden J1'!S15 -> 2080
A20: ='Ermittl.-Stunden J1'!A16 -> Socha, Pawel | C20: Jan | D20: Feb | E20: Mrz | F20: Summe | G20: Apr | H20: Mai | I20: Jun | J20: Summe | K20: Jul | L20: Aug | M20: Sept | N20: Summe | O20: Okt | P20: Nov | Q20: Dez | R20: Summe | S20: ∑ | U20: Ermittlung des Jahresstundensatzes
A21: Soll / Planung | B21: technisch | C21: ='Planung Personal'!D11*'Auswertung J1'!$W19/12 -> 0 | D21: ='Planung Personal'!E11*'Auswertung J1'!$W19/12 -> 0 | E21: ='Planung Personal'!F11*'Auswertung J1'!$W19/12 -> 0 | F21: =SUM(C21:E21) -> 0 | G21: ='Planung Personal'!G11*'Auswertung J1'!$W19/12 -> 0 | H21: ='Planung Personal'!H11*'Auswertung J1'!$W19/12 -> 0 | I21: ='Planung Personal'!I11*'Auswertung J1'!$W19/12 -> 0 | J21: =SUM(G21:I21) -> 0 | K21: ='Planung Personal'!J11*'Auswertung J1'!$W19/12 -> 86.666667 | L21: ='Planung Personal'!K11*'Auswertung J1'!$W19/12 -> 86.666667 | M21: ='Planung Personal'!L11*'Auswertung J1'!$W19/12 -> 0 | N21: =SUM(K21:M21) -> 173.33333 | O21: ='Planung Personal'!M11*'Auswertung J1'!$W19/12 -> 0 | P21: ='Planung Personal'!N11*'Auswertung J1'!$W19/12 -> 0 | Q21: ='Planung Personal'!O11*'Auswertung J1'!$W19/12 -> 0 | R21: =SUM(O21:Q21) -> 0 | S21: =SUM(F21+J21+N21+R21) -> 173.33333
B22: nicht-techn. | C22: ='Planung Personal'!D12*'Auswertung J1'!$W19/12 -> 0 | D22: ='Planung Personal'!E12*'Auswertung J1'!$W19/12 -> 0 | E22: ='Planung Personal'!F12*'Auswertung J1'!$W19/12 -> 0 | F22: =SUM(C22:E22) -> 0 | G22: ='Planung Personal'!G12*'Auswertung J1'!$W19/12 -> 0 | H22: ='Planung Personal'!H12*'Auswertung J1'!$W19/12 -> 86.666667 | I22: ='Planung Personal'!I12*'Auswertung J1'!$W19/12 -> 0 | J22: =SUM(G22:I22) -> 86.666667 | K22: ='Planung Personal'!J12*'Auswertung J1'!$W19/12 -> 0 | L22: ='Planung Personal'!K12*'Auswertung J1'!$W19/12 -> 0 | M22: ='Planung Personal'!L12*'Auswertung J1'!$W19/12 -> 0 | N22: =SUM(K22:M22) -> 0 | O22: ='Planung Personal'!M12*'Auswertung J1'!$W19/12 -> 0 | P22: ='Planung Personal'!N12*'Auswertung J1'!$W19/12 -> 0 | Q22: ='Planung Personal'!O12*'Auswertung J1'!$W19/12 -> 0 | R22: =SUM(O22:Q22) -> 0 | S22: =SUM(F22+J22+N22+R22) -> 86.666667
A23: Ist / Abrechnung | B23: technisch | C23: ='Ermittl.-Stunden J1'!C17 -> 0 | D23: ='Ermittl.-Stunden J1'!D17 -> 0 | E23: ='Ermittl.-Stunden J1'!E17 -> 0 | F23: =SUM(C23:E23) -> 0 | G23: ='Ermittl.-Stunden J1'!F17 -> 0 | H23: ='Ermittl.-Stunden J1'!G17 -> 0 | I23: ='Ermittl.-Stunden J1'!H17 -> 158 | J23: =SUM(G23:I23) -> 158 | K23: ='Ermittl.-Stunden J1'!I17 -> 148 | L23: ='Ermittl.-Stunden J1'!J17 -> 92 | M23: ='Ermittl.-Stunden J1'!K17 -> 40 | N23: =SUM(K23:M23) -> 280 | O23: ='Ermittl.-Stunden J1'!L17 -> 20 | P23: ='Ermittl.-Stunden J1'!M17 -> 0 | Q23: ='Ermittl.-Stunden J1'!N17 -> 0 | R23: =SUM(O23:Q23) -> 20 | S23: =SUM(F23+J23+N23+R23) -> 458 | U23: Bruttojahres- | V23: Jahresarbeits- | W23: Jahresstd.-
B24: nicht-techn. | C24: ='Ermittl.-Stunden J1'!C18 -> 0 | D24: ='Ermittl.-Stunden J1'!D18 -> 0 | E24: ='Ermittl.-Stunden J1'!E18 -> 0 | F24: =SUM(C24:E24) -> 0 | G24: ='Ermittl.-Stunden J1'!F18 -> 0 | H24: ='Ermittl.-Stunden J1'!G18 -> 86.67 | I24: ='Ermittl.-Stunden J1'!H18 -> 0 | J24: =SUM(G24:I24) -> 86.67 | K24: ='Ermittl.-Stunden J1'!I18 -> 0 | L24: ='Ermittl.-Stunden J1'!J18 -> 0 | M24: ='Ermittl.-Stunden J1'!K18 -> 0 | N24: =SUM(K24:M24) -> 0 | O24: ='Ermittl.-Stunden J1'!L18 -> 0 | P24: ='Ermittl.-Stunden J1'!M18 -> 7.5 | Q24: ='Ermittl.-Stunden J1'!N18 -> 0 | R24: =SUM(O24:Q24) -> 7.5 | S24: =SUM(F24+J24+N24+R24) -> 94.17
A25: Differenz Stunden | C25: =C21-C23 -> 0 | D25: =D21-D23 -> 0 | E25: =E21-E23 -> 0 | F25: =SUM(C25:E25) -> 0 | G25: =G21-G23 -> 0 | H25: =H21-H23 -> 0 | I25: =I21-I23 -> -158 | J25: =SUM(G25:I25) -> -158 | K25: =K21-K23 -> -61.333333 | L25: =L21-L23 -> -5.3333333 | M25: =M21-M23 -> -40 | N25: =SUM(K25:M25) -> -106.66667 | O25: =O21-O23 -> -20 | P25: =P21-P23 -> 0 | Q25: =Q21-Q23 -> 0 | R25: =SUM(O25:Q25) -> -20 | S25: =S21+S22-S23-S24 -> -292.17 | U25: lohn/ -gehalt 1) | V25: stunden | W25: satz
U26: ='Ermittl.-Stunden J1'!Q21 -> 38700 | V26: =W19 -> 2080 | W26: =IF(U26=0,"0,00 €", U26/V26) -> 18.605769
A27: Soll € | B27: technisch | C27: =C21*$W26 -> 0 | D27: =D21*$W26 -> 0 | E27: =E21*$W26 -> 0 | F27: =SUM(C27:E27) -> 0 | G27: =G21*$W26 -> 0 | H27: =H21*$W26 -> 0 | I27: =I21*$W26 -> 0 | J27: =SUM(G27:I27) -> 0 | K27: =K21*$W26 -> 1612.5 | L27: =L21*$W26 -> 1612.5 | M27: =M21*$W26 -> 0 | N27: =SUM(K27:M27) -> 3225 | O27: =O21*$W26 -> 0 | P27: =P21*$W26 -> 0 | Q27: =Q21*$W26 -> 0 | R27: =SUM(O27:Q27) -> 0 | S27: =SUM(R27,N27,J27,F27) -> 3225
B28: nicht-techn. | C28: =C22*$W26 -> 0 | D28: =D22*$W26 -> 0 | E28: =E22*$W26 -> 0 | F28: =SUM(C28:E28) -> 0 | G28: =G22*$W26 -> 0 | H28: =H22*$W26 -> 1612.5 | I28: =I22*$W26 -> 0 | J28: =SUM(G28:I28) -> 1612.5 | K28: =K22*$W26 -> 0 | L28: =L22*$W26 -> 0 | M28: =M22*$W26 -> 0 | N28: =SUM(K28:M28) -> 0 | O28: =O22*$W26 -> 0 | P28: =P22*$W26 -> 0 | Q28: =Q22*$W26 -> 0 | R28: =SUM(O28:Q28) -> 0 | S28: =SUM(R28,N28,J28,F28) -> 1612.5
A29: Ist € | B29: technisch | C29: =C23*$W26 -> 0 | D29: =D23*$W26 -> 0 | E29: =E23*$W26 -> 0 | F29: =SUM(C29:E29) -> 0 | G29: =G23*$W26 -> 0 | H29: =H23*$W26 -> 0 | I29: =I23*$W26 -> 2939.7115 | J29: =SUM(G29:I29) -> 2939.7115 | K29: =K23*$W26 -> 2753.6538 | L29: =L23*$W26 -> 1711.7308 | M29: =M23*$W26 -> 744.23077 | N29: =SUM(K29:M29) -> 5209.6154 | O29: =O23*$W26 -> 372.11538 | P29: =P23*$W26 -> 0 | Q29: =Q23*$W26 -> 0 | R29: =SUM(O29:Q29) -> 372.11538 | S29: =SUM(R29,N29,J29,F29) -> 8521.4423
B30: nicht-techn. | C30: =C24*$W26 -> 0 | D30: =D24*$W26 -> 0 | E30: =E24*$W26 -> 0 | F30: =SUM(C30:E30) -> 0 | G30: =G24*$W26 -> 0 | H30: =H24*$W26 -> 1612.562 | I30: =I24*$W26 -> 0 | J30: =SUM(G30:I30) -> 1612.562 | K30: =K24*$W26 -> 0 | L30: =L24*$W26 -> 0 | M30: =M24*$W26 -> 0 | N30: =SUM(K30:M30) -> 0 | O30: =O24*$W26 -> 0 | P30: =P24*$W26 -> 139.54327 | Q30: =Q24*$W26 -> 0 | R30: =SUM(O30:Q30) -> 139.54327 | S30: =SUM(R30,N30,J30,F30) -> 1752.1053
A31: Differenz Gesamtkosten Euro | C31: =C27-C29 -> 0 | D31: =D27-D29 -> 0 | E31: =E27-E29 -> 0 | F31: =SUM(C31:E31) -> 0 | G31: =G27-G29 -> 0 | H31: =H27-H29 -> 0 | I31: =I27-I29 -> -2939.7115 | J31: =SUM(G31:I31) -> -2939.7115 | K31: =K27-K29 -> -1141.1538 | L31: =L27-L29 -> -99.230769 | M31: =M27-M29 -> -744.23077 | N31: =SUM(K31:M31) -> -1984.6154 | O31: =O27-O29 -> -372.11538 | P31: =P27-P29 -> 0 | Q31: =Q27-Q29 -> 0 | R31: =SUM(O31:Q31) -> -372.11538 | S31: =S27+S28-S29-S30 -> -5436.0476
F34: Q1 | J34: Q2 | N34: Q3 | R34: Q4 | T34: Wochenarbeitsstunden: 1) | V34: ='Ermittl.-Stunden J1'!R25 -> 20 | W34: ='Ermittl.-Stunden J1'!S25 -> 1040
A35: ='Ermittl.-Stunden J1'!A26 -> Tippl, Karen | C35: Jan | D35: Feb | E35: Mrz | F35: Summe | G35: Apr | H35: Mai | I35: Jun | J35: Summe | K35: Jul | L35: Aug | M35: Sept | N35: Summe | O35: Okt | P35: Nov | Q35: Dez | R35: Summe | S35: ∑ | U35: Ermittlung des Jahresstundensatzes
A36: Soll / Planung | B36: technisch | C36: ='Planung Personal'!D13*'Auswertung J1'!$W34/12 -> 0 | D36: ='Planung Personal'!E13*'Auswertung J1'!$W34/12 -> 0 | E36: ='Planung Personal'!F13*'Auswertung J1'!$W34/12 -> 0 | F36: =SUM(C36:E36) -> 0 | G36: ='Planung Personal'!G13*'Auswertung J1'!$W34/12 -> 0 | H36: ='Planung Personal'!H13*'Auswertung J1'!$W34/12 -> 0 | I36: ='Planung Personal'!I13*'Auswertung J1'!$W34/12 -> 43.333333 | J36: =SUM(G36:I36) -> 43.333333 | K36: ='Planung Personal'!J13*'Auswertung J1'!$W34/12 -> 43.333333 | L36: ='Planung Personal'!K13*'Auswertung J1'!$W34/12 -> 43.333333 | M36: ='Planung Personal'!L13*'Auswertung J1'!$W34/12 -> 43.333333 | N36: =SUM(K36:M36) -> 130 | O36: ='Planung Personal'!M13*'Auswertung J1'!$W34/12 -> 43.333333 | P36: ='Planung Personal'!N13*'Auswertung J1'!$W34/12 -> 0 | Q36: ='Planung Personal'!O13*'Auswertung J1'!$W34/12 -> 0 | R36: =SUM(O36:Q36) -> 43.333333 | S36: =SUM(F36+J36+N36+R36) -> 216.66667
B37: nicht-techn. | C37: ='Planung Personal'!D14*'Auswertung J1'!$W34/12 -> 0 | D37: ='Planung Personal'!E14*'Auswertung J1'!$W34/12 -> 0 | E37: ='Planung Personal'!F14*'Auswertung J1'!$W34/12 -> 0 | F37: =SUM(C37:E37) -> 0 | G37: ='Planung Personal'!G14*'Auswertung J1'!$W34/12 -> 0 | H37: ='Planung Personal'!H14*'Auswertung J1'!$W34/12 -> 0 | I37: ='Planung Personal'!I14*'Auswertung J1'!$W34/12 -> 0 | J37: =SUM(G37:I37) -> 0 | K37: ='Planung Personal'!J14*'Auswertung J1'!$W34/12 -> 0 | L37: ='Planung Personal'!K14*'Auswertung J1'!$W34/12 -> 0 | M37: ='Planung Personal'!L14*'Auswertung J1'!$W34/12 -> 0 | N37: =SUM(K37:M37) -> 0 | O37: ='Planung Personal'!M14*'Auswertung J1'!$W34/12 -> 0 | P37: ='Planung Personal'!N14*'Auswertung J1'!$W34/12 -> 0 | Q37: ='Planung Personal'!O14*'Auswertung J1'!$W34/12 -> 0 | R37: =SUM(O37:Q37) -> 0 | S37: =SUM(F37+J37+N37+R37) -> 0
A38: Ist / Abrechnung | B38: technisch | C38: ='Ermittl.-Stunden J1'!C27 -> 0 | D38: ='Ermittl.-Stunden J1'!D27 -> 0 | E38: ='Ermittl.-Stunden J1'!E27 -> 0 | F38: =SUM(C38:E38) -> 0 | G38: ='Ermittl.-Stunden J1'!F27 -> 0 | H38: ='Ermittl.-Stunden J1'!G27 -> 0 | I38: ='Ermittl.-Stunden J1'!H27 -> 53.33 | J38: =SUM(G38:I38) -> 53.33 | K38: ='Ermittl.-Stunden J1'!I27 -> 72 | L38: ='Ermittl.-Stunden J1'!J27 -> 48 | M38: ='Ermittl.-Stunden J1'!K27 -> 80 | N38: =SUM(K38:M38) -> 200 | O38: ='Ermittl.-Stunden J1'!L27 -> 20 | P38: ='Ermittl.-Stunden J1'!M27 -> 0 | Q38: ='Ermittl.-Stunden J1'!N27 -> 0 | R38: =SUM(O38:Q38) -> 20 | S38: =SUM(F38+J38+N38+R38) -> 273.33 | U38: Bruttojahres- | V38: Jahresarbeits- | W38: Jahresstd.-
B39: nicht-techn. | C39: ='Ermittl.-Stunden J1'!C28 -> 0 | D39: ='Ermittl.-Stunden J1'!D28 -> 0 | E39: ='Ermittl.-Stunden J1'!E28 -> 0 | F39: =SUM(C39:E39) -> 0 | G39: ='Ermittl.-Stunden J1'!F28 -> 0 | H39: ='Ermittl.-Stunden J1'!G28 -> 64 | I39: ='Ermittl.-Stunden J1'!H28 -> 22.67 | J39: =SUM(G39:I39) -> 86.67 | K39: ='Ermittl.-Stunden J1'!I28 -> 0 | L39: ='Ermittl.-Stunden J1'!J28 -> 0 | M39: ='Ermittl.-Stunden J1'!K28 -> 0 | N39: =SUM(K39:M39) -> 0 | O39: ='Ermittl.-Stunden J1'!L28 -> 0 | P39: ='Ermittl.-Stunden J1'!M28 -> 0 | Q39: ='Ermittl.-Stunden J1'!N28 -> 0 | R39: =SUM(O39:Q39) -> 0 | S39: =SUM(F39+J39+N39+R39) -> 86.67
A40: Differenz Stunden | C40: =C36+C37-C38-C39 -> 0 | D40: =D36+D37-D38-D39 -> 0 | E40: =E36+E37-E38-E39 -> 0 | F40: =SUM(C40:E40) -> 0 | G40: =G36+G37-G38-G39 -> 0 | H40: =H36+H37-H38-H39 -> -64 | I40: =I36+I37-I38-I39 -> -32.666667 | J40: =SUM(G40:I40) -> -96.666667 | K40: =K36+K37-K38-K39 -> -28.666667 | L40: =L36+L37-L38-L39 -> -4.6666667 | M40: =M36+M37-M38-M39 -> -36.666667 | N40: =SUM(K40:M40) -> -70 | O40: =O36+O37-O38-O39 -> 23.333333 | P40: =P36+P37-P38-P39 -> 0 | Q40: =Q36+Q37-Q38-Q39 -> 0 | R40: =SUM(O40:Q40) -> 23.333333 | S40: =S36+S37-S38-S39 -> -143.33333 | U40: lohn/ -gehalt 1) | V40: stunden | W40: satz
U41: ='Ermittl.-Stunden J1'!Q31 -> 35700 | V41: =W34 -> 1040 | W41: =IF(U41=0,"0,00 €", U41/V41) -> 34.326923
A42: Soll € | B42: technisch | C42: =C36*$W41 -> 0 | D42: =D36*$W41 -> 0 | E42: =E36*$W41 -> 0 | F42: =SUM(C42:E42) -> 0 | G42: =G36*$W41 -> 0 | H42: =H36*$W41 -> 0 | I42: =I36*$W41 -> 1487.5 | J42: =SUM(G42:I42) -> 1487.5 | K42: =K36*$W41 -> 1487.5 | L42: =L36*$W41 -> 1487.5 | M42: =M36*$W41 -> 1487.5 | N42: =SUM(K42:M42) -> 4462.5 | O42: =O36*$W41 -> 1487.5 | P42: =P36*$W41 -> 0 | Q42: =Q36*$W41 -> 0 | R42: =SUM(O42:Q42) -> 1487.5 | S42: =SUM(R42,N42,J42,F42) -> 7437.5
B43: nicht-techn. | C43: =C37*$W41 -> 0 | D43: =D37*$W41 -> 0 | E43: =E37*$W41 -> 0 | F43: =SUM(C43:E43) -> 0 | G43: =G37*$W41 -> 0 | H43: =H37*$W41 -> 0 | I43: =I37*$W41 -> 0 | J43: =SUM(G43:I43) -> 0 | K43: =K37*$W41 -> 0 | L43: =L37*$W41 -> 0 | M43: =M37*$W41 -> 0 | N43: =SUM(K43:M43) -> 0 | O43: =O37*$W41 -> 0 | P43: =P37*$W41 -> 0 | Q43: =Q37*$W41 -> 0 | R43: =SUM(O43:Q43) -> 0 | S43: =SUM(R43,N43,J43,F43) -> 0
A44: Ist € | B44: technisch | C44: =C38*$W41 -> 0 | D44: =D38*$W41 -> 0 | E44: =E38*$W41 -> 0 | F44: =SUM(C44:E44) -> 0 | G44: =G38*$W41 -> 0 | H44: =H38*$W41 -> 0 | I44: =I38*$W41 -> 1830.6548 | J44: =SUM(G44:I44) -> 1830.6548 | K44: =K38*$W41 -> 2471.5385 | L44: =L38*$W41 -> 1647.6923 | M44: =M38*$W41 -> 2746.1538 | N44: =SUM(K44:M44) -> 6865.3846 | O44: =O38*$W41 -> 686.53846 | P44: =P38*$W41 -> 0 | Q44: =Q38*$W41 -> 0 | R44: =SUM(O44:Q44) -> 686.53846 | S44: =SUM(R44,N44,J44,F44) -> 9382.5779
B45: nicht-techn. | C45: =C39*$W41 -> 0 | D45: =D39*$W41 -> 0 | E45: =E39*$W41 -> 0 | F45: =SUM(C45:E45) -> 0 | G45: =G39*$W41 -> 0 | H45: =H39*$W41 -> 2196.9231 | I45: =I39*$W41 -> 778.19135 | J45: =SUM(G45:I45) -> 2975.1144 | K45: =K39*$W41 -> 0 | L45: =L39*$W41 -> 0 | M45: =M39*$W41 -> 0 | N45: =SUM(K45:M45) -> 0 | O45: =O39*$W41 -> 0 | P45: =P39*$W41 -> 0 | Q45: =Q39*$W41 -> 0 | R45: =SUM(O45:Q45) -> 0 | S45: =SUM(R45,N45,J45,F45) -> 2975.1144
A46: Differenz Euro | C46: =C42+C43-C44-C45 -> 0 | D46: =D42+D43-D44-D45 -> 0 | E46: =E42+E43-E44-E45 -> 0 | F46: =SUM(C46:E46) -> 0 | G46: =G42+G43-G44-G45 -> 0 | H46: =H42+H43-H44-H45 -> -2196.9231 | I46: =I42+I43-I44-I45 -> -1121.3462 | J46: =SUM(G46:I46) -> -3318.2692 | K46: =K42+K43-K44-K45 -> -984.03846 | L46: =L42+L43-L44-L45 -> -160.19231 | M46: =M42+M43-M44-M45 -> -1258.6538 | N46: =SUM(K46:M46) -> -2402.8846 | O46: =O42+O43-O44-O45 -> 800.96154 | P46: =P42+P43-P44-P45 -> 0 | Q46: =Q42+Q43-Q44-Q45 -> 0 | R46: =SUM(O46:Q46) -> 800.96154 | S46: =S42+S43-S44-S45 -> -4920.1923
F49: Q1 | J49: Q2 | N49: Q3 | R49: Q4 | T49: Wochenarbeitsstunden: 1) | V49: ='Ermittl.-Stunden J1'!R35 -> 0 | W49: ='Ermittl.-Stunden J1'!S35 -> 0
A50: ='Ermittl.-Stunden J1'!A36 -> MA 4 | C50: Jan | D50: Feb | E50: Mrz | F50: Summe | G50: Apr | H50: Mai | I50: Jun | J50: Summe | K50: Jul | L50: Aug | M50: Sept | N50: Summe | O50: Okt | P50: Nov | Q50: Dez | R50: Summe | S50: ∑ | U50: Ermittlung des Jahresstundensatzes
A51: Soll / Planung | B51: technisch | C51: ='Planung Personal'!D15*'Auswertung J1'!$W49/12 -> 0 | D51: ='Planung Personal'!E15*'Auswertung J1'!$W49/12 -> 0 | E51: ='Planung Personal'!F15*'Auswertung J1'!$W49/12 -> 0 | F51: =SUM(C51:E51) -> 0 | G51: ='Planung Personal'!G15*'Auswertung J1'!$W49/12 -> 0 | H51: ='Planung Personal'!H15*'Auswertung J1'!$W49/12 -> 0 | I51: ='Planung Personal'!I15*'Auswertung J1'!$W49/12 -> 0 | J51: =SUM(G51:I51) -> 0 | K51: ='Planung Personal'!J15*'Auswertung J1'!$W49/12 -> 0 | L51: ='Planung Personal'!K15*'Auswertung J1'!$W49/12 -> 0 | M51: ='Planung Personal'!L15*'Auswertung J1'!$W49/12 -> 0 | N51: =SUM(K51:M51) -> 0 | O51: ='Planung Personal'!M15*'Auswertung J1'!$W49/12 -> 0 | P51: ='Planung Personal'!N15*'Auswertung J1'!$W49/12 -> 0 | Q51: ='Planung Personal'!O45*'Auswertung J1'!$W49/12 -> 0 | R51: =SUM(O51:Q51) -> 0 | S51: =SUM(F51+J51+N51+R51) -> 0
B52: nicht-techn. | C52: ='Planung Personal'!D16*'Auswertung J1'!$W49/12 -> 0 | D52: ='Planung Personal'!E16*'Auswertung J1'!$W49/12 -> 0 | E52: ='Planung Personal'!F16*'Auswertung J1'!$W49/12 -> 0 | F52: =SUM(C52:E52) -> 0 | G52: ='Planung Personal'!G16*'Auswertung J1'!$W49/12 -> 0 | H52: ='Planung Personal'!H16*'Auswertung J1'!$W49/12 -> 0 | I52: ='Planung Personal'!I16*'Auswertung J1'!$W49/12 -> 0 | J52: =SUM(G52:I52) -> 0 | K52: ='Planung Personal'!J16*'Auswertung J1'!$W49/12 -> 0 | L52: ='Planung Personal'!K16*'Auswertung J1'!$W49/12 -> 0 | M52: ='Planung Personal'!L16*'Auswertung J1'!$W49/12 -> 0 | N52: =SUM(K52:M52) -> 0 | O52: ='Planung Personal'!M16*'Auswertung J1'!$W49/12 -> 0 | P52: ='Planung Personal'!N16*'Auswertung J1'!$W49/12 -> 0 | Q52: ='Planung Personal'!O16*'Auswertung J1'!$W49/12 -> 0 | R52: =SUM(O52:Q52) -> 0 | S52: =SUM(F52+J52+N52+R52) -> 0
A53: Ist / Abrechnung | B53: technisch | C53: ='Ermittl.-Stunden J1'!C37 -> 0 | D53: ='Ermittl.-Stunden J1'!D37 -> 0 | E53: ='Ermittl.-Stunden J1'!E37 -> 0 | F53: =SUM(C53:E53) -> 0 | G53: ='Ermittl.-Stunden J1'!F37 -> 0 | H53: ='Ermittl.-Stunden J1'!G37 -> 0 | I53: ='Ermittl.-Stunden J1'!H37 -> 0 | J53: =SUM(G53:I53) -> 0 | K53: ='Ermittl.-Stunden J1'!I37 -> 0 | L53: ='Ermittl.-Stunden J1'!J37 -> 0 | M53: ='Ermittl.-Stunden J1'!K37 -> 0 | N53: =SUM(K53:M53) -> 0 | O53: ='Ermittl.-Stunden J1'!L37 -> 0 | P53: ='Ermittl.-Stunden J1'!M37 -> 0 | Q53: ='Ermittl.-Stunden J1'!N37 -> 0 | R53: =SUM(O53:Q53) -> 0 | S53: =SUM(F53+J53+N53+R53) -> 0 | U53: Bruttojahres- | V53: Jahresarbeits- | W53: Jahresstd.-
B54: nicht-techn. | C54: ='Ermittl.-Stunden J1'!C38 -> 0 | D54: ='Ermittl.-Stunden J1'!D38 -> 0 | E54: ='Ermittl.-Stunden J1'!E38 -> 0 | F54: =SUM(C54:E54) -> 0 | G54: ='Ermittl.-Stunden J1'!F38 -> 0 | H54: ='Ermittl.-Stunden J1'!G38 -> 0 | I54: ='Ermittl.-Stunden J1'!H38 -> 0 | J54: =SUM(G54:I54) -> 0 | K54: ='Ermittl.-Stunden J1'!I38 -> 0 | L54: ='Ermittl.-Stunden J1'!J38 -> 0 | M54: ='Ermittl.-Stunden J1'!K38 -> 0 | N54: =SUM(K54:M54) -> 0 | O54: ='Ermittl.-Stunden J1'!L38 -> 0 | P54: ='Ermittl.-Stunden J1'!M38 -> 0 | Q54: ='Ermittl.-Stunden J1'!N38 -> 0 | R54: =SUM(O54:Q54) -> 0 | S54: =SUM(F54+J54+N54+R54) -> 0
A55: Differenz Stunden | C55: =C51-C53 -> 0 | D55: =D51-D53 -> 0 | E55: =E51-E53 -> 0 | F55: =SUM(C55:E55) -> 0 | G55: =G51-G53 -> 0 | H55: =H51-H53 -> 0 | I55: =I51-I53 -> 0 | J55: =SUM(G55:I55) -> 0 | K55: =K51-K53 -> 0 | L55: =L51-L53 -> 0 | M55: =M51-M53 -> 0 | N55: =SUM(K55:M55) -> 0 | O55: =O51-O53 -> 0 | P55: =P51-P53 -> 0 | Q55: =Q51-Q53 -> 0 | R55: =SUM(O55:Q55) -> 0 | S55: =S51+S52-S53-S54 -> 0 | U55: lohn/ -gehalt 1) | V55: stunden | W55: satz
U56: ='Ermittl.-Stunden J1'!Q41 -> 0 | V56: =W49 -> 0 | W56: =IF(U56=0,"0,00 €", U56/V56) -> 0,00 €
A57: Soll € | B57: technisch | C57: =C51*$W56 -> 0 | D57: =D51*$W56 -> 0 | E57: =E51*$W56 -> 0 | F57: =SUM(C57:E57) -> 0 | G57: =G51*$W56 -> 0 | H57: =H51*$W56 -> 0 | I57: =I51*$W56 -> 0 | J57: =SUM(G57:I57) -> 0 | K57: =K51*$W56 -> 0 | L57: =L51*$W56 -> 0 | M57: =M51*$W56 -> 0 | N57: =SUM(K57:M57) -> 0 | O57: =O51*$W56 -> 0 | P57: =P51*$W56 -> 0 | Q57: =Q51*$W56 -> 0 | R57: =SUM(O57:Q57) -> 0 | S57: =SUM(R57,N57,J57,F57) -> 0
B58: nicht-techn.
A59: Ist € | B59: technisch | C59: =C53*$W56 -> 0 | D59: =D53*$W56 -> 0 | E59: =E53*$W56 -> 0 | F59: =SUM(C59:E59) -> 0 | G59: =G53*$W56 -> 0 | H59: =H53*$W56 -> 0 | I59: =I53*$W56 -> 0 | J59: =SUM(G59:I59) -> 0 | K59: =K53*$W56 -> 0 | L59: =L53*$W56 -> 0 | M59: =M53*$W56 -> 0 | N59: =SUM(K59:M59) -> 0 | O59: =O53*$W56 -> 0 | P59: =P53*$W56 -> 0 | Q59: =Q53*$W56 -> 0 | R59: =SUM(O59:Q59) -> 0 | S59: =SUM(R59,N59,J59,F59) -> 0
B60: nicht-techn.
A61: Differenz Euro | C61: =C57-C59 -> 0 | D61: =D57-D59 -> 0 | E61: =E57-E59 -> 0 | F61: =SUM(C61:E61) -> 0 | G61: =G57-G59 -> 0 | H61: =H57-H59 -> 0 | I61: =I57-I59 -> 0 | J61: =SUM(G61:I61) -> 0 | K61: =K57-K59 -> 0 | L61: =L57-L59 -> 0 | M61: =M57-M59 -> 0 | N61: =SUM(K61:M61) -> 0 | O61: =O57-O59 -> 0 | P61: =P57-P59 -> 0 | Q61: =Q57-Q59 -> 0 | R61: =SUM(O61:Q61) -> 0 | S61: =SUM(R61,N61,J61,F61) -> 0
F64: Q1 | J64: Q2 | N64: Q3 | R64: Q4 | T64: Wochenarbeitsstunden: 1) | V64: ='Ermittl.-Stunden J1'!R45 -> 0 | W64: ='Ermittl.-Stunden J1'!S45 -> 0
A65: ='Ermittl.-Stunden J1'!A46 -> MA 5 | C65: Jan | D65: Feb | E65: Mrz | F65: Summe | G65: Apr | H65: Mai | I65: Jun | J65: Summe | K65: Jul | L65: Aug | M65: Sept | N65: Summe | O65: Okt | P65: Nov | Q65: Dez | R65: Summe | S65: ∑ | U65: Ermittlung des Jahresstundensatzes
A66: Soll / Planung | B66: technisch | C66: ='Planung Personal'!D17*'Auswertung J1'!$W64/12 -> 0 | D66: ='Planung Personal'!E17*'Auswertung J1'!$W64/12 -> 0 | E66: ='Planung Personal'!F17*'Auswertung J1'!$W64/12 -> 0 | F66: =SUM(C66:E66) -> 0 | G66: ='Planung Personal'!G17*'Auswertung J1'!$W64/12 -> 0 | H66: ='Planung Personal'!H17*'Auswertung J1'!$W64/12 -> 0 | I66: ='Planung Personal'!I17*'Auswertung J1'!$W64/12 -> 0 | J66: =SUM(G66:I66) -> 0 | K66: ='Planung Personal'!J17*'Auswertung J1'!$W64/12 -> 0 | L66: ='Planung Personal'!K17*'Auswertung J1'!$W64/12 -> 0 | M66: ='Planung Personal'!L17*'Auswertung J1'!$W64/12 -> 0 | N66: =SUM(K66:M66) -> 0 | O66: ='Planung Personal'!M17*'Auswertung J1'!$W64/12 -> 0 | P66: ='Planung Personal'!N17*'Auswertung J1'!$W64/12 -> 0 | Q66: ='Planung Personal'!O17*'Auswertung J1'!$W64/12 -> 0 | R66: =SUM(O66:Q66) -> 0 | S66: =SUM(F66+J66+N66+R66) -> 0
B67: nicht-techn. | C67: ='Planung Personal'!D18*'Auswertung J1'!$W64/12 -> 0 | D67: ='Planung Personal'!E18*'Auswertung J1'!$W64/12 -> 0 | E67: ='Planung Personal'!F18*'Auswertung J1'!$W64/12 -> 0 | F67: =SUM(C67:E67) -> 0 | G67: ='Planung Personal'!G18*'Auswertung J1'!$W64/12 -> 0 | H67: ='Planung Personal'!H18*'Auswertung J1'!$W64/12 -> 0 | I67: ='Planung Personal'!I18*'Auswertung J1'!$W64/12 -> 0 | J67: =SUM(G67:I67) -> 0 | K67: ='Planung Personal'!J18*'Auswertung J1'!$W64/12 -> 0 | L67: ='Planung Personal'!K18*'Auswertung J1'!$W64/12 -> 0 | M67: ='Planung Personal'!L18*'Auswertung J1'!$W64/12 -> 0 | N67: =SUM(K67:M67) -> 0 | O67: ='Planung Personal'!M18*'Auswertung J1'!$W64/12 -> 0 | P67: ='Planung Personal'!N18*'Auswertung J1'!$W64/12 -> 0 | Q67: ='Planung Personal'!O18*'Auswertung J1'!$W64/12 -> 0 | R67: =SUM(O67:Q67) -> 0
A68: Ist / Abrechnung | B68: technisch | C68: ='Ermittl.-Stunden J1'!C47 -> 0 | D68: ='Ermittl.-Stunden J1'!D47 -> 0 | E68: ='Ermittl.-Stunden J1'!E47 -> 0 | F68: =SUM(C68:E68) -> 0 | G68: ='Ermittl.-Stunden J1'!F47 -> 0 | H68: ='Ermittl.-Stunden J1'!G47 -> 0 | I68: ='Ermittl.-Stunden J1'!H47 -> 0 | J68: =SUM(G68:I68) -> 0 | K68: ='Ermittl.-Stunden J1'!I47 -> 0 | L68: ='Ermittl.-Stunden J1'!J47 -> 0 | M68: ='Ermittl.-Stunden J1'!K47 -> 0 | N68: =SUM(K68:M68) -> 0 | O68: ='Ermittl.-Stunden J1'!L47 -> 0 | P68: ='Ermittl.-Stunden J1'!M47 -> 0 | Q68: ='Ermittl.-Stunden J1'!N47 -> 0 | R68: =SUM(O68:Q68) -> 0 | S68: =SUM(F68+J68+N68+R68) -> 0 | U68: Bruttojahres- | V68: Jahresarbeits- | W68: Jahresstd.-
B69: nicht-techn. | F69: =SUM(C69:E69) -> 0 | J69: =SUM(G69:I69) -> 0 | N69: =SUM(K69:M69) -> 0 | R69: =SUM(O69:Q69) -> 0
A70: Differenz Stunden | C70: =C66-C68 -> 0 | D70: =D66-D68 -> 0 | E70: =E66-E68 -> 0 | F70: =SUM(C70:E70) -> 0 | G70: =G66-G68 -> 0 | H70: =H66-H68 -> 0 | I70: =I66-I68 -> 0 | J70: =SUM(G70:I70) -> 0 | K70: =K66-K68 -> 0 | L70: =L66-L68 -> 0 | M70: =M66-M68 -> 0 | N70: =SUM(K70:M70) -> 0 | O70: =O66-O68 -> 0 | P70: =P66-P68 -> 0 | Q70: =Q66-Q68 -> 0 | R70: =SUM(O70:Q70) -> 0 | S70: =SUM(F70+J70+N70+R70) -> 0 | U70: lohn/ -gehalt 1) | V70: stunden | W70: satz
U71: ='Ermittl.-Stunden J1'!Q51 -> 0 | V71: =W64 -> 0 | W71: =IF(U71=0,"0,00 €", U71/V71) -> 0,00 €
A72: Soll € | B72: technisch | C72: =C66*$W71 -> 0 | D72: =D66*$W71 -> 0 | E72: =E66*$W71 -> 0 | F72: =SUM(C72:E72) -> 0 | G72: =G66*$W71 -> 0 | H72: =H66*$W71 -> 0 | I72: =I66*$W71 -> 0 | J72: =SUM(G72:I72) -> 0 | K72: =K66*$W71 -> 0 | L72: =L66*$W71 -> 0 | M72: =M66*$W71 -> 0 | N72: =SUM(K72:M72) -> 0 | O72: =O66*$W71 -> 0 | P72: =P66*$W71 -> 0 | Q72: =Q66*$W71 -> 0 | R72: =SUM(O72:Q72) -> 0 | S72: =SUM(R72,N72,J72,F72) -> 0
B73: nicht-techn.
A74: Ist € | B74: technisch | C74: =C68*$W71 -> 0 | D74: =D68*$W71 -> 0 | E74: =E68*$W71 -> 0 | F74: =SUM(C74:E74) -> 0 | G74: =G68*$W71 -> 0 | H74: =H68*$W71 -> 0 | I74: =I68*$W71 -> 0 | J74: =SUM(G74:I74) -> 0 | K74: =K68*$W71 -> 0 | L74: =L68*$W71 -> 0 | M74: =M68*$W71 -> 0 | N74: =SUM(K74:M74) -> 0 | O74: =O68*$W71 -> 0 | P74: =P68*$W71 -> 0 | Q74: =Q68*$W71 -> 0 | R74: =SUM(O74:Q74) -> 0 | S74: =SUM(R74,N74,J74,F74) -> 0
B75: nicht-techn.
A76: Differenz Euro | C76: =C72-C74 -> 0 | D76: =D72-D74 -> 0 | E76: =E72-E74 -> 0 | F76: =SUM(C76:E76) -> 0 | G76: =G72-G74 -> 0 | H76: =H72-H74 -> 0 | I76: =I72-I74 -> 0 | J76: =SUM(G76:I76) -> 0 | K76: =K72-K74 -> 0 | L76: =L72-L74 -> 0 | M76: =M72-M74 -> 0 | N76: =SUM(K76:M76) -> 0 | O76: =O72-O74 -> 0 | P76: =P72-P74 -> 0 | Q76: =Q72-Q74 -> 0 | R76: =SUM(O76:Q76) -> 0 | S76: =SUM(R76,N76,J76,F76) -> 0
F78: Q1 | J78: Q2 | N78: Q3 | R78: Q4
A79: Kosten | C79: =DATE(YEAR($C$2),1,1) -> 44927 | D79: =EOMONTH(C79,1) -> 44985 | E79: =EOMONTH(D79,1) -> 45016 | F79: Summe | G79: =EOMONTH(E79,1) -> 45046 | H79: =EOMONTH(G79,1) -> 45077 | I79: =EOMONTH(H79,1) -> 45107 | J79: Summe | K79: =EOMONTH(I79,1) -> 45138 | L79: =EOMONTH(K79,1) -> 45169 | M79: =EOMONTH(L79,1) -> 45199 | N79: Summe | O79: =EOMONTH(M79,1) -> 45230 | P79: =EOMONTH(O79,1) -> 45260 | Q79: =EOMONTH(P79,1) -> 45291 | R79: Summe | S79: ∑
A80: Summe PLAN | B80: technisch | C80: =C12+C27+C42+C57+C72 -> 0 | D80: =D12+D27+D42+D57+D72 -> 0 | E80: =E12+E27+E42+E57+E72 -> 0 | F80: =SUM(C80:E80) -> 0 | G80: =G12+G27+G42+G57+G72 -> 0 | H80: =H12+H27+H42+H57+H72 -> 0 | I80: =I12+I27+I42+I57+I72 -> 6487.5 | J80: =SUM(G80:I80) -> 6487.5 | K80: =K12+K27+K42+K57+K72 -> 8100 | L80: =L12+L27+L42+L57+L72 -> 8100 | M80: =M12+M27+M42+M57+M72 -> 6487.5 | N80: =SUM(K80:M80) -> 22687.5 | O80: =O12+O27+O42+O57+O72 -> 6487.5 | P80: =P12+P27+P42+P57+P72 -> 0 | Q80: =Q12+Q27+Q42+Q57+Q72 -> 0 | R80: =SUM(O80:Q80) -> 6487.5 | S80: =F80+J80+N80+R80 -> 35662.5
B81: nicht-techn. | C81: =C13+C28+C43+C58+C73 -> 0 | D81: =D13+D28+D43+D58+D73 -> 0 | E81: =E13+E28+E43+E58+E73 -> 0 | F81: =SUM(C81:E81) -> 0 | G81: =G13+G28+G43+G58+G73 -> 0 | H81: =H13+H28+H43+H58+H73 -> 6612.5 | I81: =I13+I28+I43+I58+I73 -> 0 | J81: =SUM(G81:I81) -> 6612.5 | K81: =K13+K28+K43+K58+K73 -> 0 | L81: =L13+L28+L43+L58+L73 -> 0 | M81: =M13+M28+M43+M58+M73 -> 0 | N81: =SUM(K81:M81) -> 0 | O81: =O13+O28+O43+O58+O73 -> 0 | P81: =P13+P28+P43+P58+P73 -> 5000 | Q81: =Q13+Q28+Q43+Q58+Q73 -> 5000 | R81: =SUM(O81:Q81) -> 10000 | S81: =F81+J81+N81+R81 -> 16612.5
A82: Gesamt PLAN | C82: =SUM(C80:C81) -> 0 | D82: =SUM(D80:D81) -> 0 | E82: =SUM(E80:E81) -> 0 | F82: =SUM(F80:F81) -> 0 | G82: =SUM(G80:G81) -> 0 | H82: =SUM(H80:H81) -> 6612.5 | I82: =SUM(I80:I81) -> 6487.5 | J82: =SUM(J80:J81) -> 13100 | ... S82: =SUM(S80:S81) -> 52275
A83: Summe IST | B83: technisch | C83: =C14+C29+C44+C59+C74 -> 0 | D83: =D14+D29+D44+D59+D74 -> 0 | E83: =E14+E29+E44+E59+E74 -> 0 | F83: =SUM(C83:E83) -> 0 | G83: =G14+G29+G44+G59+G74 -> 0 | H83: =H14+H29+H44+H59+H74 -> 0 | I83: =I14+I29+I44+I59+I74 -> 9770.3279 | J83: =SUM(G83:I83) -> 9770.3279 | K83: =K14+K29+K44+K59+K74 -> 10244.423 | L83: =L14+L29+L44+L59+L74 -> 8609.4231 | M83: =M14+M29+M44+M59+M74 -> 10759.615 | N83: =SUM(K83:M83) -> 29613.462 | O83: =O14+O29+O44+O59+O74 -> 6135.5769 | P83: =P14+P29+P44+P59+P74 -> 0 | Q83: =Q14+Q29+Q44+Q59+Q74 -> 0 | R83: =SUM(O83:Q83) -> 6135.5769 | S83: =F83+J83+N83+R83 -> 45519.366
B84: nicht-techn. | C84: =C15+C30+C45+C60+C75 -> 0 | D84: =D15+D30+D45+D60+D75 -> 0 | E84: =E15+E30+E45+E60+E75 -> 0 | F84: =SUM(C84:E84) -> 0 | G84: =G15+G30+G45+G60+G75 -> 0 | H84: =H15+H30+H45+H60+H75 -> 8809.6774 | I84: =I15+I30+I45+I60+I75 -> 778.19135 | J84: =SUM(G84:I84) -> 9587.8688 | K84: =K15+K30+K45+K60+K75 -> 0 | L84: =L15+L30+L45+L60+L75 -> 0 | M84: =M15+M30+M45+M60+M75 -> 576.92308 | N84: =SUM(K84:M84) -> 576.92308 | O84: =O15+O30+O45+O60+O75 -> 1153.8462 | P84: =P15+P30+P45+P60+P75 -> 3024.1587 | Q84: =Q15+Q30+Q45+Q60+Q75 -> 0 | R84: =SUM(O84:Q84) -> 4178.0048 | S84: =F84+J84+N84+R84 -> 14342.797
A85: Gesamt IST | C85: =SUM(C83:C84) -> 0 | D85: =SUM(D83:D84) -> 0 | E85: =SUM(E83:E84) -> 0 | F85: =SUM(C85:E85) -> 0 | G85: =SUM(G83:G84) -> 0 | H85: =SUM(H83:H84) -> 8809.6774 | I85: =SUM(I83:I84) -> 10548.519 | J85: =SUM(G85:I85) -> 19358.197 | K85: =SUM(K83:K84) -> 10244.423 | L85: =SUM(L83:L84) -> 8609.4231 | M85: =SUM(M83:M84) -> 11336.538 | N85: =SUM(K85:M85) -> 30190.385 | O85: =SUM(O83:O84) -> 7289.4231 | P85: =SUM(P83:P84) -> 3024.1587 | Q85: =SUM(Q83:Q84) -> 0 | R85: =SUM(O85:Q85) -> 10313.582 | S85: =SUM(S83:S84) -> 59862.163
A86: Differenz | C86: =C82-C85 -> 0 | D86: =D82-D85 -> 0 | E86: =E82-E85 -> 0 | F86: =SUM(C86:E86) -> 0 | G86: =G82-G85 -> 0 | H86: =H82-H85 -> -2197.1774 | I86: =I82-I85 -> -4061.0192 | J86: =SUM(G86:I86) -> -6258.1966 | K86: =K82-K85 -> -2144.4231 | L86: =L82-L85 -> -509.42308 | M86: =M82-M85 -> -4849.0385 | N86: =SUM(K86:M86) -> -7502.8846 | O86: =O82-O85 -> -801.92308 | P86: =P82-P85 -> 1975.8413 | Q86: =Q82-Q85 -> 5000 | R86: =SUM(O86:Q86) -> 6173.9183 | S86: =S82-S85 -> -7587.163
F88: Q1 | J88: Q2 | N88: Q3 | R88: Q4
A89: Förderung | C89: =DATE(YEAR($C$2),1,1) -> 44927 | D89: =EOMONTH(C89,1) -> 44985 | E89: =EOMONTH(D89,1) -> 45016 | F89: Summe | G89: =EOMONTH(E89,1) -> 45046 | H89: =EOMONTH(G89,1) -> 45077 | I89: =EOMONTH(H89,1) -> 45107 | J89: Summe | K89: =EOMONTH(I89,1) -> 45138 | L89: =EOMONTH(K89,1) -> 45169 | M89: =EOMONTH(L89,1) -> 45199 | N89: Summe | O89: =EOMONTH(M89,1) -> 45230 | P89: =EOMONTH(O89,1) -> 45260 | Q89: =EOMONTH(P89,1) -> 45291 | R89: Summe | S89: ∑
A90: Soll Förderung | B90: technisch | C90: =C80*(1+Nav!$M$12)*Nav!$K$6 -> 0 | D90: =D80*(1+Nav!$M$12)*Nav!$K$6 -> 0 | E90: =E80*(1+Nav!$M$12)*Nav!$K$6 -> 0 | F90: =SUM(C90:E90) -> 0 | G90: =G80*(1+Nav!$M$12)*Nav!$K$6 -> 0 | H90: =H80*(1+Nav!$M$12)*Nav!$K$6 -> 0 | I90: =I80*(1+Nav!$M$12)*Nav!$K$6 -> 5831.8732 | J90: =SUM(G90:I90) -> 5831.8732 | K90: =K80*(1+Nav!$M$12)*Nav!$K$6 -> 7281.414 | L90: =L80*(1+Nav!$M$12)*Nav!$K$6 -> 7281.414 | M90: =M80*(1+Nav!$M$12)*Nav!$K$6 -> 5831.8732 | N90: =SUM(K90:M90) -> 20394.701 | O90: =O80*(1+Nav!$M$12)*Nav!$K$6 -> 5831.8732 | P90: =P80*(1+Nav!$M$12)*Nav!$K$6 -> 0 | Q90: =Q80*(1+Nav!$M$12)*Nav!$K$6 -> 0 | R90: =SUM(O90:Q90) -> 5831.8732 | S90: =F90+J90+N90+R90 -> 32058.448
B91: nicht-techn. | C91: =C81*(1+Nav!$M$13)*Nav!$K$6 -> 0 | D91: =D81*(1+Nav!$M$13)*Nav!$K$6 -> 0 | E91: =E81*(1+Nav!$M$13)*Nav!$K$6 -> 0 | F91: =SUM(C91:E91) -> 0 | G91: =G81*(1+Nav!$M$13)*Nav!$K$6 -> 0 | H91: =H81*(1+Nav!$M$13)*Nav!$K$6 -> 6011.8205 | I91: =I81*(1+Nav!$M$13)*Nav!$K$6 -> 0 | J91: =SUM(G91:I91) -> 6011.8205 | K91: =K81*(1+Nav!$M$13)*Nav!$K$6 -> 0 | L91: =L81*(1+Nav!$M$13)*Nav!$K$6 -> 0 | M91: =M81*(1+Nav!$M$13)*Nav!$K$6 -> 0 | N91: =SUM(K91:M91) -> 0 | O91: =O81*(1+Nav!$M$13)*Nav!$K$6 -> 0 | P91: =P81*(1+Nav!$M$13)*Nav!$K$6 -> 4545.8 | Q91: =Q81*(1+Nav!$M$13)*Nav!$K$6 -> 4545.8 | R91: =SUM(O91:Q91) -> 9091.6 | S91: =F91+J91+N91+R91 -> 15103.42
A92: Gesamt SOLL Förderung | C92: =SUM(C90:C91) -> 0 | D92: =SUM(D90:D91) -> 0 | E92: =SUM(E90:E91) -> 0 | F92: =SUM(C92:E92) -> 0 | G92: =SUM(G90:G91) -> 0 | H92: =SUM(H90:H91) -> 6011.8205 | I92: =SUM(I90:I91) -> 5831.8732 | J92: =SUM(G92:I92) -> 11843.694 | K92: =SUM(K90:K91) -> 7281.414 | L92: =SUM(L90:L91) -> 7281.414 | M92: =SUM(M90:M91) -> 5831.8732 | N92: =SUM(K92:M92) -> 20394.701 | O92: =SUM(O90:O91) -> 5831.8732 | P92: =SUM(P90:P91) -> 4545.8 | Q92: =SUM(Q90:Q91) -> 4545.8 | R92: =SUM(O92:Q92) -> 14923.473 | S92: =SUM(S90:S91) -> 47161.868
A93: Ist Förderung | B93: technisch | C93: =C83*(1+Nav!$M$12)*Nav!$K$6 -> 0 | D93: =D83*(1+Nav!$M$12)*Nav!$K$6 -> 0 | E93: =E83*(1+Nav!$M$12)*Nav!$K$6 -> 0 | F93: =SUM(C93:E93) -> 0 | G93: =G83*(1+Nav!$M$12)*Nav!$K$6 -> 0 | H93: =H83*(1+Nav!$M$12)*Nav!$K$6 -> 0 | I93: =I83*(1+Nav!$M$12)*Nav!$K$6 -> 8782.9385 | J93: =SUM(G93:I93) -> 8782.9385 | K93: =K83*(1+Nav!$M$12)*Nav!$K$6 -> 9209.1217 | L93: =L83*(1+Nav!$M$12)*Nav!$K$6 -> 7739.3548 | M93: =M83*(1+Nav!$M$12)*Nav!$K$6 -> 9672.2487 | N93: =SUM(K93:M93) -> 26620.725 | O93: =O83*(1+Nav!$M$12)*Nav!$K$6 -> 5515.5155 | P93: =P83*(1+Nav!$M$12)*Nav!$K$6 -> 0 | Q93: =Q83*(1+Nav!$M$12)*Nav!$K$6 -> 0 | R93: =SUM(O93:Q93) -> 5515.5155 | S93: =F93+J93+N93+R93 -> 40919.179
B94: nicht-techn. | C94: =C84*(1+Nav!$M$13)*Nav!$K$6 -> 0 | D94: =D84*(1+Nav!$M$13)*Nav!$K$6 -> 0 | E94: =E84*(1+Nav!$M$13)*Nav!$K$6 -> 0 | F94: =SUM(C94:E94) -> 0 | G94: =G84*(1+Nav!$M$13)*Nav!$K$6 -> 0 | H94: =H84*(1+Nav!$M$13)*Nav!$K$6 -> 8009.4063 | I94: =I84*(1+Nav!$M$13)*Nav!$K$6 -> 707.50044 | J94: =SUM(G94:I94) -> 8716.9068 | K94: =K84*(1+Nav!$M$13)*Nav!$K$6 -> 0 | L94: =L84*(1+Nav!$M$13)*Nav!$K$6 -> 0 | M94: =M84*(1+Nav!$M$13)*Nav!$K$6 -> 524.51538 | N94: =SUM(K94:M94) -> 524.51538 | O94: =O84*(1+Nav!$M$13)*Nav!$K$6 -> 1049.0308 | P94: =P84*(1+Nav!$M$13)*Nav!$K$6 -> 2749.4441 | Q94: =Q84*(1+Nav!$M$13)*Nav!$K$6 -> 0 | R94: =SUM(O94:Q94) -> 3798.4749 | S94: =F94+J94+N94+R94 -> 13039.897
A95: Gesamt IST Förderung | C95: =SUM(C93:C94) -> 0 | D95: =SUM(D93:D94) -> 0 | E95: =SUM(E93:E94) -> 0 | F95: =SUM(C95:E95) -> 0 | G95: =SUM(G93:G94) -> 0 | H95: =SUM(H93:H94) -> 8009.4063 | I95: =SUM(I93:I94) -> 9490.439 | J95: =SUM(G95:I95) -> 17499.845 | K95: =SUM(K93:K94) -> 9209.1217 | L95: =SUM(L93:L94) -> 7739.3548 | M95: =SUM(M93:M94) -> 10196.764 | N95: =SUM(K95:M95) -> 27145.24 | O95: =SUM(O93:O94) -> 6564.5463 | P95: =SUM(P93:P94) -> 2749.4441 | Q95: =SUM(Q93:Q94) -> 0 | R95: =SUM(O95:Q95) -> 9313.9904 | S95: =SUM(S93:S94) -> 53959.076
A96: Differnz Förderung | C96: =C92-C95 -> 0 | D96: =D92-D95 -> 0 | E96: =E92-E95 -> 0 | F96: =F92-F95 -> 0 | G96: =G92-G95 -> 0 | H96: =H92-H95 -> -1997.5858 | I96: =I92-I95 -> -3658.5657 | J96: =J92-J95 -> -5656.1516 | ... S96: =S92-S95 -> -6797.2079
F98: Q1 | J98: Q2 | N98: Q3 | R98: Q4
A99: Zahlung PT | C99: Jan | D99: Feb | E99: Mrz | F99: Summe | G99: Apr | H99: Mai | I99: Jun | J99: Summe | K99: Jul | L99: Aug | M99: Sept | N99: Summe | O99: Okt | P99: Nov | Q99: Dez | R99: Summe | S99: ∑
A100: Datum
A101: Betrag | S101: =SUM(C101:E101,G101:I101,K101:M101,O101:Q101) -> 0
A102: Abweichung zu IST | C102: =C101-C95 -> 0 | D102: =D101-D95 -> 0 | E102: =E101-E95 -> 0 | F102: =SUM(C102:E102) -> 0 | G102: =G101-G95 -> 0 | H102: =H101-H95 -> -8009.4063 | I102: =I101-I95 -> -9490.439 | J102: =SUM(G102:I102) -> -17499.845 | K102: =K101-K95 -> -9209.1217 | L102: =L101-L95 -> -7739.3548 | M102: =M101-M95 -> -10196.764 | N102: =SUM(K102:M102) -> -27145.24 | O102: =O101-O95 -> -6564.5463 | P102: =P101-P95 -> -2749.4441 | Q102: =Q101-Q95 -> 0 | R102: =SUM(O102:Q102) -> -9313.9904 | S102: =SUM(F102,J102,N102,R102) -> -53959.076

Sheet ZA Übersicht
D4: ZA1 | G4: ZA2 | J4: ZA3 | M4: ZA4
D5: 45047 | E5: bis | F5: 45138 | G5: 45139 | H5: bis | I5: 45199 | J5: 45200 | K5: bis | L5: 45230 | M5: 45231 | N5: bis | O5: 45291
D6: zuwendungsfähige Kosten | E6: Fördersatz | F6: angeforderte Zuwendung | G6: zuwendungsfähige Kosten | H6: Fördersatz | I6: angeforderte Zuwendung | J6: zuwendungsfähige Kosten | K6: Fördersatz | L6: angeforderte Zuwendung | M6: zuwendungsfähige Kosten | N6: Fördersatz | O6: angeforderte Zuwendung
B7: Personal technisch | C7: 0.2842 | D7: 20016.26 | E7: 0.7 | F7: =D7*$E$7 -> 14011.382 | G7: 19508.81 | H7: 0.7 | I7: =G7*$H$7 -> 13656.167 | J7: 6135.52 | K7: 0.7 | L7: =J7*$K$7 -> 4294.864 | N7: 0.7 | O7: =M7*$H$7 -> 0 | P7: =D7+G7+J7+M7 -> 45660.59
B8: Zuschlag für übrige Kosten | D8: =D7*$C$7 -> 5688.6211 | F8: =D8*$E$7 -> 3982.0348 | G8: =G7*$C$7 -> 5544.4038 | I8: =G8*$H$7 -> 3881.0827 | J8: =J7*$C$7 -> 1743.7148 | L8: =J8*$H$7 -> 1220.6003 | M8: =M7*$C$7 -> 0 | O8: =M8*$N$7 -> 0
B9: Kosten Aufträge an Dritte | D9: 0 | F9: =D9*$E$7 -> 0 | G9: 0 | I9: =G9*$H$7 -> 0 | J9: 0 | L9: =J9*$H$7 -> 0 | M9: 0 | O9: =M9*$H$7 -> 0
B10: personal nichttechnisch | C10: 0.2988 | D10: 9588.3 | E10: 0.7 | F10: =D10*$E$10 -> 6711.81 | G10: 576.9 | H10: 0.7 | I10: =G10*$H$10 -> 403.83 | J10: 1153.8 | K10: 0.7 | L10: =J10*$K$10 -> 807.66 | M10: 2769.12 | N10: 0.7 | O10: =M10*$N$10 -> 1938.384 | P10: =D10+G10+J10+M10 -> 14088.12
B11: Zuschlag für übrige Kosten | D11: =D10*$C$10 -> 2864.984 | F11: =D11*$E$10 -> 2005.4888 | G11: =G10*$C$10 -> 172.37772 | I11: =G11*$H$10 -> 120.6644 | J11: =J10*$C$10 -> 344.75544 | L11: =J11*$H$10 -> 241.32881 | M11: =M10*$C$10 -> 827.41306 | O11: =M11*$H$10 -> 579.18914
B12: Kosten der Aufträge an Dritte | D12: 0 | F12: =D12*$E$10 -> 0 | G12: 0 | I12: =G12*$H$10 -> 0 | J12: 0 | L12: =J12*$H$10 -> 0 | M12: 0 | O12: =M12*$H$10 -> 0
B13: Summe technisch | D13: =SUM(D7:D9) -> 25704.881 | F13: =SUM(F7:F9) -> 17993.417 | G13: =SUM(G7:G9) -> 25053.214 | I13: =SUM(I7:I9) -> 17537.25 | J13: =SUM(J7:J9) -> 7879.2348 | L13: =SUM(L7:L9) -> 5515.4643 | M13: =SUM(M7:M9) -> 0 | O13: =SUM(O7:O9) -> 0
B14: Summe nichttechnisch | D14: =SUM(D10:D12) -> 12453.284 | F14: =SUM(F10:F12) -> 8717.2988 | G14: =SUM(G10:G12) -> 749.27772 | I14: =SUM(I10:I12) -> 524.4944 | J14: =SUM(J10:J12) -> 1498.5554 | L14: =SUM(L10:L12) -> 1048.9888 | M14: =SUM(M10:M12) -> 3596.5331 | O14: =SUM(O10:O12) -> 2517.5731
B15: Summe | D15: =SUM(D13:D14) -> 38158.165 | F15: =SUM(F13:F14) -> 26710.716 | G15: =SUM(G13:G14) -> 25802.492 | I15: =SUM(I13:I14) -> 18061.744 | J15: =SUM(J13:J14) -> 9377.7902 | L15: =SUM(L13:L14) -> 6564.4532 | M15: =SUM(M13:M14) -> 3596.5331 | O15: =SUM(O13:O14) -> 2517.5731 | P15: =D15+G15+J15+M15 -> 76934.98 | Q15: =P15*0.7 -> 53854.486
Q16: =P15-Q15 -> 23080.494
F17: Auszahlung | G17: Differenz
B18: Summe angef. Zuwendungen | C18: ZA1 | D18: =F15 -> 26710.716 | E18: Mai-Jul | F18: 20197 | G18: =D18-F18 -> 6513.7156
C19: ZA2 | D19: =I15 -> 18061.744 | E19: Aug-Sept. | G19: =D19-F19 -> 18061.744
C20: ZA3 | D20: =L15 -> 6564.4532 | E20: Okt. | F20: 24450 | G20: =D20-F20 -> -17885.547
C21: ZA 4 | D21: =O15 -> 2517.5731 | E21: 45253 | F21: 2743 | G21: =D21-F21 -> -225.42686
D22: =SUM(D18:D21) -> 53854.486 | F22: =SUM(F18:F21) -> 47390 | G22: =SUM(G18:G21) -> 6464.486
C23: Gesperrt | F23: =D30*0.1 -> 5385.5 | H23: =F23+F21 -> 8128.5
F24: =SUM(F22:F23) -> 52775.5
F25: =F24-Q15 -> -1078.986 | G25: =F23-F25 -> 6464.486
B28: Zuwendung Bescheid | C28: 2023 | D28: 20197 | E28: 2023 | F28: 26711
C29: 2024 | D29: 33658 | F29: 18062
D30: =SUM(D28:D29) -> 53855 | F30: 6564
E31: 2024 | F31: 2518
F32: =SUM(F28:F31) -> 53855
E33: Einbehalt | F33: =F32*0.1 -> 5385.5
B36: ÄB | C36: 2023 | D36: 48470
C37: 2024 | D37: 5385
D38: =SUM(D36:D37) -> 53855
B41: zahlungen | C41: 45142 | D41: 20197
C42: 45212 | D42: 24450
C43: 45253 | D43: 2743
D44: =SUM(D41:D43) -> 47390 | E44: 53854.486 | F44: =E44-D44 -> 6464.486

Sheet MA1 J2
V2: Förderkennzeichen: | AA2: =Nav!$C$6 -> DS200424
N4: Stundennachweis
N5: Fördermodul Netzwerkprojekte des Bundesministeriums für Wirtschaft und Energie (BMWi)
A6: Zuwendungsempfänger (Firmenstempel) | N6: Der Stundennachweis verbleibt beim Zuwendungsempfänger und ist nur nach Aufforderung vorzulegen.
A7: Vorhabenthema
A8: =Nav!$C$3 -> Durchführbarkeitsstudie "BioInk"
A10: Monat | M10: Mitarbeiter(in): [Name, Vorname]
A11: =Nav!$P$4 | M11: ='Planung Personal'!$B$9 -> Tippl, Mario
A13: Die zu Lasten des Vorhabens abzurechnenden Personalstunden sind täglich eigenhändig von der betreffenden Person zu erfassen. Nur die produktiven, für das Vorhaben geleisteten Stunden sind zuwendungsfähig.
E15: Arbeitszeiten in Stunden je Kalendertag: | AJ15: Summe Monat
A16: lfd. Nr. | D16: V | E16: =A11 | F16: =E16+1 -> #VALUE! | G16: =F16+1 -> #VALUE! | H16: =G16+1 -> #VALUE! | I16: =H16+1 -> #VALUE! | J16: =I16+1 -> #VALUE! | K16: =J16+1 -> #VALUE! | L16: =K16+1 -> #VALUE! | M16: =L16+1 -> #VALUE! | ... AI16: =AH16+1 -> #VALUE!
A17: 1. | B17: AP | C17: förderbare Projektarbeiten (1)
B18: Nr. | C18: Kurzbezeichnung des Arbeitspakets
C19: =VLOOKUP(B19,'AP Übersicht'!$A$8:$B$36,2,FALSE) -> #N/A | AJ19: =SUM(E19:AI19) -> 0
C20: =VLOOKUP(B20,'AP Übersicht'!$A$8:$B$36,2,FALSE) -> #N/A | AJ20: =SUM(E20:AI20) -> 0
C21: =VLOOKUP(B21,'AP Übersicht'!$A$8:$B$36,2,FALSE) -> #N/A | AJ21: =SUM(E21:AI21) -> 0
C22: =VLOOKUP(B22,'AP Übersicht'!$A$8:$B$36,2,FALSE) -> #N/A | AJ22: =SUM(E22:AI22) -> 0
C23: =VLOOKUP(B23,'AP Übersicht'!$A$8:$B$36,2,FALSE) -> #N/A | AJ23: =SUM(E23:AI23) -> 0
C24: =VLOOKUP(B24,'AP Übersicht'!$A$8:$B$36,2,FALSE) -> #N/A | AJ24: =SUM(E24:AI24) -> 0
C25: =VLOOKUP(B25,'AP Übersicht'!$A$8:$B$36,2,FALSE) -> #N/A | AJ25: =SUM(E25:AI25) -> 0
C26: =VLOOKUP(B26,'AP Übersicht'!$A$8:$B$36,2,FALSE) -> #N/A | AJ26: =SUM(E26:AI26) -> 0
C27: =VLOOKUP(B27,'AP Übersicht'!$A$8:$B$36,2,FALSE) -> #N/A | AJ27: =SUM(E27:AI27) -> 0
C28: =VLOOKUP(B28,'AP Übersicht'!$A$8:$B$36,2,FALSE) -> #N/A | AJ28: =SUM(E28:AI28) -> 0
C29: =VLOOKUP(B29,'AP Übersicht'!$A$8:$B$36,2,FALSE) -> #N/A | AJ29: =SUM(E29:AI29) -> 0
C30: =VLOOKUP(B30,'AP Übersicht'!$A$8:$B$36,2,FALSE) -> #N/A | AJ30: =SUM(E30:AI30) -> 0
C31: Summe der förderbaren Stunden | E31: =SUM(E17:E30) -> 0 | F31: =SUM(F17:F30) -> 0 | G31: =SUM(G17:G30) -> 0 | H31: =SUM(H17:H30) -> 0 | I31: =SUM(I17:I30) -> 0 | J31: =SUM(J17:J30) -> 0 | K31: =SUM(K17:K30) -> 0 | L31: =SUM(L17:L30) -> 0 | ... AI31: =SUM(AI17:AI30) -> 0 | AJ31: =SUM(AJ19:AJ30) -> 0
A32: 2. | C32: Nicht zuschussfähige Arbeiten | AJ32: =SUM(E32:AI32) -> 0
A33: 3. | C33: Zeitausgleich | AJ33: =SUM(D33:AI33) -> 0
C34: Urlaub (nur bezahlten Urlaub aufführen) | AJ34: =SUM(E34:AI34) -> 0
C35: Krankheit (nur bei Lohn- und Gehaltsfortzahlung) | AJ35: =SUM(E35:AI35) -> 0
C36: Sonstige bezahlte Ausfallzeiten (z. B. Feiertage) | AJ36: =SUM(E36:AI36) -> 0
AJ37: =SUM(AJ31:AJ36) -> 0
A38: (1) Die geleisteten Bearbeitungsstunden sind für den gesamten Bewilligungszeitraum eigenhändig und zeitnah, d. h. mindestens innerhalb einer Woche zu erfassen. Die Angaben sind subventionserheblich im Sinne des § 264 Strafgesetzbuch.
P40: Datum / Unterschrift des Mitarbeiters
A41: (2) Förderbar pro Monat sind die tatsächlich für das Projekt geleisteten Stunden, jedoch nicht mehr als arbeitsvertraglich, betrieblich oder tariflich vereinbart, maximal in Höhe von 52 (Wochen) / 12 (Monate) x Wochenarbeitszeit. Überstunden sind nicht förderbar.
P42: Datum / Unterschrift Geschäftsführer bzw. FuE-Verantwortlicher (in öffentlichen Forschungseinrichtungen)
V45: Förderkennzeichen: | AA45: =Nav!$C$6 -> DS200424
N47: Stundennachweis
N48: Fördermodul Netzwerkprojekte des Bundesministeriums für Wirtschaft und Energie (BMWi)
A49: Zuwendungsempfänger (Firmenstempel) | N49: Der Stundennachweis verbleibt beim Zuwendungsempfänger und ist nur nach Aufforderung vorzulegen.
A50: Vorhabenthema
A51: =Nav!$C$3 -> Durchführbarkeitsstudie "BioInk"
A53: Monat | M53: Mitarbeiter(in): [Name, Vorname]
A54: =A11+31 -> #VALUE! | M54: =M11 -> Tippl, Mario
A56: Die zu Lasten des Vorhabens abzurechnenden Personalstunden sind täglich eigenhändig von der betreffenden Person zu erfassen. Nur die produktiven, für das Vorhaben geleisteten Stunden sind zuwendungsfähig.
E58: Arbeitszeiten in Stunden je Kalendertag: | AJ58: Summe Monat
A59: lfd. Nr. | D59: V | E59: =A54 -> #VALUE! | F59: =E59+1 -> #VALUE! | G59: =F59+1 -> #VALUE! | H59: =G59+1 -> #VALUE! | I59: =H59+1 -> #VALUE! | J59: =I59+1 -> #VALUE! | K59: =J59+1 -> #VALUE! | L59: =K59+1 -> #VALUE! | M59: =L59+1 -> #VALUE! | ... AF59: =AE59+1 -> #VALUE! | AG59: =IF(AND(DAY(DATE(YEAR($A$11),3,0))=29,YEAR($A$11)<>1900),29,"") -> #VALUE!
A60: 1. | B60: AP | C60: förderbare Projektarbeiten (1)
B61: Nr. | C61: Kurzbezeichnung des Arbeitspakets
C62: =VLOOKUP(B62,'AP Übersicht'!$A$8:$B$36,2,FALSE) -> #N/A | AJ62: =SUM(E62:AI62) -> 0
C63: =VLOOKUP(B63,'AP Übersicht'!$A$8:$B$36,2,FALSE) -> #N/A | AJ63: =SUM(E63:AI63) -> 0
C64: =VLOOKUP(B64,'AP Übersicht'!$A$8:$B$36,2,FALSE) -> #N/A | AJ64: =SUM(E64:AI64) -> 0
C65: =VLOOKUP(B65,'AP Übersicht'!$A$8:$B$36,2,FALSE) -> #N/A | AJ65: =SUM(E65:AI65) -> 0
C66: =VLOOKUP(B66,'AP Übersicht'!$A$8:$B$36,2,FALSE) -> #N/A | AJ66: =SUM(E66:AI66) -> 0
C67: =VLOOKUP(B67,'AP Übersicht'!$A$8:$B$36,2,FALSE) -> #N/A | AJ67: =SUM(E67:AI67) -> 0
C68: =VLOOKUP(B68,'AP Übersicht'!$A$8:$B$36,2,FALSE) -> #N/A | AJ68: =SUM(E68:AI68) -> 0
C69: =VLOOKUP(B69,'AP Übersicht'!$A$8:$B$36,2,FALSE) -> #N/A | AJ69: =SUM(E69:AI69) -> 0
C70: =VLOOKUP(B70,'AP Übersicht'!$A$8:$B$36,2,FALSE) -> #N/A | AJ70: =SUM(E70:AI70) -> 0
C71: =VLOOKUP(B71,'AP Übersicht'!$A$8:$B$36,2,FALSE) -> #N/A | AJ71: =SUM(E71:AI71) -> 0
